Workbook

Sheet survey
A1: GeoPoll Submission Form
A2: FAO - Household Questionnaire | P2: Additional notes
A3: Q # | B3: Q Name | C3: Suggested Qname | D3: English | E3: Length | F3: Arabic | G3: Length | H3: Q Type | I3: Randomize | J3: Conditional | K3: Programming Instructions | L3: Skip Pattern | M3: Codes | N3: Default skip patterns & conditional | O3: Specify skip pattern variable (from blue text) | Q3: Estimated percentage of repondents | T3: Mandatory | X3: Duration (sec) | Y3: Weighted duration | Z3: Core questions only
A4: A. PRESENTATION OF THE SURVEY AND ELIGIBILITY CRITERIA SELECTION | T4: no | Y4: =IF(X4="","",X4*V4) | Z4: =IF(T4="yes",Y4,"")
A5: NA | B5: Optin | D5: Optin | E5: =LEN(D5) | F5: Optin | G5: =LEN(F5) | H5: Open Ended | I5: NA | J5: NA | K5: Form Type - TextBox | L5: Any Response = phone_number | M5: NA | N5: NA | T5: no | X5: 0 | Y5: =IF(X5="","",X5*Q5)
A6: NA | B6: phone_number | C6: phone_number | D6: Input the phone number that you are contacting: | E6: =LEN(D6) | F6: أدخل رقم الهاتف الذي تتصل به: | G6: =LEN(F6) | H6: Open Ended | I6: NA | J6: NA | K6: Form Type - TextBox | L6: Any Response = calldispo | M6: NA | N6: NA | T6: yes | X6: 0 | Y6: =IF(X6="","",X6*Q6) | Z6: 0
A7: NA | B7: calldispo | C7: calldispo | D7: Phone number: #CATI_MOBILENUMBER# 1)Someone answers 2)Answering machine 3)No answer 4)Hang up or refusal 5)Call back 6)Under review 7)Disconnected | E7: =LEN(D7) | F7: رقم الهاتف: #CATI_MOBILENUMBER# 1) يجيب شخص ما 2) جهاز الرد الالي 3) لا جواب 4) إنهاء المكالمة أو الرفض 5) معاودة الاتصال 6) قيد المراجعة 7) قطع الاتصال | G7: =LEN(F7) | H7: Single Choice | I7: NA | J7: NA | K7: Form Type - Buttons | L7: 1 = resp_language 2 = AnsweringMachine 3 = NoAnswer 4 = Refusal 5 = WhenCallBack 6 = UnderReview 7 = Disconnected | M7: NA | N7: NA | T7: no | X7: 14.695308 | Y7: =IF(X7="","",X7*Q7)
A8: NA | B8: AnsweringMachine | C8: calldispo_answeringmachine | D8: Reached an answering machine. | E8: =LEN(D8) | F8: لقد تم توجيهك إلى جهاز الرد الالي | G8: =LEN(F8) | H8: NA | I8: NA | J8: NA | K8: NA | L8: End Poll AnsweringMachine | M8: NA | N8: NA | T8: no | X8: 0 | Y8: =IF(X8="","",X8*Q8)
A9: NA | B9: NoAnswer | C9: calldispo_noanswer | D9: Phone rang and no one answered. | E9: =LEN(D9) | F9: رن الهاتف ولم يرد أحد | G9: =LEN(F9) | H9: NA | I9: NA | J9: NA | K9: NA | L9: End Poll NoAnswer | M9: NA | N9: NA | T9: no | X9: 0 | Y9: =IF(X9="","",X9*Q9)
A10: NA | B10: UnderReview | C10: calldispo_underreview | D10: Case needs review by a supervisor. | E10: =LEN(D10) | F10: الحالة تحتاج إلى مراجعة من قبل مشرف | G10: =LEN(F10) | H10: NA | I10: NA | J10: NA | K10: NA | L10: End Poll UnderReview | M10: NA | N10: NA | T10: no | X10: 0 | Y10: =IF(X10="","",X10*Q10)
A11: NA | B11: Disconnected | C11: calldispo_disconnected | D11: Phone was disconnected or out of service. | E11: =LEN(D11) | F11: تم فصل الهاتف أو الهاتف خارج الخدمة | G11: =LEN(F11) | H11: NA | I11: NA | J11: NA | K11: NA | L11: End Poll Disconnected | M11: NA | N11: NA | T11: no | X11: 0 | Y11: =IF(X11="","",X11*Q11)
A12: NA | B12: resp_language | C12: resp_language | D12: Which language do you wish to proceed with? [OPERATOR: READ ANSWER CHOICES. SINGLE RESPONSE.] 1)Arabic | E12: =LEN(D12) | F12: ما هي اللغة التي ترغب في المتابعة بها؟ [المُشغل: اقرأ خيارات الإجابة. استجابة واحدة.] 1) عربي | G12: =LEN(F12) | H12: Single Choice | I12: NA | J12: NA | K12: Form Type - Buttons | L12: 1 = introduction [English] 2 = introduction [languages & add more if needed] | M12: NA | N12: For any response, go to introduction | P12: Arabic | T12: no | X12: 3.1032724 | Y12: =IF(X12="","",X12*Q12)
A13: NA | B13: introduction | C13: introduction | D13: Hello sir/ma'am, my name is #OPERATOR#, and I am calling from GeoPoll Polling Agency on behalf of the Food and Agriculture Organization of the United Nations [FAO]. We are conducting a survey on household livelihoods and the ability to access food in your area. I would like to ask you some questions about your household. The survey usually takes 20-30 minutes to complete. Any information that you provide will be kept strictly confidential, only used for the purpose of the survey and will not be shown to other people. Your voluntary participation in the outcome of this interview is NOT IN ANY WAY linked to your personal chance of receiving any assistance. This is voluntary and you can choose not to answer any or all of the questions if you want. However, we hope that you will participate since your views are important. Please note that this call may be recorded for quality purposes. Do you have any questions? [OPERATOR: ADDRESS QUESTIONS FROM RESPONDENT, IF ANY.] 1)CONTINUE | E13: =LEN(D13) | F13: مرحبًا سيدي / سيدتي ، اسمي #OPERATOR#. أتصل من وكالة GeoPoll الاستقصائية نيابة عن منظمة الأغذية والزراعة للأمم المتحدة (الفاو). نجري دراسة استقصائية حول سبل عيش الأسر والقدرة على الوصول إلى الغذاء في منطقتك. أود أن أطرح عليك بعض الأسئلة حول أسرتك. يستغرق الاستبيان عادةً 20-30 دقيقة. سيتم الاحتفاظ بسرية تامة بأي معلومات تقدمها ، ولن يتم استخدامها إلا لغرض الدراسة ولن يتم عرضها لأشخاص آخرين. إن مشاركتك الطوعية في نتيجة هذه الدراسة ليست مرتبطة بأي شكل من الأشكال بفرصتك الشخصية في تلقي أي مساعدة. هذا تطوعي ويمكنك اختيار عدم الإجابة على أي من الأسئلة أو جميعها إذا كنت تريد ذلك. ومع ذلك ، نأمل أن تشارك لأن آرائك مهمة. يرجى الملاحظة أنه قد يتم تسجيل هذه المكالمة لغاية مراقبة الجودة. هل لديك اسئلة؟ [المُشغل: أجب على أسئلة المُجيب ، إن وجدت.] 1) تابع | G13: =LEN(F13) | H13: Single Choice | I13: NA | J13: NA | K13: Form Type - Buttons | L13: 1 = Agree | M13: NA | N13: For any response, go to Agree | P13: 0 | T13: no | X13: 37.418449 | Y13: =IF(X13="","",X13*Q13)
A14: NA | B14: Agree | C14: resp_agree | D14: Are you interested in participating in this survey? [OPERATOR: SINGLE RESPONSE] 1)Yes 2)Not now but another time in the week 3)No | E14: =LEN(D14) | F14: هل لديك رغبة في بالمشاركة في هذه الدراسة؟ [المشغل: استجابة واحدة] 1) نعم 2) ليس الآن ولكن في وقت آخر في الأسبوع 3) لا | G14: =LEN(F14) | H14: StartRecording | I14: NA | J14: NA | K14: Form Type - Buttons | L14: 1 = [id_panel OR resp_firstname] 2 = WhenCallBack 3 = resp_refusalwhy | M14: NA | N14: if Agree = 1, go to id_panel OR resp_firstname if Agree = 2, go to WhenCallBack if Agree = 3, go to resp_refusalwhy | O14: id_panel | Q14: 1 | T14: no | X14: 3.8059516 | Y14: =IF(X14="","",X14*Q14)
A15: NA | B15: id_panel | C15: id_panel | D15: Have you or any member of your household received a call on behalf of FAO regarding this topic in the past two years? [OPERATOR: SINGLE RESPONSE.] 1)YES 2)NO 3)DON'T KNOW | E15: =LEN(D15) | F15: هل تلقيت انت أو أي أحد من أفراد أسرتك أي مكالمه بالنيابة عن منظمة الأغذيه و الزراعه [ الفاو ] بخصوص هذا الموضوع خلال العامين السابقين ؟ [ المشغل : أجابه واحده ] 1)نعم 2)لا 3)لا أعرف | G15: =LEN(F15) | H15: Single Choice | I15: NA | J15: NA | K15: Form Type - Buttons | L15: 1-3 = resp_firstname | M15: NA | N15: For any response, go to resp_firstname | P15: It is highly recommended to include the question id_panel if a panelist approach is used. | Q15: 1 | T15: no
A16: NA | B16: resp_refusalwhy | C16: resp_refusalwhy | D16: Please let us know why you have REFUSED to take the survey. [OPERATOR: SINGLE RESPONSE] 1)Not interested 2)Do not want to be recorded 3)Other [specify] | E16: =LEN(D16) | F16: يرجى إخبارنا سبب رفضك للمشاركة في هذه الدراسة. [المشغل: استجابة واحدة] 1) غير مهتم 2) لا أريد أن يتم تسجيلي 3) آخر [حدد] | G16: =LEN(F16) | H16: Open Ended - Single Choice | I16: NA | J16: NA | K16: Form Type - RadioList | L16: Any Response = Refusal | M16: NA | N16: For any response, go to Refusal | Q16: 1 | T16: no | X16: 0 | Y16: =IF(X16="","",X16*Q16)
A17: NA | B17: WhenCallBack | C17: resp_whencallback | D17: When would it be a good time to call you back? [RECORD HH/MM/DD/MM OF CALLBACK] | E17: =LEN(D17) | F17: ما هو التاريخ / الوقت المناسب لمعاودة الاتصال بك؟ [RECORD HH / MM / DD / MM of CALLBACK] | G17: =LEN(F17) | H17: Open Ended | I17: NA | J17: NA | K17: Form Type - TextBox IsCallBackDemographic | L17: Any Response = CallbackMessageEN | M17: NA | N17: For any response, go to CallbackMessageEN | Q17: 1 | T17: no | X17: 0 | Y17: =IF(X17="","",X17*Q17)
A18: NA | B18: CallbackMessageEN | C18: callbackmessage_en | D18: Thank you, we will call you back at {WhenCallBack} you requested. Thank you again and have a great day! [OPERATOR: ENTER CALL NOTES BELOW, WHO YOU SPOKE TO AND WHAT THEY SAID] | E18: =LEN(D18) | F18: شكرًا لك ، سوف نعاود الاتصال بك في #WhenCallBack# الذي طلبته. شكرا لك مرة أخرى و نتمنى لك يوم جميل! [المُشغل: أدخل ملاحظات الاتصال أدناه ، مع من تحدثت وماذا قالوا] | G18: =LEN(F18) | H18: Open Ended | I18: NA | J18: NA | K18: Form Type - TextBox | L18: Any Response = End poll callback | M18: NA | N18: NA | Q18: 1 | T18: no | X18: 0 | Y18: =IF(X18="","",X18*Q18)
A19: NA | B19: Ineligible | C19: NA | D19: You are ineligible for this survey. Thank you for your time and please look out for future surveys! | E19: =LEN(D19) | F19: أنت غير مؤهل للمشاركة في هذه الدراسة، شكرًا لك على وقتك. ترقب دراسات GeoPoll المستقبلية! | G19: =LEN(F19) | H19: NA | I19: NA | J19: NA | K19: NA | L19: End Poll Ineligible | M19: NA | N19: NA | Q19: 1 | T19: no | X19: 0 | Y19: =IF(X19="","",X19*Q19)
A20: NA | B20: Refusal | C20: NA | D20: Thank you for your time, you will be removed from today's survey. | E20: =LEN(D20) | F20: شكراً جزيلاً على وقتك، سنقوم بحذف إسمك من دراسة اليوم. | G20: =LEN(F20) | H20: NA | I20: NA | J20: NA | K20: NA | L20: End poll declined | M20: NA | N20: NA | Q20: 1 | T20: no | X20: 0 | Y20: =IF(X20="","",X20*Q20)
A21: B. GENERAL INFORMATION & ELIGIBILITY CRITERIA | Y21: =IF(X21="","",X21*Q21) | Z21: =IF(T21="yes",Y21,"")
A22: NA | B22: resp_firstname | C22: resp_firstname | D22: What is your first name? [OPERATOR: RECORD THE RESPONDENT'S FIRST NAME. ENTER 999 FOR REFUSED.] | E22: =LEN(D22) | F22: ما اسمك؟ [المُشغل: سجل اسم المجيب. أدخل 999 في حالة الرفض.] | G22: =LEN(F22) | H22: Open Ended | I22: NA | J22: NA | K22: Form Type - TextBox | L22: Any Response = resp_lastname | M22: NA | N22: For any response, go to resp_lastname | Q22: =1 | T22: yes | X22: 25.874027 | Y22: =IF(X22="","",X22*Q22) | Z22: 25.87402725219727
A23: NA | B23: resp_lastname | C23: resp_lastname | D23: What is your last name? [OPERATOR: RECORD THE RESPONDENT'S LAST NAME. ENTER 999 FOR REFUSED.] | E23: =LEN(D23) | F23: ما هو اسم عائلتك؟ [المُشغل: سجل اسم عائلة المجيب. أدخل 999 في حالة الرفض.] | G23: =LEN(F23) | H23: Open Ended | I23: NA | J23: NA | K23: Form Type - TextBox | L23: Any Response = resp_age | M23: NA | N23: For any response, go to resp_age | Q23: =1 | T23: yes | X23: 8.5994816 | Y23: =IF(X23="","",X23*Q23) | Z23: 8.599481582641602
A24: 1 | B24: resp_age | C24: resp_age | D24: How old are you? [OPERATOR: RECORD AGE IN NUMBER OF YEARS. ROUND UP TO NEAREST WHOLE NUMBER. IF THE RESPONDENT GIVES BIRTH YEAR, REPEAT THE QUESTION. ENTER 00 FOR DON'T KNOW.] | E24: =LEN(D24) | F24: كم عمرك؟ [المُشغل: سجل العمر في عدد السنوات. قم بالتقريب لأقرب رقم كامل. إذا أعطى المجيب سنة الميلاد ، فكرر السؤال. أدخل 00 للا أعرف.] | G24: =LEN(F24) | H24: Range | I24: NA | J24: NA | K24: Form Type - TextBox | L24: 0-17 = Ineligible 18-100 = resp_gender 00 = Ineligible | M24: NA | N24: Only respondents from 18-100 will be eligible for the survey. | Q24: =1 | T24: yes | X24: 9.8907185 | Y24: =IF(X24="","",X24*Q24) | Z24: 9.890718460083008
A25: =A24+1 | B25: resp_gender | C25: resp_gender | D25: What is the gender of the respondent? [OPERATOR: DO NOT ASK THIS QUESTION OUT LOUD. LISTEN TO THE VOICE AND SELECT THE GENDER.] 1)Male 2)Female 3)DON'T KNOW 4)REFUSED | E25: =LEN(D25) | F25: ما هو جنس المجيب؟ [المُشغل: لا تطرح هذا السؤال. استمع إلى الصوت وحدد المربع الصحيح.] 1) ذكر 2) أنثى 3) لا أعرف 4) رفض الإجابة | G25: =LEN(F25) | H25: Single Choice | I25: NA | J25: NA | K25: Form Type - Buttons | L25: 1-4 = phone_number_conf | M25: NA | N25: For any response, go to phone_number_conf | Q25: =1 | T25: yes | X25: 1.7156482 | Y25: =IF(X25="","",X25*Q25) | Z25: 1.715648174285889
Q26: =1 | Y26: =IF(X26="","",X26*Q26) | Z26: =IF(T26="yes",Y26,"")
B27: phone_number_conf | C27: phone_number_conf | D27: Is the phone number I am calling you on yours or a household members? [OPERATOR: SINGLE RESPONSE.] 1)YES 2)NO 3)DON'T KNOW 4)REFUSED | E27: =LEN(D27) | F27: هل رقم الهاتف الذي أتصل به هو رقمك أو رقم أحد أفراد أسرتك؟ [المشغل: استجابة واحدة.] 1) نعم 2) لا 3) لا أعرف 4) رفض الإجابة | G27: =LEN(F27) | H27: Single Choice | I27: NA | J27: NA | K27: Form Type - Buttons | L27: 1 = contact_2 2 = phone_number_personal 3-4 = contact_2 | M27: NA | N27: if phone_number_conf = 1, go to contact_2 if phone_number_conf = 2, go to phone_number_personal if phone_number_conf = 3-4, go to contact_2 | Q27: =1 | T27: yes - panel | X27: 6.375237 | Y27: =IF(X27="","",X27*Q27)
B28: phone_number_personal | C28: phone_number_pers | D28: What is your phone number? [OPERATOR: RECORD THE NUMBER GIVEN] | E28: =LEN(D28) | F28: ما هو رقم هاتفك؟ ( المشغل: قم بتسجيل الرقم المعطى لك ) | G28: =LEN(F28) | H28: Open Ended | I28: NA | J28: NA | K28: Form Type - TextBox | L28: Any Response = contact_2 | M28: NA | N28: For any response, go to contact_2 | Q28: =1 | T28: yes - panel | X28: 28.700001 | Y28: =IF(X28="","",X28*Q28)
B29: contact_2 | C29: contact_2 | D29: Can you give me an additional phone number belonging to you, another household member or a close relation living outside of the household at which you can be reached? [OPERATOR: SINGLE RESPONSE.] 1)YES - mine 2)YES - other household member 3)YES - friend or relative [non-household member] 4)NO 5)DON'T KNOW 6)REFUSED | E29: =LEN(D29) | F29: هل يمكن أن تعطيني رقم هاتف إضافي يخصك، أو أحد أفراد الأسرة، أو قريب يعيش خارج المنزل ويمكن التواصل معك عبره؟ [المشغل: استجابة واحدة.] 1) نعم - لي 2) نعم - فرد اخر من أفراد الأسرة 3) نعم - صديق أو أحد الأقارب [ ليس فردا من أفراد الأسرة ] 4) لا 5) لا أعرف 6) رفض الإجابة | G29: =LEN(F29) | H29: Single Choice | I29: NA | J29: NA | K29: Form Type - Buttons | L29: 1-3 = phone_number_2 4-6 = hh_admin1 | M29: NA | N29: if contact_2 = 1-3, go to phone_number_2 if contact_2 = 4-6, go to contact_3 | Q29: =1 | T29: yes - panel | X29: 10.141817 | Y29: =IF(X29="","",X29*Q29)
B30: phone_number_2 | C30: phone_number_2 | D30: What is the additional phone number? [OPERATOR: RECORD THE NUMBER GIVEN] | E30: =LEN(D30) | F30: ما هو رقم الهاتف الإضافي؟ ( المشغل: قم بتسجيل الرقم المعطى لك ) | G30: =LEN(F30) | H30: Open Ended | I30: NA | J30: NA | K30: Form Type - TextBox | L30: Any Response = contact_2_name | M30: NA | N30: For any response, go to contact_2_name | Q30: =1 | T30: yes - panel | X30: 21.659983 | Y30: =IF(X30="","",X30*Q30)
B31: contact_2_name | C31: contact_2_name | D31: What is the name of the contact? [OPERATOR: RECORD THE NAME OF THE CONTACT FOR THE PHONE NUMBER.] | E31: =LEN(D31) | F31: ما هو اسم صاحب رقم الهاتف الإضافي الذي قمت بمشاركته؟ ( المشغل: قم بتسجيل اسم صاحب رقم الهاتف ) | G31: =LEN(F31) | H31: Open Ended | I31: NA | J31: Send if "contact_2" "Equals" "YES - other household member" Or "contact_2" "Equals" "YES - friend or relative [non-household member]" if not satisfied go to "contact_3" | K31: Form Type - TextBox | L31: Any Response = contact_3 | M31: NA | N31: Asked if response to contact_2 was "YES - other household member" or "YES - friend or relative [non-household member]". Otherwise, it skips to "contact_3". For any response, go to contact_3 | Q31: =1 | T31: yes - panel | X31: 11.821796 | Y31: =IF(X31="","",X31*Q31)
B32: contact_3 | C32: contact_3 | D32: Can you give me an additional phone number belonging to you, another household member or a close relation living outside of the household at which you can be reached? [OPERATOR: SINGLE RESPONSE.] 1)YES - mine 2)YES - other household member 3)YES - friend or relative [non-household member] 4)NO 5)DON'T KNOW 6)REFUSED | E32: =LEN(D32) | F32: هل يمكن أن تعطيني رقم هاتف إضافي يخصك، أو أحد أفراد الأسرة، أو قريب يعيش خارج المنزل ويمكن التواصل معك عبره؟ [المشغل: استجابة واحدة.] 1) نعم - لي 2) نعم - فرد اخر من أفراد الأسرة 3) نعم - صديق أو أحد الأقارب [ ليس فردا من أفراد الأسرة ] 4) لا 5) لا أعرف 6) رفض الإجابة | G32: =LEN(F32) | H32: Single Choice | I32: NA | J32: NA | K32: Form Type - Buttons | L32: 1-3= phone_number_3 4-6 = hh_admin1 | M32: NA | N32: if contact_3 = 1-3, go to phone_number_3 if contact_3 = 4-6, go to hh_admin1 | Q32: =1 | T32: yes - panel | X32: 3.163594 | Y32: =IF(X32="","",X32*Q32)
B33: phone_number_3 | C33: phone_number_3 | D33: What is the additional phone number? [OPERATOR: RECORD THE NUMBER GIVEN] | E33: =LEN(D33) | F33: ما هو رقم الهاتف الإضافي؟ ( المشغل: قم بتسجيل الرقم المعطى لك ) | G33: =LEN(F33) | H33: Open Ended | I33: NA | J33: NA | K33: Form Type - TextBox | L33: Any Response = contact_3_name | M33: NA | N33: For any response, go to contact_3_name | Q33: =1 | T33: yes - panel | X33: 10.830144 | Y33: =IF(X33="","",X33*Q33)
B34: contact_3_name | C34: phone_number_3_name | D34: What is the name of the contact? [OPERATOR: RECORD THE NAME OF THE CONTACT FOR THE PHONE NUMBER.] | E34: =LEN(D34) | F34: ما هو اسم صاحب رقم الهاتف الإضافي الذي قمت بمشاركته؟ (المشغل: قم بتسجيل اسم صاحب رقم الهاتف) | G34: =LEN(F34) | H34: Open Ended | I34: NA | J34: Send if "contact_3" "Equals" "YES - other household member" Or "contact_3" "Equals" "YES - friend or relative [non-household member]" if not satisfied go to "hh_admin1" | K34: Form Type - TextBox | L34: Any Response = hh_admin1 | M34: NA | N34: Asked if response to contact_3 was "YES - other household member" or "YES - friend or relative [non-household member]". Otherwise, it skips to "hh_admin1". For any response, go to hh_admin1 | Q34: =1 | T34: yes - panel | X34: 11.260417 | Y34: =IF(X34="","",X34*Q34)
Q35: =1 | Y35: =IF(X35="","",X35*Q35) | Z35: =IF(T35="yes",Y35,"")
A36: 3 | B36: hh_admin1 | C36: hh_admin1 | D36: Currently, in which Governorate does your household reside? [OPERATOR: SINGLE SELECTION.] [HINT: HOUSEHOLD CONSISTS OF ALL MEMBERS LIVING TOGETHER, SHARING RESOURCES & EATING FROM THE SAME POT.] 1)ADMIN1 2)DON'T KNOW 3)REFUSED | E36: =LEN(D36) | F36: حاليًا ، في أي محافظة تقيم أسرتك؟ [المشغل: استجابة واحدة.] [ملحوظة: تتكون الأسرة من جميع الأعضاء الذين يعيشون معًا ، ويتشاركون الموارد ويأكلون من نفس القدر.] 1) ADMIN 1 2) لا أعرف 3) رفض الإجابة | G36: =LEN(F36) | H36: Single Choice | I36: NA | J36: NA | K36: Form Type - Buttons IsDemographic - ADM1 | L36: 1 = hh_admin2_1 2-3 = Ineligible | M36: NA | N36: The administrative information will be updated by GeoPoll based on the sample design document and the administrative boundaries provided by the dashboard team after the questionnaire validation. | Q36: =1 | T36: yes | X36: 13.957259 | Y36: =IF(X36="","",X36*Q36) | Z36: 13.95725891910985
A37: =A36+1 | B37: hh_admin2_1 | C37: hh_admin2_1 | D37: Currently, in which District does your household reside? [OPERATOR: SINGLE RESPONSE.] 1)ADMIN2 2)DON'T KNOW 3)REFUSED | E37: =LEN(D37) | F37: حاليًا ، في أي مديرية تقيم أسرتك؟ [المشغل: استجابة واحدة.] 1) ADMIN 2 2) لا أعرف 3) رفض الإجابة | G37: =LEN(F37) | H37: Single Choice | I37: NA | J37: NA | K37: Form Type - Buttons IsDemographic - ADM2 | L37: 1 = hh_agricactivity 2-3 = Ineligible | M37: NA | Q37: =1 | T37: yes | X37: 7.954999 | Y37: =IF(X37="","",X37*Q37) | Z37: 7.954998970031738
B38: quotareached | C38: quotareached | D38: [OPERATOR: DO NOT READ. ANSWER QUESTION BELOW.] THIS RESPONDENT REPORTED THEY LIVE IN: {ADM1} {ADM2} 1)THE GOAL FOR THIS LOCATION HAS BEEN ACHIEVED - END SURVEY 2)THE GOAL FOR THIS LOCATION IS OPEN - CONTINUE SURVEY | E38: =LEN(D38) | F38: [المُشغل: لا تقرأ. أجب على السؤال أدناه.] أبلغ هذا المجيب أنه يعيش في: {ADM1} {ADM2} 1) تم تحقيق الهدف لهذا الموقع - إنه الاستبيان 2) لا يزال يتعين تحقيق الهدف لهذا الموقع - تابع الاستبيان | G38: =LEN(F38) | H38: Single Choice | I38: NA | J38: NA | K38: Form Type - Buttons | L38: 1 = End Poll Quota Reached 2 = hh_agricactivity | M38: NA
A39: =#REF!+1 | B39: hh_agricactivity | C39: hh_agricactivity | D39: Has anybody in your household produced crops or livestock for household consumption or for sale in the past 12 months, including household members currently away for transhumance? [OPERATOR: SINGLE RESPONSE. THIS IS THE MAIN SCREENING QUESTION.] [HINT FOR PROBING: Do you cultivate any plants to sale or consume? Do you raise any animals with the intent of selling or consuming them or their products like meat, milk, wool or leather? Is one of your household member currently away with cattle or other animals for transhumance?] 1)Yes - crop production 2)Yes - livestock production 3)Yes - both crop and livestock production 4)No 5)DON'T KNOW 6)REFUSED | E39: =LEN(D39) | F39: هل قام أي شخص في أسرتك بإنتاج المحاصيل أو الماشية للاستهلاك المنزلي أو للبيع خلال الاثني عشر شهرًا الماضية ، بما في ذلك أفراد الأسرة الغير موجودين بغرض التنقل الرعوي؟ [المشغل: استجابة واحدة. هذا هو سؤال الفرز الرئيسي.] [ملحوظة للتحقيق: هل قمت بزراعة أي نباتات للبيع أو الاستهلاك ؟ هل قمت بتربية أي حيوانات بنية البيع أو الاستهلاك أو انتاج منتجات مثل اللحوم و الالبان و الصوف و الجلد ؟ هل أي فرد من أفراد أسرتك حاليا بعيدًا عن الأسرة مع الماشية أو حيوانات أخري بغرض التنقل الرعوي ؟] 1) نعم - إنتاج المحاصيل 2) نعم - إنتاج الماشية 3) نعم - كل من إنتاج المحاصيل والماشية 4) لا 5) لا أعرف 6) رفض الإجابة | G39: =LEN(F39) | H39: Single Choice | I39: NA | J39: NA | K39: Form Type - Buttons | L39: 1-4 = resp_id or hh_fish 5-6 = Ineligible | M39: NA | N39: if hh_agricactivity = 1-4, go to resp_id or hh_fish. Otherwise, the respondent is ineligible. | O39: o_fishery_activity | Q39: =1 | T39: yes | X39: 24.410839 | Y39: =IF(X39="","",X39*Q39) | Z39: 24.41083908081055
B40: o_fishery_activity | D40: Has anybody in your household been involved in fishery and aquaculture for household consumption or sale in the past 12 months? [OPERATOR: SINGLE CHOICE.] 1)YES 2)NO 3) DON'T KNOW 4)REFUSED | F40: هل شارك أي فرد من افراد الأسرة في مصائد الأسماك وتربية الأحياء المائية لغرض الاستهلاك المنزلي أو للبيع خلال الاثني عشر شهرًا الماضية؟ [المُشغل: استجابة واحدة.] 1) نعم 2) لا 3) لا أعرف 4) رفض الإجابة | H40: Single Choice | L40: 1-4 = resp_id | N40: For any response, go to resp_id | O40: resp_id
A41: B. GENERAL HOUSEHOLD INFORMATION | Y41: =IF(X41="","",X41*Q41) | Z41: =IF(T41="yes",Y41,"")
A42: =A39+1 | B42: resp_id | C42: resp_id | D42: Are you the head of household? [OPERATOR: SINGLE RESPONSE.] 1)Yes 2)No 3)DON'T KNOW 4)REFUSED | E42: =LEN(D42) | F42: هل أنت رب الأسرة ؟ [المشغل: استجابة واحدة.] 1) نعم 2) لا 3) لا أعرف 4) رفض الإجابة | G42: =LEN(F42) | H42: Single Choice | I42: NA | J42: NA | K42: Form Type - Buttons | L42: 1 = hh_education 2-4 = hh_gender | M42: NA | N42: if resp_id = 1, go to hh_education. Otherwise, go to hh_gender. | Q42: 1 | T42: yes | X42: 10.5 | Y42: =IF(X42="","",X42*Q42) | Z42: 10.5
A43: =A42+1 | B43: hh_gender | C43: hh_gender | D43: Is the head of your household male or female? [OPERATOR: SINGLE RESPONSE.] 1)Male 2)Female 3)DON'T KNOW 4)REFUSED | E43: =LEN(D43) | F43: هل رب أسرتك ذكر أم أنثى؟ [المشغل: استجابة واحدة.] 1) ذكر 2) أنثى 3) لا أعرف 4) رفض الإجابة | G43: =LEN(F43) | H43: Single Choice | I43: NA | J43: NA | K43: Form Type - Buttons | L43: 1-4 = hh_education | M43: NA | N43: if hh_gender = 1-4, go to hh_education. | Q43: =1 | T43: yes | X43: 10.504534 | Y43: =IF(X43="","",X43*Q43) | Z43: 10.5045337677002
Q44: =1 | Y44: =IF(X44="","",X44*Q44) | Z44: =IF(T44="yes",Y44,"")
A45: =A43+1 | B45: hh_education | C45: hh_education | D45: What is the educational level attained by the head of household? [OPERATOR: SINGLE RESPONSE.] 1)None or did not complete primary school 2)Completed primary school 3)Completed secondary school 4)Completed higher education [University / College] degree 5)Religious or informal education only 6)DON'T KNOW 7)REFUSED | E45: =LEN(D45) | F45: ما هو المستوى التعليمي الذي وصل إليه رب الأسرة؟ [المشغل: استجابة واحدة.] 1) لا شيء أو لم يكمل المرحلة الابتدائية 2) أكمل المرحلة الابتدائية 3) أكمل المرحلة الثانوية 4) أكمل درجة تعليم عالي [جامعة / كلية] 5) تربية دينية أو غير رسمية فقط 6) لا أعرف 7) رفض الإجابة | G45: =LEN(F45) | H45: Single Choice | I45: NA | J45: NA | K45: Form Type - Buttons | L45: 1-7 = hh_wealth | M45: NA | N45: if hh_education = 1-7, go to o_hh_wealth_water. | Q45: =1 | T45: yes | X45: 12.421899 | Y45: =IF(X45="","",X45*Q45) | Z45: 12.42189884185791
Q46: =1 | Y46: =IF(X46="","",X46*Q46) | Z46: =IF(T46="yes",Y46,"")
A47: 10 | B47: o_hh_wealth_water | C47: hh_wealth_water | D47: Where does the water that you drink at home come from? [OPERATOR: SINGLE CHOICE.] 1) Piped water to premise (public or private) 2) Public tap 3) Well 4) Covered well 5) Covered spring 6) Rainwater 7) Bottled water (mineral/Kawthar) 8) Valley/stream/canal 9) Unprotected well 10) Unprotected spring 11) Water trucks/drum on carts/donkeys 12) Water cistern/reservoir/dam 13)DON'T KNOW 14)REFUSED | E47: =LEN(D47) | F47: من أين تأتي المياه التي تشربونها في المنزل؟ [المُشغل: استجابة واحدة.] 1) مشروع مياه موصل إلى المنازل (حكومي أو خاص) 2) حنفية عامة 3) بئر ارتوازية 4) بئر مغطاة 5) عين مغطاة 6) مياه الأمطار 7) مياه معالجة (معدنية أو كوثر) 8 ) وادي أو جدول أو غيل 9 ) بئر مكشوفة 10) ماء عين مكشوفة 11) شاحنات / عربات/ دواب لنقل المياه 12) صهاريج/ حواجز مائية/ سدود 13) لا أعرف 14) رفض الإجابة | G47: =LEN(F47) | H47: Single Choice | I47: NA | J47: NA | K47: Form Type - Buttons | L47: 1-14 = [income_main O+L49R other optional question] | M47: NA | N47: For any response, go to [income_main OR other optional question] | O47: 1-14 = o_rural_urban | P47: Select wealth indicators based on baseline information available; you can delete those that you do not want to use. If none of these indicators work in the context of your country, other wealth proxies are proposed in the optional questions below. Remember that baseline data will be necessary, and the variable should be defined properly in the "weight_input_table". | Q47: =1 | T47: yes | X47: 16.615656 | Y47: =IF(X47="","",X47*Q47) | Z47: 16.61565589904785
B48: o_rural_urban | D48: Which of these best describes the area where you live? [OPERATOR: SINGLE RESPONSE] 1)Rural 2)Urban 3)Sub-urban | E48: 112 | F48: أي من هؤلاء يصف المنطقة التي تعيش فيها ؟ [المشغل: استجابة واحدة] 1)الريف 2)الحضر 3)ضواحي الحضر | G48: 96 | H48: Single Choice | I48: NA | J48: NA | K48: Form Type - Buttons | L48: 1-3 = hh_residencetype | O48: 1-3 = hh_residencetype | Q48: =1 | Y48: =IF(X48="","",X48*Q48)
B49: hh_residencetype | C49: hh_residencetype | D49: How would you describe your residence status? Are you a... [OPERATOR: READ OUT THE OPTIONS. SINGLE RESPONSE.] [HINT: IF RESPONDENT IS ONLY AWAY FROM THE HOUSEHOLD FOR SHORT SEASONAL WORK (<6 MONTHS) OR TRANSHUMANCE, MAKE SURE TO REFER TO THEIR HOUSEHOLD WHERE THEY TYPICALLY ARE LOCATED.] 1)Permanent resident 2)Returnee 3)Internally displaced person [IDP] 4)Refugee 5)DON'T KNOW 6)REFUSED | E49: =LEN(D49) | F49: كيف تصف حالة إقامتك؟ هل أنت... [المُشغل: اقرأ الخيارات. استجابة واحدة.] [ملحوظة: إذا كان المجيب بعيدًا فقط عن الأسرة للعمل الموسمي القصير (أقل من 6 أشهر) أو بغرض التنقل الرعوي ، فتأكد من الرجوع إلى أسرته في المكان الذي يوجد فيه عادةً.] 1) مقيم دائم 2) عائد 3) نازح داخليًا 4) لاجئ 5) لا أعرف 6) رفض الإجابة | G49: =LEN(F49) | H49: Single Choice | I49: NA | J49: NA | K49: Form Type - Buttons | L49: 1 = hh_residencecomp 2-4 = hh_arrivaltime 5-6 = hh_residencecomp | M49: NA | N49: 1 = hh_residencecomp 2-4 = hh_arrivaltime 5-6 = hh_residencecomp | Q49: =1 | T49: yes | X49: 13.220665 | Y49: =IF(X49="","",X49*Q49) | Z49: 13.22066497802734 | AD49: Important to define different categories in training material
B50: hh_arrivaltime | C50: hh_arivaltime | D50: How long ago did you arrive in this place? [OPERATOR: INDICATE THE NUMBER OF MONTHS. YOU MAY NEED TO CALCULATE THIS. ENTER 888 FOR DON'T KNOW & 999 FOR REFUSED.] | E50: =LEN(D50) | F50: منذ متى وصلت إلى هذا المكان؟ [المشغل: حدد عدد الأشهر. قد تحتاج إلى حساب ذلك. أدخل 888 لـ "لا أعرف" و999 لـ "رفض".] | G50: =LEN(F50) | H50: Range | I50: NA | J50: Send if "hh_residencetype" "Equals" "Internally displaced person [IDP]" Or "hh_residencetype" "Equals" "Returnee" Or "hh_residencetype" "Equals" "Refugee" if not satisfied go to "hh_displacementfreq" | K50: Form Type - TextBox | L50: 0-100 = hh_displacementfreq 888-888 = hh_displacementfreq 999-999 = hh_displacementfreq | M50: NA | N50: Asked to respondents that answered "Returnee", "IDP" or "Refugee" to hh_residencetype. All other respondents will skip to hh_residencecomp. For any response, go to hh_displacementfreq. | T50: yes
B51: hh_displacementfreq | C51: hh_displacementfreq | D51: How many times have you [respondent] been forced to move due to conflict, insecurity or disaster since you were first displaced? [OPERATOR: ENTER 888 FOR DON'T KNOW & 999 FOR REFUSED.] | E51: =LEN(D51) | F51: كم مرة اضطررت [المستجيب] إلى الانتقال بسبب الصراع أو انعدام الأمن أو الكوارث منذ نزوحك لأول مرة؟ [المشغل: أدخل 888 في حالة عدم المعرفة و999 في حالة الرفض.] | G51: =LEN(F51) | H51: Range | I51: NA | J51: NA | K51: Form Type - TextBox | L51: 0-100 = hh_residencecomp 888-888 = hh_residencecomp 999-999 = hh_residencecomp | M51: NA | N51: Asked to respondents that answered "Returnee", "IDP" or "Refugee" to hh_residencetype. All other respondents will skip to hh_residencecomp. For any response, go to hh_residencecomp. | T51: yes | AC51: Necessary for categorization of household residence type. Will depend on country context but these questions allow for flexibility of the definition.
B52: hh_residencecomp | C52: hh_residencecomp 1)hh_residencecomp_none 2)hh_residencecomp_permresident 3)hh_residencecomp_returnee 4)hh_residencecomp_idp 5)hh_residencecomp_refugee 6)hh_residencecomp_dk 7)hh_residencecomp_ref | D52: Does your household include any members with a different status type than the one you reported? And if so, which one(s)? [OPERATOR: MULTIPLE RESPONSES POSSIBLE. SELECT ALL THAT APPLY.] 1)No other status 2)Permanent resident 3)Returnee 4)Internally displaced person [IDP] 5)Refugee 6)DON'T KNOW 7)REFUSED | E52: =LEN(D52) | F52: هل تضم أسرتك أي أفراد لديهم نمط (حالة) إقامة مختلفة عن النمط الذي ذكرته؟ وإذا كان الأمر كذلك، فما هو النمط (الانماط)؟ [المشغل: إجابات متعددة ممكنة. حدد كل ما ينطبق.] 1) لا يوجد وضع آخر 2) مقيم دائم 3) عائد 4) نازح داخليًا 5) لاجئ 6) لا أعرف 7) رفض الإجابة | G52: =LEN(F52) | H52: Select All That Apply | I52: NA | J52: Send if "hh_residencetype" "Equals" "Internally displaced person [IDP]" Or "hh_residencetype" "Equals" "Returnee" Or "hh_residencetype" "Equals" "Refugee" Or "hh_residencetype" "Equals" "Permanent resident" if not satisfied go to "hh_site" | K52: Form Type - Checklist Included unselected "hh_residencetype" 1,2,3= IsNone | L52: 1-7 = hh_site | M52: 1)hh_residencecomp_none 2)hh_residencecomp_permresident 3)hh_residencecomp_returnee 4)hh_residencecomp_idp 5)hh_residencecomp_refugee 6)hh_residencecomp_dk 7)hh_residencecomp_ref | N52: Asked only to respondents who stated a status in hh_residencetype. Otherwise, go to hh_size . For any response, go to hh_site | T52: yes | AC52: Necessary for categorization of household residence type. Will depend on country context but these questions allow for flexibility of the definition. | AD52: In enumerator training, include explanation of status type
B53: hh_site | C53: hh_site | D53: Which of the following best describes where you live? [OPERATOR: READ ANSWERS OUT LOUD. SINGLE RESPONSE.] 1)Formal camp or settlement 2)Informal camp or settlement 3)Outside of a camp or settlement, with a host family 4)Outside of a camp or settlement, on my own 5)DON'T KNOW 6)REFUSED | E53: =LEN(D53) | F53: أي مما يلي يصف المكان الذي تعيش فيه على أفضل نحو؟ [المشغل: اقرأ الإجابات بصوت واضح. إجابة واحدة.] 1) مخيم نازحين رسمي 2) مخيم نازحين غير رسمي 3) خارج مخيمات النازحين، مع عائلة مضيفة 4) خارج مخيمات النازحين، بمفردي 5) لا أعرف 6) رفض الإجابة | G53: =LEN(F53) | H53: Single Choice | I53: NA | J53: Send if "hh_residencetype" "Equals" "Internally displaced person [IDP]" Or "hh_residencetype" "Equals" "Returnee" Or "hh_residencetype" "Equals" "Refugee" if not satisfied go to "hh_shelter" | K53: Form Type - Buttons | L53: 1-6 = hh_shelter | M53: NA | N53: Asked to respondents that answered "Returnee", "IDP" or "Refugee" to hh_residencetype. All other respondents will skip to hh_shelter. For any response, go to hh_shelter | T53: no | AD53: Note to explain to COs the importance of site/shelter for vulnerability assessments
B54: hh_shelter | C54: hh_shelter | D54: What kind of shelter is your household living in? [OPERATOR: SINGLE RESPONSE.] 1)Apartment/house, good condition 2)Apartment/house, damaged/destroyed, bad condition 3)Hotel/motel/short term rental 4)Unfinished or abandoned building 5)Tent/makeshift shelter 6)Mud or block structure 7)Container/caravan 8)Public building or collective shelter 9)Other shelter (eg garage, farm building etc) 10)DON'T KNOW 11)REFUSED | E54: =LEN(D54) | F54: ما نوع المأوى الذي تعيش فيه أسرتك؟ [المشغل: إجابة واحدة.] 1) شقة/منزل، بحالة جيدة 2) شقة/منزل، متضرر/مدمر، بحالة سيئة 3) فندق/لوكندا /إيجار قصير الأجل 4) مبنى غير مكتمل أو مهجور 5) خيمة/مأوى مؤقت 6) مبنى طيني أو من الطوب 7) حاوية/مقطورة 8) مبنى عام أو مأوى جماعي (مدارس أو ما شابه) 9) مأوى آخر (مثل المرآب أو مبنى المزرعة وما إلى ذلك) 10) لا أعرف 11) رفض الإجابة | G54: =LEN(F54) | H54: Single Choice | I54: NA | J54: NA | K54: Form Type - Buttons | L54: 1-11 = hh_predisp_agricactivity | M54: NA | N54: For any response, go to hh_predisp_agricactivity. | T54: no | AH54: Consider whether shelter should be mandatory vulnerability proxy
B55: hh_predisp_agricactivity | C55: hh_predisp_agricactivity | D55: Did you or others in your household engage in agricultural activities prior to your displacement? [OPERATOR: SINGLE RESPONSE.] 1)YES 2)NO 3)DON'T KNOW 4)REFUSED | E55: =LEN(D55) | F55: هل شاركت أنت أو أي شخص آخر في أسرتك في أنشطة زراعية قبل نزوحك؟ [المشغل: إجابة واحدة.] 1)نعم 2)لا 3)لا أعرف 4) رفض الإجابة | G55: =LEN(F55) | H55: Single Choice | I55: NA | J55: Send if "hh_residencetype" "Equals" "Returnee" OR "hh_residencetype" "Equals" "Internally displaced person [IDP]" OR "hh_residencetype" "Equals" "Refugee" OR "hh_residencecomp" "Contains" "Returnee" OR "hh_residencecomp" "Contains" "Internally displaced person [IDP]" OR "hh_residencecomp" "Contains" "Refugee" if not satisfied go to "income_main" | K55: Form Type - Buttons | L55: 1 = hh_disp_agricactivity_type 2-4 = hh_size | M55: NA | N55: If hh_disp_agricactivity = 1, go to hh_disp_agricactivity_type; otherwise, go to hh_size. | T55: no
B56: hh_predisp_agricactivity_type | C56: hh_predisp_agricactivity_type 1)hh_predisp_crpprod 2)hh_predisp_lsprod 3)hh_predisp_fishprod 4)hh_predisp_dk 5)hh_predisp_ref | D56: What type of agricultural activities were they? [OPERATOR: MULTIPLE RESPONSES POSSIBLE.] 1)Crop production 2) Livestock production 3)Fisheries or aquaculture production 4)DON'T KNOW 5)REFUSED | E56: =LEN(D56) | F56: ما نوع الأنشطة الزراعية التي مارستها/مارسوها؟ [المشغل: إجابات متعددة ممكنة.] 1) إنتاج المحاصيل 2) إنتاج الثروة الحيوانية 3) إنتاج الأسماك أو تربية الأحياء المائية 4) لا أعرف 5) رفض الإجابة | G56: =LEN(F56) | H56: Select All That Apply | I56: NA | J56: NA | K56: Form Type - Checklist 4,5= IsNone | L56: 1-5 = hh_size | M56: 1)hh_predisp_crpprod 2)hh_predisp_lsprod 3)hh_predisp_fishprod 4)hh_predisp_dk 5)hh_predisp_ref | N56: For any response, go to hh_size. | T56: no
B57: crp_returnee_plotaccess | C57: crp_returnee_plotaccess | D57: If you used to cultivate land in this area, fled and have since returned, are you able to access the same land as before? [OPERATOR: SINGLE RESPONSE.] 1)YES 2)NO 3)I never had land here 4)DON'T KNOW 5)REFUSED | E57: =LEN(D57) | F57: إذا كنت تزرع أرضًا في هذه المنطقة، ثم نزحت وعدت منذ ذلك الحين، فهل يمكنك الوصول إلى نفس الأرض كما كنت تفعل من قبل؟ [المشغل: إجابة واحدة.] 1)نعم 2)لا 3)لم يكن لدي أرض هنا قط 4)لا أعرف 5) رفض الإجابة | G57: =LEN(F57) | H57: Single Choice | I57: NA | J57: Send if "hh_residencetype" "Equals" "Returnee" if not satisfied go to "hh_size" | K57: Form Type - Buttons | L57: 1 = hh_size 2 = crp_orig_plot 3-5 =hh_size | M57: NA | N57: Asked only to respondents that indicated returnees as head of household, if non-returnee, proceed to hh_size. If crp_returnee_plotaccess = 1,3-5, go to hh_size if crp_returnee_plotaccess = 2, go to crp_orig_plot | T57: no
B58: crp_orig_plot | C58: crp_orig_plot_ 1)crp_origplot_occup_comm 2)crp_origplot_occup_displacedppl 3)crp_origplot_occup_armedgps 4)crp_plot_unsafe_armedgps 5)crp_plot_unsafe_explosives 6)crp_orig_plot_distance 7)crp_orig_plot_other 8)crp_orig_plot_dk 9)crp_orig_plot_ref | D58: Why are you unable to access your original land for cultivation? [OPERATOR: MULTIPLE RESPONSES POSSIBLE.] 1)Occupied by someone else from my community 2)Land given away to / occupied by displaced persons 3)Occupied by armed groups 4)No safe access - presence of armed groups 5)No safe access - there are explosive ordnance, IEDs, or landmines on the land 6)Land is too far from where I'm settled 7)Other [specify] 8)DON'T KNOW 9)REFUSED | E58: =LEN(D58) | F58: لماذا لا تستطيع الوصول إلى أرضك الأصلية للزراعة؟ [المشغل: إجابات متعددة ممكنة.] 1) محتلة من قبل شخص آخر من مجتمعي 2) الأرض مُنحت للنازحين/محتلة من قبلهم 3) محتلة من قبل الجماعات المسلحة 4) عدم وجود وصول آمن - وجود الجماعات المسلحة 5) عدم وجود وصول آمن - هناك ذخائر متفجرة أو عبوات ناسفة أو ألغام أرضية على الأرض 6) الأرض بعيدة جدًا عن المكان الذي أستقر فيه 7) أخرى [حدد] 8) لا أعرف | G58: =LEN(F58) | H58: Open Ended-Select All That Apply | I58: NA | J58: NA | K58: Form Type - Checklist 7,8= IsNone | L58: 1-8 = hh_size | M58: 1)crp_origplot_occup_comm 2)crp_origplot_occup_displacedppl 3)crp_origplot_occup_armedgps 4)crp_plot_unsafe_armedgps 5)crp_plot_unsafe_explosives 6)crp_orig_plot_distance 7)crp_orig_plot_other 8)crp_orig_plot_dk 9)crp_orig_plot_ref | N58: For any response, go to hh_size. | Q58: ='[1]Additional information'!$D$17 | T58: no | Y58: =IF(X58="","",X58*Q58)
A59: =#REF!+1 | B59: hh_size | C59: hh_size | D59: How many people are part of the household? [OPERATOR: RECORD NUMBER OF MEMBERS IN HOUSEHOLD. ENTER 88 FOR DON'T KNOW & 99 FOR REFUSED.] [HINT: TO BE A PART OF THE SAME HOUSEHOLD, MEMBERS MUST LIVE UNDER THE SAME ROOF, SHARE THE SAME RESOURCES & EAT FROM THE SAME POT.] | E59: =LEN(D59) | F59: كم عدد الأشخاص الذين هم جزء من الأسرة؟ [المُشغل: سجل عدد أعضاء الأسرة. أدخل 88 للا أعرف و 99 في حالة الرفض.] [ملحوظة: لكي يكونوا جزءًا من نفس الأسرة، يجب أن يكون جميع الاعضاء يعيشون تحت سقف منزل واحد، و يتشاركون نفس الموارد و يأكلون من نفس القدر] | G59: =LEN(F59) | H59: Range | I59: NA | J59: NA | K59: Form Type - TextBox | L59: 1-50 = hh_asset_prod 88-88 = hh_asset_prod 99-99 = hh_asset_prod | M59: NA | N59: For any response, go to [next question] | O59: For any response, go to o_hh_asset | Q59: =1 | T59: no | X59: 16.902294 | Y59: =IF(X59="","",X59*Q59)
A60: =A59+1 | B60: o_hh_asset | C60: hh_asset_prod_ 1)hh_asset_prod_process 2)hh_asset_prod_farmmach 3)hh_asset_prod_sewing 4)hh_asset_prod_taxi 5)hh_asset_prod_truck 6)hh_asset_prod_other 7) hh_asset_prod_none 8) hh_asset_prod_dk 9) hh_asset_prod_ref | D60: Does your household own any of the following assets? [OPERATOR: MULTIPLE RESPONSES POSSIBLE. READ ANSWER OPTIONS OUT LOUD.] 1) Land 2) Farm/agriculture tools [manual items like a plough, sickle, rake etc.] 3) Farm/agriculture machinery [e.g. tractor, power harvester, etc.] 4) Water/irrigation pump 5) Processing assets [e.g. grinding/crushing machine, mill, oil press] 6) Fishing net 7) Fishing boat 8) Livestock (cattle/goats/sheep) 9) Taxi/ Truck/Van [small truck] 10) Car 11) Motorbike / scooter / auto rickshaw 12) Bicycle 13) Sewing machine or weaving tool 14) Other productive assets 15) Do not own any productive assets 16) House/Apartment 17) Mattress or sofa 18) Stove 19) Fridge 20) Television 21) Radio 22) Mobile phone 23) Internet 24) Bank savings/jewellery/other savings 25) Generator 26) Electric bulbs/solar panels/batteries 27) Other household assets 28) Do not own any household assets 29) DON’T KNOW 30) REFUSED | E60: =LEN(D60) | F60: هل تمتلك أسرتك أيًا من الأصول التالية؟ [المشغل: عدة استجابات محتملة. يرجي قراءة اختيارات الإجابة بصوت مرتفع] 1) أرض 2) معدات زراعية [معدات زراعية يدوية مثل المحراث ، والمنجل ، مجرفة ، إلخ] 3) آلات زراعية [على سبيل المثال حراثة ، حصادة كهربائية ، إلخ] 4) مضخة مياه / ري 5) ادوات تستخدم لمعاملات ما بعد الحصاد [على سبيل المثال آلة طحن / سحق ، مطحنة ، معصرة زيت] 6) شبكة صيد 7) قارب صيد 8) الثروة الحيوانية (الأبقار / الماعز / الأغنام) 9) تاكسي / شاحنة / سيارة نقل [شاحنة صغيرة] 10) سيارة 11) دراجة نارية / دراجة صغيرة / عربة آلية 12) دراجة هوائية 13) ماكينة الخياطة أو أداة النسيج 14) أصول إنتاجية أخرى 15) لا تملك أي أصول إنتاجية 16) بيت / شقة 17) مرتبة أو أريكة 18) موقد 19) ثلاجة 20) تلفاز 21) راديو 22) الهاتف المحمول 23) الإنترنت 24) مدخرات بنكية / مجوهرات / مدخرات أخرى 25) مولد 26) المصابيح الكهربائية / الألواح الشمسية / البطاريات 27) أصول الأسرة الأخرى 28) لا تملك أي أصول منزلية 29) لا أعرف 30) رفض الإجابة | G60: =LEN(F60) | H60: Select All That Apply | I60: NA | J60: NA | K60: Form Type - Checklist 28,29,30 = IsNone | L60: 1-30 = hh_maritalstat | N60: For any response, go to [hh_maritalstat] | O60: 1-30 = hh_maritalstat | P60: This wealth indicator may be useful to Identify poor households in middle income countries. It could be interesting for F2F surveys, to be used as baseline reference for follow-up surveys. | Q60: =1 | T60: no | X60: 16.957804 | Y60: =IF(X60="","",X60*Q60)
A61: =#REF!+1 | B61: hh_maritalstat | C61: hh_maritalstat | D61: What is the head of household’s current marital status? [OPERATOR: SINGLE RESPONSE.] 1)Single / never married 2)Married 3)Separated 4)Divorced 5)Widowed 6)DON’T KNOW 7)REFUSED | E61: =LEN(D61) | F61: ما هي الحالة الاجتماعية الحالية لرب الأسرة؟ [المشغل: استجابة واحدة.] 1) أعزب / لم يتزوج قط 2) متزوج 3) منفصل 4) مطلق 5) أرمل 6) لا أعرف 7) رفض الإجابة | G61: =LEN(F61) | H61: Single Choice | I61: NA | J61: NA | K61: Form Type - Buttons | L61: 1-7 = hh_age | M61: NA | N61: For any response, go to [next question] | O61: 1-7 = hh_age | Q61: =1 | T61: no | X61: 9.9618664 | Y61: =IF(X61="","",X61*Q61)
A62: =A61+1 | B62: hh_age | C62: hh_age | D62: How old is the head of household? [OPERATOR: SINGLE RESPONSE.] 1)Under 18 2)18 to 40 3)41 to 65 4)Over 65 5)DON'T KNOW 6)REFUSED | E62: =LEN(D62) | F62: كم عمر رب الاسرة؟ [المشغل: استجابة واحدة.] 1) أقل من 18 عامًا 2) بين 18 و 40 عامًا 3) بين 41 و 65 عامًا 4) فوق 65 عامًا 5) لا أعرف 6) رفض الإجابة | G62: =LEN(F62) | H62: Single Choice | I62: NA | J62: NA | K62: Form Type - Buttons | L62: 1-6 = income_main | M62: NA | N62: For any response, go to [next question] | O62: 1-6 = o_fishery_activity | Q62: =1 | T62: no | X62: 7.0248413 | Y62: =IF(X62="","",X62*Q62)
A63: C. INCOME SOURCES, LIVELIHOOD AND SHOCKS | B63: C. INCOME & SHOCKS | Y63: =IF(X63="","",X63*Q63)
Q64: =1 | Y64: =IF(X64="","",X64*Q64) | Z64: =IF(T64="yes",Y64,"")
A65: =A62+1 | B65: income_main | C65: income_main | D65: What was your household's main source of income in the past 3 months? [OPERATOR: SINGLE RESPONSE. REFUSED OPTION SHOULD BE AVOIDED AS MUCH AS POSSIBLE.] 1)Production and sale of staple crops 2)Production and sale of vegetables or fruit 3)Production and sale of cashcrops 4)Production and sale of livestock or livestock products 5)Production and sale of honey or bee products 6)Production and sale of fish or aquatic products 7)Collection and sale of forestry or bush products 8)Agricultural trade EXCLUDING producers [formal or informal] 9)Daily wage on farms and other casual employment in agricultural sector 10)Stable employment in agricultural sector 11)Non-agricultural self-employed or liberal profession / doctor / architect / lawyer / including restaurant 12)Off-farm daily wages and other non-agricultural casual employment 13)Stable employment in non-agricultural sector 14)Public employment 15)Income not derived from work / Charity 16)Income not derived from work / Welfare transfer, pension, humanitarian aid 17)Income not derived from work / Remittances 18)Income not derived from work / Income from other rents 19)No income source in the last 3 months and used exclusively savings / debt 20)REFUSED | E65: =LEN(D65) | F65: ما كان مصدر الدخل الرئيسي لأسرتك في الأشهر الثلاثة الماضية؟ [المشغل: استجابة واحدة. يجب تجنب الخيار "رفض الإجابة" قدر الإمكان.] 1) إنتاج وبيع المحاصيل الأساسية 2) إنتاج وبيع الخضار أو الفاكهة 3) إنتاج وبيع المحاصيل النقدية 4) إنتاج وبيع الحيوانات الأليفة أو منتجاتها 5) انتاج و بيع العسل أو منتجات النحل 6) إنتاج وبيع الأسماك أو منتجات المنتجات المائية 7) جمع وبيع منتجات الغابات أو الأحراش 8) التجارة الزراعية الرسمية و غير الرسمية باستثناء المنتجين 9) الأجر اليومي في المزارع وغيرها من العمالة العرضية في قطاع الزراعة 10) العمالة المستقرة في القطاع الزراعي 11) العاملين لحسابهم الخاص غير الزراعيين أو المهنة الحرة / طبيب / مهندس معماري / محامٍ / بما في ذلك مطعم 12) الأجور اليومية خارج المزرعة وغيرها من العمالة العرضية غير الزراعية 13) العمالة المستقرة في القطاع غير الزراعي 14) الوظائف العامة 15) الدخل غير المستمد من العمل / الاعمال الخيرية 16) الدخل غير المستمد من العمل / المدفوعات التحويلية ، المعاش التقاعدي ، المساعدات الإنسانية 17) الدخل غير المستمد من العمل / التحويلات 18) الدخل غير المستمد من العمل / الدخل من الإيجارات الأخرى 19) لم يكن هناك مصدر دخل خلال الأشهر الثلاثة الماضية واستخدمت المدخرات أو الدين حصريًا 20) رفض الإجابة | G65: =LEN(F65) | H65: Single Choice | I65: NA | J65: NA | K65: Form Type - Buttons IsDemographic | L65: 1-3 = income_main_crop_check 4 = income_main_ls_check 5 = income_main_comp OR optional question 6 = income_main_fish_check 7-18 = income_main_comp OR optional question 19-20 = shock | M65: NA | N65: if options #1-3 selected go to income_main_crop_check if options #4 selected go to income_main_ls_check if options #6 selected go to income_main_fish_check if options #5, 7-18 selected, go to [income_main_comp OR optional question] if options #19-20 selected, go to shock | O65: income_main_gender | Q65: =1 | T65: yes | X65: 31.888334 | Y65: =IF(X65="","",X65*Q65) | Z65: 31.88833427429199
B66: income_main_crop_check | C66: income_main_crop_check | D66: Are the crops sold also produced by you or anyone in your household? [OPERATOR: SINGLE RESPONSE.] 1)YES 2)NO 3)DON'T KNOW 4)REFUSED | E66: =LEN(D66) | F66: هل تم إنتاج المحاصيل التي تبيعها أنت أو أي شخص في منزلك أيضًا؟ [المشغل: استجابة واحدة.] 1) نعم 2) لا 3) لا أعرف 4) رفض الإجابة | G66: =LEN(F66) | H66: Single Choice | I66: NA | J66: NA | K66: Form Type - Buttons | L66: 1-4 = income_main_comp OR optional question | M66: NA | N66: if income_main_crop_check = 1-4, go to [income_main_comp OR optional question] | O66: 1-4 = income_main_gender | Q66: =1 | T66: yes | X66: 8 | Y66: =IF(X66="","",X66*Q66) | Z66: 8
B67: income_main_ls_check | C67: income_main_ls_check | D67: Are the livestock or livestock products sold also produced by you or anyone in your household? [OPERATOR: SINGLE RESPONSE.] 1)YES 2)NO 3)DON'T KNOW 4)REFUSED | E67: =LEN(D67) | F67: هل تم إنتاج المواشي ومنتجاتها التي تبيعها أنت أو أي شخص في منزلك أيضًا؟ [المشغل: استجابة واحدة.] 1) نعم 2) لا 3) لا أعرف 4) رفض الإجابة | G67: =LEN(F67) | H67: Single Choice | I67: NA | J67: NA | K67: Form Type - Buttons | L67: 1-4 = income_main_comp OR optional question | M67: NA | N67: if income_main_ls_check = 1-4, go to [income_main_comp OR optional question] | O67: 1-4 = income_main_gender | Q67: =1 | T67: yes | X67: 8 | Y67: =IF(X67="","",X67*Q67) | Z67: 8
B68: income_main_fish_check | C68: income_main_fish_check | D68: Are the fish or aquatic products sold also captured/harvested by you or anyone in your household? [OPERATOR: SINGLE RESPONSE.] 1)YES 2)NO 3)DON'T KNOW 4)REFUSED | E68: =LEN(D68) | F68: هل الأسماك أو المنتجات المائية التي تُباع تم أيضًا صيدها أو جمعها بواسطتك أو أي شخص في منزلك؟ [المشغل: استجابة واحدة.] 1) نعم 2) لا 3) لا أعرف 4) رفض الإجابة | G68: =LEN(F68) | H68: Single Choice | I68: NA | J68: NA | K68: Form Type - Buttons | L68: 1-4 = income_main_comp OR optional question | M68: NA | N68: if income_main_fish_check = 1-4, go to [income_main_comp OR optional question] | O68: 1-4 = income_main_gender | Q68: =1 | T68: yes | X68: 8 | Y68: =IF(X68="","",X68*Q68) | Z68: 8
Q69: =1 | Y69: =IF(X69="","",X69*Q69) | Z69: =IF(T69="yes",Y69,"")
A70: 19 | B70: income_main_gender | C70: income_main_gender | D70: What is the gender of the household member[s] generating income from this source? [OPERATOR: SINGLE RESPONSE.] 1)Male 2)Female 3)Joint [both male & female] 4)DON'T KNOW 5)REFUSED | E70: =LEN(D70) | F70: ما هو جنس الفرد ( الأفراد ) داخل الاسرة الذين يحصلون علي الدخل من هذا المصدر ؟ [المشغل: استجابة واحدة.] 1) ذكر 2) أنثى 3) مختلط ( ذكر و أنثى ) 4) لا أعرف 5) رفض الإجابة | G70: =LEN(F70) | H70: Single Choice | I70: NA | J70: NA | K70: Form Type - Buttons | L70: 1-5 = [income_main_comp OR optional question] | M70: NA | N70: if income_main_gender = 1-5, go to income_main_comp or optional question | O70: 1-5 = income_main_comp | Q70: =1 | T70: no | X70: 4.7874017 | Y70: =IF(X70="","",X70*Q70)
Q71: =1 | Y71: =IF(X71="","",X71*Q71) | Z71: =IF(T71="yes",Y71,"")
A72: 21 | B72: income_main_comp | C72: income_main_comp | D72: Has your household's income from {income_main} changed in the last 3 months compared to the same period of last year? [OPERATOR: SINGLE RESPONSE.] 1)A lot more [increased by more than 50%] 2)Slightly more 3)Same 4)Slightly less 5)A lot less [less than half as much] 6)DON'T KNOW 7)REFUSED | E72: =LEN(D72) | F72: هل تغير دخل أسرتك من {income_main} في الأشهر الثلاثة الماضية مقارنة بنفس الفترة من العام الماضي؟ [المشغل: استجابة واحدة.] 1) أكثر بكثير [زاد بنسبة تزيد عن 50٪] 2) أكثر قليلا 3) نفس الشيء 4) أقل قليلاً 5) أقل بكثير [أقل من نصف الكمية] 6) لا أعرف 7) رفض الإجابة | G72: =LEN(F72) | H72: Single Choice | I72: NA | J72: NA | K72: Form Type - Buttons | L72: 1-7= income_sec | M72: NA | N72: if income_main_comp = 1-7, go to income_sec | Q72: =1 | T72: yes | X72: 22.126215 | Y72: =IF(X72="","",X72*Q72) | Z72: 22.1262149810791
Q73: =1 | Y73: =IF(X73="","",X73*Q73) | Z73: =IF(T73="yes",Y73,"")
A74: =A72+1 | B74: income_sec | C74: income_sec | D74: What was your household's second most important source of income in the past 3 months? [OPERATOR: SINGLE RESPONSE. DON'T KNOW AND REFUSED OPTIONS SHOULD BE AVOIDED AS MUCH AS POSSIBLE.] 1)Production and sale of staple crops 2)Production and sale of vegetables or fruit 3)Production and sale of cashcrops 4)Production and sale of livestock or livestock products 5)Production and sale of honey or bee products 6)Production and sale of fish or aquatic products 7)Collection and sale of forestry or bush products 8)Agricultural trade EXCLUDING producers [formal or informal] 9)Daily wage on farms and other casual employment in agricultural sector 10)Stable employment in agricultural sector 11)Non-agricultural self-employed or liberal profession / doctor / architect / lawyer / including restaurant 12)Off-farm daily wages and other non-agricultural casual employment 13)Stable employment in non-agricultural sector 14)Public employment 15)Income not derived from work / Charity 16)Income not derived from work / Welfare transfer, pension, humanitarian aid 17)Income not derived from work / Remittances 18)Income not derived from work / Income from other rents 19)No second most important source of income 20)DON'T KNOW 21)REFUSED | E74: =LEN(D74) | F74: ما هو ثاني أهم مصدر دخل لأسرتك فى الثلاثة أشهر الماضية ؟ [المشغل: استجابة واحدة. يجب تجنب خيارات الإجابة "لا أعرف" و "رفض الإجابة" قدر الإمكان.] 1) إنتاج وبيع المحاصيل الأساسية 2) إنتاج وبيع الخضار أو الفاكهة 3) إنتاج وبيع المحاصيل النقدية 4) إنتاج وبيع الحيوانات الأليفة أو منتجاتها 5) انتاج و بيع العسل أو منتجات النحل 6) إنتاج وبيع الأسماك أو منتجات المنتجات المائية 7) جمع وبيع منتجات الغابات أو الأحراش 8) التجارة الزراعية الرسمية و غير الرسمية باستثناء المنتجين 9) الأجر اليومي في المزارع وغيرها من العمالة العرضية في قطاع الزراعة 10) العمالة المستقرة في القطاع الزراعي 11) العاملين لحسابهم الخاص غير الزراعيين أو المهنة الحرة / طبيب / مهندس معماري / محامٍ / بما في ذلك مطعم 12) الأجور اليومية خارج المزرعة وغيرها من العمالة العرضية غير الزراعية 13) العمالة المستقرة في القطاع غير الزراعي 14) الوظائف العامة 15) الدخل غير المستمد من العمل / الاعمال الخيرية 16) الدخل غير المستمد من العمل / المدفوعات التحويلية ، المعاش التقاعدي ، المساعدات الإنسانية 17) الدخل غير المستمد من العمل / التحويلات 18) الدخل غير المستمد من العمل / الدخل من الإيجارات الأخرى 19) لم يكن هناك مصدر دخل ثانٍ 20) لا أعرف 21) رفض الإجابة | G74: =LEN(F74) | H74: Single Choice | I74: NA | J74: NA | K74: Form Type - Buttons exclude selected "income_main" IsDemographic | L74: 1-3 = income_sec_crop_check 4 = income_sec_ls_check 5 = income_sec_comp OR optional question 6 = income_sec_fish_check 7-18 = income_sec_comp OR optional question 19-21 = shock | M74: NA | N74: if options #1-3 selected, go to income_sec_crop_check if options #4 selected, go to income_sec_ls_check if options #6 selected, go to income_sec_fish_check if options #5, 7-18 selected, go to [income_sec_comp OR optional question] if options #19-21 selected, go to shock | O74: income_sec_gender | Q74: =1 | T74: yes | X74: 18.710653 | Y74: =IF(X74="","",X74*Q74) | Z74: 18.71065330505371
B75: income_sec_crop_check | C75: income_sec_crop_check | D75: Are the crops sold also produced by you or anyone in your household? [OPERATOR: SINGLE RESPONSE.] 1)YES 2)NO 3)DON'T KNOW 4)REFUSED | E75: =LEN(D75) | F75: هل تم إنتاج المحاصيل التي تبيعها أنت أو أي شخص في منزلك أيضًا؟ [المشغل: استجابة واحدة.] 1) نعم 2) لا 3) لا أعرف 4) رفض الإجابة | G75: =LEN(F75) | H75: Single Choice | I75: NA | J75: NA | K75: Form Type - Buttons | L75: 1-4 = income_sec_comp OR optional question | M75: NA | N75: if income_sec_crop_check = 1-4, go to [income_sec_comp OR optional question] | O75: 1-4 = income_sec_gender | Q75: =1 | T75: yes | X75: 8 | Y75: =IF(X75="","",X75*Q75) | Z75: 8
B76: income_sec_ls_check | C76: income_sec_ls_check | D76: Are the livestock or livestock products sold also produced by you or anyone in your household? [OPERATOR: SINGLE RESPONSE.] 1)YES 2)NO 3)DON'T KNOW 4)REFUSED | E76: =LEN(D76) | F76: هل تم إنتاج المواشي ومنتجاتها التي تبيعها أنت أو أي شخص في منزلك أيضًا؟ [المشغل: استجابة واحدة.] 1) نعم 2) لا 3) لا أعرف 4) رفض الإجابة | G76: =LEN(F76) | H76: Single Choice | I76: NA | J76: NA | K76: Form Type - Buttons | L76: 1-4 = income_sec_comp OR optional question | M76: NA | N76: if income_sec_ls_check = 1-4, go to [income_sec_comp OR optional question] | O76: 1-4 = income_sec_gender | Q76: =1 | T76: yes | X76: 8 | Y76: =IF(X76="","",X76*Q76) | Z76: 8
B77: income_sec_fish_check | C77: income_sec_fish_check | D77: Are the fish or aquatic products sold also captured/harvested by you or anyone in your household? [OPERATOR: SINGLE RESPONSE.] 1)YES 2)NO 3)DON'T KNOW 4)REFUSED | E77: =LEN(D77) | F77: هل الأسماك أو المنتجات المائية التي تُباع تم أيضًا صيدها أو جمعها بواسطتك أو أي شخص في منزلك؟ [المشغل: استجابة واحدة.] 1) نعم 2) لا 3) لا أعرف 4) رفض الإجابة | G77: =LEN(F77) | H77: Single Choice | I77: NA | J77: NA | K77: Form Type - Buttons | L77: 1-4 = income_sec_comp OR optional question | M77: NA | N77: if income_sec_fish_check = 1-4, go to [income_sec_comp OR optional question] | O77: 1-4 = income_sec_gender | Q77: =1 | T77: yes | X77: 8 | Y77: =IF(X77="","",X77*Q77) | Z77: 8
Q78: =1 | Y78: =IF(X78="","",X78*Q78) | Z78: =IF(T78="yes",Y78,"")
A79: 24 | B79: income_sec_gender | C79: income_sec_gender | D79: What is the gender of the household member[s] generating income from this source? [OPERATOR: SINGLE RESPONSE.] 1)Male 2)Female 3)Joint [both male & female] 4)DON'T KNOW 5)REFUSED | E79: =LEN(D79) | F79: ما هو جنس الفرد ( الأفراد ) داخل الاسرة الذين يحصلون علي الدخل من هذا المصدر ؟ [المشغل: استجابة واحدة.] 1) ذكر 2) أنثى 3) مختلط ( ذكر و أنثى ) 4) لا أعرف 5) رفض الإجابة | G79: =LEN(F79) | H79: Single Choice | I79: NA | J79: NA | K79: Form Type - Buttons | L79: 1-5 = [income_sec_comp OR optional question] | M79: NA | N79: if income_sec_gender = 1-5, go to income_sec_comp or optional question | O79: 1-5 = income_sec_comp | Q79: =1 | T79: no | X79: 4.7874017 | Y79: =IF(X79="","",X79*Q79)
Q80: =1 | Y80: =IF(X80="","",X80*Q80) | Z80: =IF(T80="yes",Y80,"")
A81: =#REF!+1 | B81: income_sec_comp | C81: income_sec_comp | D81: Has your household's income from {income_sec} changed in the last 3 months compared to the same period of last year? [OPERATOR: SINGLE RESPONSE.] 1)A lot more [increased by more than 50%] 2)Slightly more 3)Same 4)Slightly less 5)A lot less [less than half as much] 6)DON'T KNOW 7)REFUSED | E81: =LEN(D81) | F81: هل تغير دخل أسرتك من {income_sec} في الأشهر الثلاثة الماضية مقارنة بنفس الفترة من العام الماضي؟ [المشغل: استجابة واحدة.] 1) أكثر بكثير [زاد بنسبة تزيد عن 50٪] 2) أكثر قليلا 3) نفس الشيء 4) أقل قليلاً 5) أقل بكثير [أقل من نصف الكمية] 6) لا أعرف 7) رفض الإجابة | G81: =LEN(F81) | H81: Single Choice | I81: NA | J81: NA | K81: Form Type - Buttons | L81: 1-7= income_third | M81: NA | N81: if income_sec_comp = 1-7, go to income_third | Q81: =1 | T81: yes | X81: 17.261402 | Y81: =IF(X81="","",X81*Q81) | Z81: 17.26140213012695
Q82: =1 | Y82: =IF(X82="","",X82*Q82) | Z82: =IF(T82="yes",Y82,"")
A83: =A81+1 | B83: income_third | C83: income_third | D83: What was your household's third most important source of income in the past 3 months? [OPERATOR: SINGLE RESPONSE. DON'T KNOW AND REFUSED OPTIONS SHOULD BE AVOIDED AS MUCH AS POSSIBLE.] 1)Production and sale of staple crops 2)Production and sale of vegetables or fruit 3)Production and sale of cashcrops 4)Production and sale of livestock or livestock products 5)Production and sale of honey or bee products 6)Production and sale of fish or aquatic products 7)Collection and sale of forestry or bush products 8)Agricultural trade EXCLUDING producers [formal and informal] 9)Daily wage on farms and other casual employment in agricultural sector 10)Stable employment in agricultural sector 11)Non-agricultural self-employed or liberal profession / doctor / architect / lawyer / including restaurant 12)Off-farm daily wages and other non-agricultural casual employment 13)Stable employment in non-agricultural sector 14)Public employment 15)Income not derived from work / Charity 16)Income not derived from work / Welfare transfer, pension, humanitarian aid 17)Income not derived from work / Remittances 18)Income not derived from work / Income from other rents 19)No third most important source of income 20)DON'T KNOW 21)REFUSED | E83: =LEN(D83) | F83: ما هو ثالث أهم مصدر دخل لأسرتك فى الثلاثة أشهر الماضية ؟ [المشغل: استجابة واحدة. يجب تجنب خيارات الإجابة "لا أعرف" و "رفض الإجابة" قدر الإمكان.] 1) إنتاج وبيع المحاصيل الأساسية 2) إنتاج وبيع الخضار أو الفاكهة 3) إنتاج وبيع المحاصيل النقدية 4) إنتاج وبيع الحيوانات الأليفة أو منتجاتها 5) انتاج و بيع العسل أو منتجات النحل 6) إنتاج وبيع الأسماك أو منتجات المنتجات المائية 7) جمع وبيع منتجات الغابات أو الأحراش 8) التجارة الزراعية الرسمية و غير الرسمية باستثناء المنتجين 9) الأجر اليومي في المزارع وغيرها من العمالة العرضية في قطاع الزراعة 10) العمالة المستقرة في القطاع الزراعي 11) العاملين لحسابهم الخاص غير الزراعيين أو المهنة الحرة / طبيب / مهندس معماري / محامٍ / بما في ذلك مطعم 12) الأجور اليومية خارج المزرعة وغيرها من العمالة العرضية غير الزراعية 13) العمالة المستقرة في القطاع غير الزراعي 14) الوظائف العامة 15) الدخل غير المستمد من العمل / الاعمال الخيرية 16) الدخل غير المستمد من العمل / المدفوعات التحويلية ، المعاش التقاعدي ، المساعدات الإنسانية 17) الدخل غير المستمد من العمل / التحويلات 18) الدخل غير المستمد من العمل / الدخل من الإيجارات الأخرى 19) لم يكن هناك مصدر دخل ثالث 20) لا أعرف 21) رفض الإجابة | G83: =LEN(F83) | H83: Single Choice | I83: NA | J83: NA | K83: Form Type - Buttons exclude selected "income_main" exclude selected "income_sec" IsDemographic | L83: 1-3 = income_third_crop_check 4 = income_third_ls_check 5 = income_third_comp OR optional question 6 = income_third_fish_check 7-18 = income_third_comp OR optional question 19-21 = shock | M83: NA | N83: if options #1-3 selected, go to income_third_crop_check if options #4 selected, go to income_third_ls_check if option #6 selected, go to income_third_fish_check if options #5, 7-18 selected, go to [income_third_comp OR optional question] if options #19-21 selected, go to shock | O83: income_third_gender | Q83: =1 | T83: yes | X83: 14.475392 | Y83: =IF(X83="","",X83*Q83) | Z83: 14.47539234161377
B84: income_third_crop_check | C84: income_third_crop_check | D84: Are the crops sold also produced by you or anyone in your household? [OPERATOR: SINGLE RESPONSE.] 1)YES 2)NO 3)DON'T KNOW 4)REFUSED | E84: =LEN(D84) | F84: هل تم إنتاج المحاصيل التي تبيعها أنت أو أي شخص في منزلك أيضًا؟ [المشغل: استجابة واحدة.] 1) نعم 2) لا 3) لا أعرف 4) رفض الإجابة | G84: =LEN(F84) | H84: Single Choice | I84: NA | J84: NA | K84: Form Type - Buttons | L84: 1-4 = income_third_comp OR optional question | M84: NA | N84: if income_third_crop_check = 1-4, go to [income_third_comp OR optional question] | O84: 1-4 = income_third_gender | Q84: =1 | T84: yes | X84: 8 | Y84: =IF(X84="","",X84*Q84) | Z84: 8
B85: income_third_ls_check | C85: income_third_ls_check | D85: Are the livestock or livestock products sold also produced by you or anyone in your household? [OPERATOR: SINGLE RESPONSE.] 1)YES 2)NO 3)DON'T KNOW 4)REFUSED | E85: =LEN(D85) | F85: هل تم إنتاج المواشي ومنتجاتها التي تبيعها أنت أو أي شخص في منزلك أيضًا؟ [المشغل: استجابة واحدة.] 1) نعم 2) لا 3) لا أعرف 4) رفض الإجابة | G85: =LEN(F85) | H85: Single Choice | I85: NA | J85: NA | K85: Form Type - Buttons | L85: 1-4 = income_third_comp OR optional question | M85: NA | N85: if income_third_ls_check = 1-4, go to [income_third_comp OR optional question] | O85: 1-4 = income_third_gender | Q85: =1 | T85: yes | X85: 8 | Y85: =IF(X85="","",X85*Q85) | Z85: 8
B86: income_third_fish_check | C86: income_third_fish_check | D86: Are the fish or aquatic products sold also captured/harvested by you or anyone in your household? [OPERATOR: SINGLE RESPONSE.] 1)YES 2)NO 3)DON'T KNOW 4)REFUSED | E86: =LEN(D86) | F86: هل الأسماك أو المنتجات المائية التي تُباع تم أيضًا صيدها أو جمعها بواسطتك أو أي شخص في منزلك؟ [المشغل: استجابة واحدة.] 1) نعم 2) لا 3) لا أعرف 4) رفض الإجابة | G86: =LEN(F86) | H86: Single Choice | I86: NA | J86: NA | K86: Form Type - Buttons | L86: 1-4 = income_third_comp OR optional question | M86: NA | N86: if income_third_fish_check = 1-4, go to [income_third_comp OR optional question] | O86: 1-4 = income_third_gender | Q86: =1 | T86: yes | X86: 8 | Y86: =IF(X86="","",X86*Q86) | Z86: 8
Q87: =1 | Y87: =IF(X87="","",X87*Q87) | Z87: =IF(T87="yes",Y87,"")
A88: 18 | B88: income_third_gender | C88: income_third_gender | D88: What is the gender of the household member[s] generating income from this source? [OPERATOR: SINGLE RESPONSE.] 1)Male 2)Female 3)Joint [both male & female] 4)DON'T KNOW 5)REFUSED | E88: =LEN(D88) | F88: ما هو جنس الفرد ( الأفراد ) داخل الاسرة الذين يحصلون علي الدخل من هذا المصدر ؟ [المشغل: استجابة واحدة.] 1) ذكر 2) أنثى 3) مختلط ( ذكر و أنثى ) 4) لا أعرف 5) رفض الإجابة | G88: =LEN(F88) | H88: Single Choice | I88: NA | J88: NA | K88: Form Type - Buttons | L88: 1-5 = income_third_comp or optional question | M88: NA | N88: if income_third_gender = 1-5, go to [income_third_comp or optional question] | O88: 1-5 = income_third_comp | Q88: =1 | T88: no | X88: 4.7874017 | Y88: =IF(X88="","",X88*Q88)
Q89: =1 | Y89: =IF(X89="","",X89*Q89) | Z89: =IF(T89="yes",Y89,"")
A90: =#REF!+1 | B90: income_third_comp | C90: income_third_comp | D90: Has your household's income from {income_third} changed in the last 3 months compared to the same period of last year? [OPERATOR: SINGLE RESPONSE.] 1)A lot more [increased by more than 50%] 2)Slightly more 3)Same 4)Slightly less 5)A lot less [less than half as much] 6)DON'T KNOW 7)REFUSED | E90: =LEN(D90) | F90: هل تغير دخل أسرتك من {income_third} في الأشهر الثلاثة الماضية مقارنة بنفس الفترة من العام الماضي؟ [المشغل: استجابة واحدة.] 1) أكثر بكثير [زاد بنسبة تزيد عن 50٪] 2) أكثر قليلا 3) نفس الشيء 4) أقل قليلاً 5) أقل بكثير [أقل من نصف الكمية] 6) لا أعرف 7) رفض الإجابة | G90: =LEN(F90) | H90: Single Choice | I90: NA | J90: NA | K90: Form Type - Buttons | L90: 1-7= shock | M90: NA | N90: if income_third_comp = 1-7, go to shock | O90: 1-7 = o_debt | Q90: =1 | T90: yes | X90: 15.876503 | Y90: =IF(X90="","",X90*Q90) | Z90: 15.87650299072266
B91: o_debt | C91: Have you incurred any new debt in the past three months which you have not repaid? [OPERATOR: SINGLE RESPONSE.] 1)YES 2)NO 3)DON’T KNOW 4)REFUSED | D91: Have you incurred any new debt in the past three months which you have not repaid? [OPERATOR: SINGLE RESPONSE.] 1)YES 2)NO 3)DON’T KNOW 4)REFUSED | F91: هل تكبدت أي ديون جديدة في الأشهر الثلاثة الماضية لم تسددها؟ [المشغل: استجابة واحدة.] 1) نعم 2) لا 3) لا أعرف 4) رفض الإجابة | H91: Single Choice | L91: 1 = o_debt_amount; 2-4 = shock | O91: 1 = o_debt_amount; 2-4 = shock | Q91: =1 | Y91: =IF(X91="","",X91*Q91)
B92: o_debt_amount | D92: What is the total amount of debt you currently have [in Rial]? [OPERATOR: DOUBLE CHECK FOR OUTLIERS & MAKE SURE THE INFORMATION IS RECORDED IN THE CORRECT CURRENCY. ENTER 8888888 FOR DON'T KNOW AND 9999999 FOR REFUSED.] | F92: ما هو المبلغ الإجمالي للديون التي عليك حاليًا [بالريال]؟ [المُشغل: تحقق مزدوج من القيم المتطرفة وتأكد من تسجيل المعلومات بالعملة الصحيحة. أدخل 8888888 للا أعرف و 9999999 في حالة الرفض.] | H92: Range | L92: Any response go to shock | O92: Any response go to shock | P92: Debt minimum: YER 1000 Debt Maximum: YER 1000000
A93: =#REF!+1 | B93: shock | C93: shock_ 1) shock_noshock 2) shock_sicknessordeathofhh 3) shock_lostemplorwork 4) shock_otherintrahhshock 5) shock_higherfoodprices 6) shock_higherfuelprices 7) shock_mvtrestrict 8) shock_othereconomicshock 9) shock_pestoutbreak 10) shock_plantdisease 11) shock_animaldisease 12) shock_napasture 13) shock_othercropandlivests 14) shock_coldtemporhail 15) shock_flood 16) shock_hurricane 17) shock_drought 18) shock_earthquake 19) shock_landslides 20) shock_firenatural 21) shock_othernathazard 22) shock_violenceinsecconf 23) shock_theftofprodassets 24) shock_firemanmade 25) shock_othermanmadehazard 26) shock_dk 27) shock_ref | D93: Has your household or community faced any particular disaster or crisis affecting your household's ability to raise an income and/or to produce food for self consumption in the last 3 months, and if so, which one[s]? [OPERATOR: SELECT RELEVANT SHOCKS EXPERIENCED BY THE HOUSEHOLD. MULTIPLE RESPONSES POSSIBLE. REFER TO ECONOMIC SHOCKS, CROP AND LIVESTOCK SHOCKS, INTRA-HOUSEHOLD SHOCK, NATURAL HAZARDS AND HUMAN-INDUCED HAZARDS.] 1)No shock 2)Sickness or accident or death of household member[s] [sickness of breadwinner / unusually high medical expenditure / funeral expenses / death of breadwinner] 3)Lost employment or working opportunities [not due to illness/accident] 4)Other intra-household shock 5)Unusually high food prices 6)Unusually high fuel prices or transport prices 7)Population movement restrictions [e.g. due to epidemic or infrastructure damage] 8)Other economic shock 9)Pest outbreak 10)Plant disease 11)Animal disease [affecting many animals] or death 12)Lack of physical access to pasture 13)Other crop and livestock shock 14)Cold temperatures or hail 15)Flood / riverbank erosion 16)Hurricane / cyclone / tornado 17)Drought / heat stress 18)Earthquake 19)Landslides 20)Fire from natural disaster 21)Other natural hazard 22)Violence and insecurity / conflict 23)Theft of production assets [land / livestock / tools / etc] 24)Fire from human-induced disaster 25)Other human-induced hazard 26)DON'T KNOW 27)REFUSED | E93: =LEN(D93) | F93: هل واجهت أسرتك أو هل واجه مجتمعك أي كارثة أو أزمة معينة أثرت على قدرة أسرتك على إدرار الدخل و / أو إنتاج الغذاء للاستهلاك الذاتي في الأشهر الثلاثة الماضية ، وإذا كان الأمر كذلك ، فما كانت؟ [المُشغل: حدد الصدمات ذات الصلة التي اختبرتها الأسرة. استجابات متعددة ممكنة. راجع الصدمات الاقتصادية والصدمات التي تصيب المحصول والمواشي و داخل الأسرة والمخاطر الطبيعية والأخطار التي يسببها الإنسان.] 1) لا صدمة 2) مرض أو حادث أو وفاة أحد أفراد الأسرة [مرض العائل / النفقات الطبية المرتفعة بشكل غير عادي / نفقات الجنازة / وفاة العائل] 3) فرص العمل أو العمل المفقودة [ليس بسبب مرض / حادث] 4) صدمة أخرى داخل الأسرة 5) أسعار المواد الغذائية أعلى بكثير من المعتاد 6) أسعار الوقود أو أسعار النقل أعلى بكثير من المعتاد 7) القيود المفروضة على حركة السكان [على سبيل المثال بسبب الوباء أو تلف البنية التحتية] 8) صدمة اقتصادية أخرى 9) تفشي الآفات 10) أمراض نباتية 11) أمراض حيوانية تصيب العديد من الحيوانات أو تتسبب بنفقها 12) عدم إمكانية الوصول للمراعي 13) صدمة أخرى للمحاصيل والماشية 14) درجات الحرارة الباردة أو البرد 15) الفيضانات / تآكل ضفاف الأنهار 16) إعصار 17) الجفاف / الإجهاد الحراري 18) زلزال 19) الانهيارات الارضية 20) حريق مسبب من كارثة طبيعية 21) مخاطر طبيعية أخرى 22) العنف وانعدام الأمن / النزاع 23) سرقة أصول الإنتاج [الأرض / الماشية / الأدوات / إلخ] 24) حريق مسبب من كارثة من صنع الإنسان 25) مخاطر أخرى من صنع الإنسان 26) لا أعرف 27) رفض الإجابة | G93: =LEN(F93) | H93: Select All That Apply | I93: NA | J93: NA | K93: Form Type - Checklist 1,26,27 = IsNone | L93: 1-27 = [confl_wellbeing] | M93: 1)shock_noshock 2)shock_sicknessordeathofhh 3)shock_lostemplorwork 4)shock_otherintrahhshock 5)shock_higherfoodprices 6)shock_higherfuelprices 7)shock_mvtrestrict 8)shock_othereconomicshock 9)shock_pestoutbreak 10)shock_plantdisease 11)shock_animaldisease 12)shock_napasture 13)shock_othercropandlivests 14)shock_coldtemporhail 15)shock_flood 16)shock_hurricane 17)shock_drought 18)shock_earthquake 19)shock_landslides 20)shock_firenatural 21)shock_othernathazard 22)shock_violenceinsecconf 23)shock_theftofprodassets 24)shock_firemanmade 25)shock_othermanmadehazard 26)shock_dk 27)shock_ref | N93: if shock = 1-27, go to [confl_wellbeing] | O93: 1-27 = confl_wellbeing | Q93: =1 | T93: yes | X93: 37.85363 | Y93: =IF(X93="","",X93*Q93) | Z93: 37.85363006591797
A94: CONFLICT MODULE | Y94: =IF(X94="","",X94*Q94) | Z94: =IF(T94="yes",Y94,"")
B95: confl_wellbeing | C95: confl_wellbeing 1)confl_wb_none 2)confl_wb_livelihood 3)confl_wb_health 4)confl_wb_transport 5)confl_wb_edu 6)confl_wb_food_water 7)confl_wb_safety 8)confl_wb_land_sec 9)confl_wb_lack_justice 10)confl_wb_corrupt 11)confl_wb_lack_gov 12)confl_wb_assistance 13)confl_wb_other 14)confl_wb_dk 15)confl_wb_ref | D95: What are the main problems affecting the community's wellbeing? [OPERATOR: UP TO THREE RESPONSES ALLOWED] 1)There are no issues or concerns 2)Employment / livelihoods [lack of or inadequate] 3)Health care [lack of or inadequate] 4)Transportation [lack of or inadequate] 5)Education [lack of or inadequate] 6)Access to food/water [lack of or inadequate] 7)Security and safety of family members [lack of or inadequate] 8)Security of land or property [lack of or inadequate] 9)Lack of justice 10)Corruption 11)Lack of governance 12)Accessing or receiving assistance 13)Other [specify] 14)DON'T KNOW 15)REFUSED | E95: =LEN(D95) | F95: ما هي المشاكل الرئيسية التي تؤثر على تحسين حال المجتمع؟ [المشغل: مسموح بثلاث إجابات كحد أقصى] 1) لا توجد مشكلات أو مخاوف 2) التوظيف / سبل العيش [نقص أو عدم كفاية] 3) الرعاية الصحية [نقص أو عدم كفاية] 4) وسائل النقل [نقص أو عدم كفاية] 5) التعليم [نقص أو عدم كفاية] 6) الوصول إلى الغذاء / المياه [نقص أو عدم كفاية] 7) أمن وسلامة أفراد الأسرة [نقص أو عدم كفاية] 8) أمان الأرض أو الممتلكات [نقص أو عدم كفاية] 9) نقص العدالة 10) الفساد 11) عدم الحوكمة 12) الوصول إلى المساعدة أو تلقيها 13) آخر [حدد] 14) لا أعرف 15) رفض الإجابة | G95: =LEN(F95) | H95: Select All That Apply | I95: NA | J95: NA | K95: Form Type - Checklist 1,14,15 = IsNone Min = 1 Max = 3 | L95: 1-15 = confl_yn | M95: 1)confl_wb_none 2)confl_wb_livelihood 3)confl_wb_health 4)confl_wb_transport 5)confl_wb_edu 6)confl_wb_food_water 7)confl_wb_safety 8)confl_wb_land_sec 9)confl_wb_lack_justice 10)confl_wb_corrupt 11)confl_wb_lack_gov 12)confl_wb_assistance 13)confl_wb_other 14)confl_wb_dk 15)confl_wb_ref | N95: For any response, go to confl_yn. | T95: no | AH95: Better if optional. Some options might be a bit sensitive in some contexts (e.g. corruption)
B96: confl_yn | C96: confl_yn | D96: Have you or anyone within your household been affected by any form of insecurity or conflict during the past 3 months? [OPERATOR: SINGLE RESPONSE.] 1)YES 2)NO 3)DON'T KNOW 4)REFUSED | E96: =LEN(D96) | F96: هل تأثرت أنت أو أي شخص في أسرتك بأي شكل من أشكال انعدام الأمن أو الصراع خلال الأشهر الثلاثة الماضية؟ 1)نعم 2)لا 3) لا أعرف 4) رفض الإجابة | G96: =LEN(F96) | H96: Single Choice | I96: NA | J96: NA | K96: Form Type - Buttons | L96: 1 = confl_prim_insec 2-4 = crp_intro | M96: NA | N96: if confl_yn = 1, go to confl_prim_insec. Otherwise, go to crp_intro | T96: yes | AH96: Better with 3 months recall period indeed
B97: confl_pimary_insec | C97: confl_prim_insec | D97: What has been the primary type of insecurity affecting your household? [OPERATOR: SINGLE RESPONSE.] 1)Disputes or conflicts over land, water or pasture 2)Criminality, gang violence or banditry 3)Conflict between community groups 4)Armed conflict 5)Disputes or conflicts over assistance being provided 6)Other [specify] 7)DON'T KNOW 8)REFUSED | E97: =LEN(D97) | F97: ما هو نوع عدم الأمان الرئيسي الذي يؤثر على أسرتك؟ [المشغل: إجابة واحدة.] 1) النزاعات حول الأرض أو المياه أو المراعي 2) الإجرام أو عنف العصابات أو اللصوصية 3) النزاعات/ الخلافات بين مجموعات المجتمع 4) النزاعات المسلحة أو الأعمال العدائية المسلحة 5) النزاعات أو الصراعات حول تقديم المساعدة 6) أخرى [حدد] 7) لا أعرف 8) رفض الإجابة | G97: =LEN(F97) | H97: Single Choice | I97: NA | J97: NA | K97: Form Type - Buttons | L97: 1-8 = confl_agri_imp | M97: NA | N97: if confl_prim_insec = 1-8, go to confl_agri_imp. | T97: no | AD97: In enumerator training, include explanation/examples of ''insecurity''
B98: confl_agri_imp | C98: confl_agri_imp 1)confl_agri_none 2)confl_agri_access_field 3)confl_agri_inputs 4)confl_agri_prod_asset 5)confl_agri_water_infra 6)confl_agri_crp_damage 7)confl_agri_crp_theft_occup 8)confl_agri_ls_reduce_mob 9)confl_agri_ls_damage 10)confl_agri_ls_theft 11)confl_agri_land_contam 12)confl_agri_extortion 13)confl_agri_other 14)confl_agri_dk 15)confl_agri_ref | D98: How has insecurity and/or conflict affected your household's farming, livestock or fishing activities? [OPERATOR: SELECT UP TO THREE IMPACTS.] 1)No effect on my household's agricultural activities 2)Could not access or limited access to fields/fishing areas 3)Could not access [or poor quality] inputs [seeds, fertiliser] 4)Damage or destruction of productive assets [tools, machinery] 5)Damage to water infrastructure and/or reduced access to water 6)Damage or destruction of crops 7)Theft/occupation of agricultural land 8)Reduced livestock mobility due to insecurity 9)Death or injury of livestock 10)Theft of livestock 11)Land contaminated by landmines and/or explosive remnants of war 12)Extortion [e.g. payments demanded by armed groups] 13)Other [specify] 14)DON'T KNOW 15)REFUSED | E98: =LEN(D98) | F98: كيف أثر انعدام الأمن على أنشطة الزراعة أو الثروة الحيوانية أو صيد السماك في أسرتك؟ [المشغل: حدد ما يصل إلى ثلاثة تأثيرات.] 1) لا يوجد تأثير على الأنشطة الزراعية لأسرتي 2) عدم القدرة على الوصول إلى الحقول/مناطق الصيد أو تقييد الوصول إليها 3) عدم القدرة على الوصول إلى المدخلات [البذور والأسمدة] [أو جودتها رديئة] 4) إتلاف أو تدمير الأصول الإنتاجية [الأدوات والآلات] 5) إتلاف البنية التحتية للمياه و/أو انخفاض الوصول إلى المياه 6) إتلاف أو تدمير المحاصيل 7) سرقة/احتلال الأراضي الزراعية 8) تقليل حركة الماشية بسبب انعدام الأمن 9) موت أو إصابة الماشية 10) سرقة الماشية 11) تلوث الأراضي بالألغام الأرضية و/أو آثار الحروب المتفجرة 12) الابتزاز [على سبيل المثال الجبايات التي تطالب بها الجماعات المسلحة] 13) أخرى [حدد] 14) لا أعرف 15) رفض الإجابة | G98: =LEN(F98) | H98: Open-Ended - Select All That Apply | I98: NA | J98: NA | K98: Form Type - Checklist 14,15 = IsNone Min = 1 Max = 3 | L98: 1-15 = confl_foodsec_imp | M98: 1)confl_agri_none 2)confl_agri_access_field 3)confl_agri_inputs 4)confl_agri_prod_asset 5)confl_agri_water_infra 6)confl_agri_crp_damage 7)confl_agri_crp_theft_occup 8)confl_agri_ls_reduce_mob 9)confl_agri_ls_damage 10)confl_agri_ls_theft 11)confl_agri_land_contam 12)confl_agri_extortion 13)confl_agri_other 14)confl_agri_dk 15)confl_agri_ref | N98: if confl_agri_imp = 1-15, go to confl_foodsec_imp. | T98: yes
B99: confl_foodsec_imp | C99: confl_foodsec_imp 1)confl_fs_none 2)confl_fs_high_cost 3)confl_fs_lack_food_mkt 4)confl_fs_access_mkt 5)confl_fs_reduced_income 6)confl_fs_access_assistance 7)confl_fs_theft_damage 8)confl_fs_illicit_pay 9)confl_fs_other 10)confl_fs_dk 11)confl_fs_ref | D99: How has insecurity affected your household's access to food? [OPERATOR: SELECT UP TO THREE IMPACTS.] 1)No effect on my access to food 2)High food costs 3)Lack of food in the markets 4)Difficult/dangerous to access markets 5)Reduced income to buy food 6)Difficult to access assistance [food, cash or vouchers] 7)Theft/damage to household food stores 8)Demands for illicit payments or taxes 9)Other [specify] 10)DON'T KNOW 11)REFUSED | E99: =LEN(D99) | F99: كيف أثر انعدام الأمن على قدرة أسرتك على الوصول إلى الغذاء؟ [المشغل: حدد ما يصل إلى ثلاثة تأثيرات.] 1) لا يوجد تأثير على قدرتي على الوصول إلى الغذاء 2) ارتفاع تكاليف الغذاء 3) نقص الغذاء في الأسواق 4) صعوبة/خطورة الوصول إلى الأسواق 5) انخفاض الدخل لشراء الغذاء 6) صعوبة الوصول إلى المساعدة [الغذائية أو النقدية أو القسائم] 7) سرقة/تلف مخازن الغذاء المنزلية 8) مطالبات بمدفوعات أو ضرائب غير مشروعة 9) أخرى [حدد] 10) لا أعرف 11) رفض الإجابة | G99: =LEN(F99) | H99: Open-Ended - Select All That Apply | I99: NA | J99: NA | K99: Form Type - Checklist 10,11 = IsNone Min = 1 Max = 3 | L99: 1-11 = crp_intro | M99: 1)confl_fs_none 2)confl_fs_high_cost 3)confl_fs_lack_food_mkt 4)confl_fs_access_mkt 5)confl_fs_reduced_income 6)confl_fs_access_assistance 7)confl_fs_theft_damage 8)confl_fs_illicit_pay 9)confl_fs_other 10)confl_fs_dk 11)confl_fs_ref | N99: if confl_foodsec_imp = 1-11, go to crp_intro. | T99: no
Q100: =1 | Y100: =IF(X100="","",X100*Q100) | Z100: =IF(T100="yes",Y100,"")
...

Sheet Crop list
C3: Select top 10 crops | D3: GeoPoll code | E3: Dataset code | F3: Label (EN) | G3: Label (AR)
D4: {=_xlfn.SEQUENCE(90,1,1,1)} | E4: 1.1 | F4: Rice | G4: الرز
C5: x | D5: 2 | E5: 1.2 | F5: Wheat | G5: القمح
C6: x | D6: 3 | E6: 1.3 | F6: Millet | G6: الدخن
C7: x | D7: 4 | E7: 1.4 | F7: Sorghum | G7: الذرة الرفيعة
D8: 5 | E8: 1.5 | F8: Maize | G8: الذرة
D9: 6 | E9: 1.6 | F9: Barley | G9: الشعير
D10: 7 | E10: 1.99 | F10: Other Cereal | G10: الحبوب الأخرى
D11: 8 | E11: 2.1 | F11: Cassava | G11: الكسافا
C12: x | D12: 9 | E12: 2.2 | F12: Potatoe | G12: البطاطا
D13: 10 | E13: 2.3 | F13: Sweet Potatoes | G13: البطاطا الحلوة
D14: 11 | E14: 2.4 | F14: Yams | G14: اليام
D15: 12 | E15: 2.5 | F15: Carrots | G15: الجزر
D16: 13 | E16: 2.6 | F16: Cocoyam | G16: القلقاس
D17: 14 | E17: 2.99 | F17: Other tubers | G17: الدرنات الأخرى
D18: 15 | E18: 3.1 | F18: Beans | G18: الفاصوليا
C19: x | D19: 16 | E19: 3.2 | F19: Lentils | G19: العدس
D20: 17 | E20: 3.3 | F20: Peas | G20: البازيلاء
D21: 18 | E21: 3.4 | F21: Soybeans | G21: فول الصويا
D22: 19 | E22: 3.5 | F22: Chickpeas | G22: الحمص
D23: 20 | E23: 3.6 | F23: Fava beans | G23: الفول
D24: 21 | E24: 3.7 | F24: Broad beans | G24: الفاصوليا العريضة
D25: 22 | E25: 3.99 | F25: Other pulses | G25: البقول الاخرى
D26: 23 | E26: 4.1 | F26: Cabbage | G26: الملفوف
D27: 24 | E27: 4.2 | F27: Lettuce | G27: الخس
D28: 25 | E28: 4.3 | F28: Spinach-Amaranth | G28: السبانخ - القطيفة
D29: 26 | E29: 4.4 | F29: Cassava leaves | G29: أوراق الكسافا
D30: 27 | E30: 4.5 | F30: Potatoe leaves | G30: أوراق البطاطا
D31: 28 | E31: 4.6 | F31: Moringa | G31: المورينجا
... D35: 32 | E35: 4.99 | F35: Other leafy vegetables | G35: الخضار الورقية الأخرى
C36: x | D36: 33 | E36: 5.1 | F36: Tomatoes | G36: الطماطم
D37: 34 | E37: 5.2 | F37: Cucumber | G37: الخيار
D38: 35 | E38: 5.3 | F38: Pumpkin | G38: اليقطين
D39: 36 | E39: 5.4 | F39: Eggplant/aubergine | G39: الباذنجان
D40: 37 | E40: 5.5 | F40: Zucchini | G40: الكوسة
C41: x | D41: 38 | E41: 5.6 | F41: Okra | G41: البامية
D42: 39 | E42: 5.7 | F42: Bell pepper | G42: الفلفل حلو
D43: 40 | E43: 5.8 | F43: Onions | G43: بصل
D44: 41 | E44: 5.9 | F44: Haricot | G44: اللوبياء
D45: 42 | E45: 5.101 | F45: Green peas | G45: البازلاء الخضراء
D46: 43 | E46: 5.11 | F46: Fava beans green | G46: الفول الأخضر
D47: 44 | E47: 5.99 | F47: Other non leafy vegs | G47: الخضار غير الورقية الأخرى
C48: x | D48: 45 | E48: 6.1 | F48: Orange | G48: البرتقال
D49: 46 | E49: 6.2 | F49: Lemon | G49: الليمون
D50: 47 | E50: 6.3 | F50: Grapefruit | G50: الجريب فروت
D51: 48 | E51: 6.4 | F51: Mandarins/clementines | G51: اليوسفي / الكليمنتين
D52: 49 | E52: 6.99 | F52: Other citrus fruit | G52: الحمضيات الأخرى
D53: 50 | E53: 7.1 | F53: Sweet Banana | G53: الموز
D54: 51 | E54: 7.2 | F54: Plantains | G54: موز الجنة
D55: 52 | E55: 7.3 | F55: Papaya | G55: البابايا
D56: 53 | E56: 7.4 | F56: Mango | G56: المانجو
D57: 54 | E57: 7.5 | F57: Guava | G57: الجوافة
D58: 55 | E58: 7.6 | F58: Pineapple | G58: الأناناس
D59: 56 | E59: 7.7 | F59: Avocado | G59: الأفوكادو
D60: 57 | E60: 7.8 | F60: Water Melon | G60: البطيخ الأحمر
... D62: 59 | E62: 7.101 | F62: Figs | G62: التين
C63: x | D63: 60 | E63: 7.11 | F63: Grapes | G63: العنب
D64: 61 | E64: 7.12 | F64: Olives | G64: الزيتون
D65: 62 | E65: 7.13 | F65: Apple | G65: التفاح
D66: 63 | E66: 7.14 | F66: Apricot | G66: المشمش
D67: 64 | E67: 7.15 | F67: Cherries | G67: الكرز
D68: 65 | E68: 7.16 | F68: Peach/nectarine | G68: الدراق / النكتارين
D69: 66 | E69: 7.17 | F69: Strawberries | G69: الفراولة
D70: 67 | E70: 7.18 | F70: Melon [Cantaloupe] | G70: الشمام
D71: 68 | E71: 7.99 | F71: Other fruit | G71: الفواكه الأخرى
D72: 69 | E72: 8.1 | F72: Coconuts | G72: جوز الهند
D73: 70 | E73: 8.2 | F73: Groundnut/peanut | G73: الفول السوداني
D74: 71 | E74: 8.3 | F74: Cashew Nut | G74: الكاجو
D75: 72 | E75: 8.4 | F75: Kola Nut | G75: جوز الكولا
... D81: 78 | E81: 9.1 | F81: Cocoa | G81: الكاكاو
C82: x | D82: 79 | E82: 9.2 | F82: Coffee | G82: القهوة
D83: 80 | E83: 9.3 | F83: Tea | G83: الشاي
D84: 81 | E84: 9.4 | F84: Sugarcane | G84: قصب السكر
D85: 82 | E85: 9.5 | F85: Sunflower | G85: دوار الشمس
D86: 83 | E86: 9.99 | F86: Other food cash crop | G86: المحاصيل الغذائية النقدية الأخرى
D87: 84 | E87: 10.1 | F87: Cotton | G87: القطن
D88: 85 | E88: 10.2 | F88: Rubber | G88: المطاط
D89: 86 | E89: 10.3 | F89: Jute | G89: الجوت
D90: 87 | E90: 10.4 | F90: Fodder | G90: العلف
D91: 88 | E91: 10.5 | F91: Tobacco | G91: التبغ
C92: x | D92: 89 | E92: 10.6 | F92: Qat | G92: القات
D93: 90 | E93: 10.99 | F93: Other non-food cash crop | G93: المحاصيل النقدية غير الغذائية الأخرى

Sheet Additional information
C2: Original | D2: Replacement (EN) | E2: Replacement (AR) | F2: Comment (EN) | G2: Comment (AR) | H2: Example (EN) | I2: Example (AR)
B3: FOR CORE QUESTIONS . (Mandatory to fill out) . | C3: ADMIN1 | D3: Governorate | E3: محافظة | F3: The first subdivision of the country, after national level; region; province; governorate; etc. | G3: التقسيم الأول للبلاد ، بعد المستوى الوطني ؛ منطقة؛ محافظة؛ ولاية ؛ إلخ. | H3: region | I3: منطقة
C4: ADMIN2 | D4: District | E4: مديرية | F4: The second subdivision of the country; district; municipality; LGA; etc. | G4: التقسيم الثاني للبلاد ؛ قضاء؛ بلدية؛ إلخ. | H4: district | I4: قضاء
C5: reference year | D5: last year | E5: العام الماضي | F5: Comparison questions will need need a reference year. Select whether you want to use "last year" or "a normal year" as a baseline. A "normal year" should refers to an average year from the past 5 years - make sure to train the enumerators accordingly. | G5: سوف تحتاج أسئلة المقارنة إلى سنة مرجعية. حدد ما إذا كنت تريد استخدام "العام الماضي" أو "العام العادي" كخط أساس. يجب أن يشير "العام العادي" إلى متوسط ​​عام من السنوات الخمس الماضية - تأكد من تدريب جامعي البيانات وفقًا لذلك. | H5: a normal year | I5: العام العادي
C6: season | D6: Ongoing season | E6: الموسم الحالي | F6: Name the crop season(s) of interest if there are several cropping seasons in the country (e.g. Meher and Belg in Ethiopia, rainy season / flood-recession cropping / irrigated dry season in the Sahel). You can refer to the “last season” or “ongoing season". | G6: قم بتسمية موسم (مواسم) المحاصيل ذات الأهمية إذا كان هناك عدة مواسم محصولية في البلد (على سبيل المثال ، Meher و Belg في إثيوبيا ، موسم الأمطار / محاصيل الركود بسبب الفيضانات / موسم الجفاف المروي في منطقة الساحل). يمكنك الرجوع إلى "الموسم الماضي" أو "الموسم الجاري". | H6: wet season | I6: موسم الأمطار
C7: season phase | D7: Growth | E7: النمو | F7: Indicate the phase of the season at the time of data collection. If the harvest from the season has not yet occurred, the question on crop harvest (crp_harv_change) will include the word “expected” (where #expected or nothing# is located). If the harvest has occured, "expected" will not be inserted in the question. | G7: حدد مرحلة الموسم في وقت جمع البيانات. إذا لم يتم الحصاد من الموسم بعد ، فإن السؤال عن حصاد المحاصيل (crp_harv_change) سيتضمن كلمة "متوقع" (حيث يوجد # متوقع أو لا شيء #). إذا تم الحصاد ، لن يتم إدخال "متوقع" في السؤال . | H7: Harvesting | I7: الحصاد
C8: local measurement unit | D8: 5)Labneh 6)Qassabh 7)Hablah 8)Ma'ad 9)Salook 10)Shaklah 11)Neiha 12)Matreh 13)Wadan 14)Oqum 15)Asaoo 16)Shagan 17)Arfad 18)Aber 19)Taleem 20)Magabi 21)Hediah 22)Thera'a 23)Materah | E8: 5)لبنة 6)قصبة 7) حبل/حبلة 8) معاد 9)سلوق 10) شكلة 11) نيحة 12) مطرح 13)ودن 14) عقم 15)اسعاو 16) شجن 17)رفد/ارفاد 19) عبر 20) تليم 21)مجابي 22) حدية 23) ذراع 24) مطبرة | F8: Specify the local measurement unit for land size, other than acres, hectares, square meters and square feet. If no other unit of measurement is needed, keep this cell blank. | G8: حدد وحدة القياس المحلية لمساحة الأرض ، بخلاف الفدان والهكتار والمتر المربع والقدم المربع. إذا لم تكن هناك حاجة إلى وحدة قياس أخرى ، احتفظ بهذه الخلية فارغة. | H8: Jeribs | I8: جريب
C9: local measurement unit conversion | F9: Include the conversion of the local measurement unit to hectares. In other words, how many local measurement units are in 1 ha. Only digits in Latin numbers should be inputted. | G9: قم بتضمين تحويل وحدة القياس المحلية إلى هكتار. بمعنى آخر ، إلى كم هو عدد وحدات القياس المحلية في هكتار واحد. يرجى إدخال الأرقام في الأبجدية اللاتينية (...3, 2, 1). | H9: 0.2 | I9: 0.2
B10: FOR OPTIONAL QUESTIONS . (Fill out if applicable) . | C10: currency | D10: Rial | E10: الريال | F10: The name of the main currency used nationally; USD; Naira; Rial; Pesos; etc. | G10: اسم العملة الرئيسية المستخدمة وطنيا ؛ دولار أمريكي؛ نيرة؛ الريال؛ بيزو؛ إلخ. | H10: Naira | I10: نيرة
C11: MIN AMOUNT | D11: Not applicable | E11: Not applicable | F11: The minimum amount for an income source should be set at 0 or any value below which it is not possible to do a transaction. For example, the smallest coin/banknote in a currency can be 1000, in which case you would set the minimum at 1000. Provide this input in the same currency as specified above. Only digits in Latin numbers should be inputted. | G11: يجب تعيين الحد الأدنى لمبلغ مصدر الدخل على 0 أو أي قيمة أقل منها لا يمكن إجراء معاملة. على سبيل المثال ، يمكن أن تكون أصغر عملة / ورقة نقدية في عملة ما هي 1000 ، وفي هذه الحالة يمكنك تعيين الحد الأدنى عند 1000. يجب أن يكون هذا المبلغ بنفس العملة المحددة في الصف أعلاه. يرجى إدخال الأرقام في الأبجدية اللاتينية (...3, 2, 1). | H11: 5 | I11: 5
C12: MAX AMOUNT | D12: Not applicable | E12: Not applicable | F12: Set the maximum amount for an income source over 3 months. Enumerators will not be able to input values above this amount in questions related to income amounts. Using previous representative surveys for this population, you can estimate this amount by using the mean income plus five (5) standard deviations, unless the country has high inflation. In the latter case, set the maximum value based on your country context (higher than the proposed approach). Provide this input in the same currency as specified above. Only digits in Latin numbers should be inputted. | G12: حدد الحد الأقصى لمبلغ مصدر الدخل على مدى 3 أشهر. لن يتمكن جامعي البيانات من إدخال قيم أعلى من هذا المبلغ في الأسئلة المتعلقة بمبالغ الدخل. باستخدام المسوح التمثيلية السابقة لهذه الفئة من السكان ، يمكنك تقدير هذا المبلغ باستخدام متوسط ​​الدخل بالإضافة إلى خمسة انحرافات معيارية ما لم يكن هناك تضخم مرتفع في الدولة. في الحالة الأخيرة ، قم بتعيين الحد الأقصى للقيمة بناءً على سياق بلدك (أعلى من النهج المقترح). يجب أن يكون هذا المبلغ بنفس العملة المحددة أعلاه. يرجى إدخال الأرقام في الأبجدية اللاتينية (...3, 2, 1). | H12: 5000000 | I12: 5000000
C13: THRESHOLD | D13: Not applicable | E13: Not applicable | F13: The threshold salary should be calculated to flag outliers (responses that look suspiciously high). Using previous representative surveys for this population, a good estimate is the average plus three (3) standard deviations, which should give the threshold for the 3 or 4% highest income values. Provide this input in the same currency as specified above. Only digits in Latin numbers should be inputted. | G13: يجب حساب قيمة العتبة للراتب لتحديد القيم المتطرفة (الاستجابات التي تبدو مرتفعة بشكل مثير للريبة). باستخدام المسوح التمثيلية السابقة لهذه الفئة من السكان ، فإن التقدير الجيد هو المتوسط ​​زائد ثلاثة انحرافات معيارية ، والذي يجب أن يعطي قيمة العتبة لقيم الدخل الأعلى بنسبة 3 أو 4٪. يجب أن يكون هذا المبلغ بنفس العملة المحددة أعلاه. يرجى إدخال الأرقام في الأبجدية اللاتينية (...3, 2, 1). | H13: 1200000 | I13: 1200000
C14: local vegetables | D14: tomatoes, okra, zucchini, cauliflower, cucumber, onions | E14: طماطم ، بامية ، كوسة ، قرنييط (زهرة) ، خيار ، بصل | F14: Input some common local vegetables [to be used as examples in the food consumption score indicator]. | G14: أدخل بعض الخضروات المحلية الشائعة [لاستخدامها كأمثلة في مؤشر درجة استهلاك الغذاء]. | H14: eggplants, zucchini, cauliflower | I14: باذنجان ، كوسة ، قرنبيط
C15: local fruits | D15: apple, orange, banana, grapes, mango, papaya, fig, muskmelon, red watermelon, dates | E15: التفاح / البرتقال ، الموز ، العنب ، المانجو ، البابايا ، التين ، الشمام ، البطيخ الاحمر ، البلح | F15: Input some common local fruits [to be used as examples in the food consumption score indicator]. | G15: أدخل بعض الفاكهة المحلية الشائعة [لاستخدامها كأمثلة في مؤشر درجة استهلاك الغذاء]. | H15: apples, bananas, oranges | I15: التفاح والموز والبرتقال
B17: FILL OUT FOR QUESTIONNAIRE DURATION ESTIMATION . | C17: Expected percentage of respondents cultivating crops | D17: 38.7% (Source: YEM10) | E17: 38.7% (Source: YEM10) | F17: If the survey is representative and has no quotas, write the proportion of rural households cultivating crops at country level, or if the survey follows a previous round with identical sample design, just report the percentage from the previous round. If you are using quotas, calculate the ratio of the quota over the minimum sample size at the level where the quota is implemented (so if you have a minimum sample size per strata of 110 with a quota of 100 crop producers, then it's 100/110 = 91% (the maximum you should write is 100%). | G17: إذا كان المسح تمثيليًا وليس له حصص نسبية ، فاكتب نسبة الأسر الريفية التي تزرع محاصيل على المستوى الوطني ، أو إذا كان المسح يتبع جولة سابقة بتصميم عينة متطابق ، فما عليك سوى الإبلاغ عن النسبة المئوية من الجولة السابقة. إذا كنت تستخدم نظام الحصص النسبية ، فاحسب نسبة الحصة إلى الحد الأدنى لحجم العينة على المستوى الذي يتم فيه تنفيذ الحصة (لذلك إذا كان لديك حد أدنى لحجم العينة لكل طبقة 110 مع حصة 100 منتج محصول ، فسيكون 100 / 110 = 91٪ (الحد الأقصى الذي يجب أن تكتبه هو 100٪). | H17: 0.91 | I17: 0.91
C18: Expected percentage of respondents raising livestock | D18: 44.7% (Source: YEM10) | E18: 44.7% (Source: YEM10) | F18: If the survey is representative and has no quotas, write the proportion of rural households raising livestock at country level, or if the survey follows a previous round with identical sample design, just report the percentage from the previous round. If you are using quotas, calculate the ratio of the quota over the minimum sample size at the level where the quota is implemented (so if you have a minimum sample size of 110 but a quota of 100 livestock producers, then it's 100/110 = 91% (the maximum you should write is 100%) | G18: إذا كان المسح تمثيليًا وليس له حصص نسبية ، فاكتب نسبة الأسر الريفية التي تربي الماشية على المستوى الوطني ، أو إذا كان المسح يتبع جولة سابقة بتصميم عينة متطابق ، فما عليك سوى الإبلاغ عن النسبة المئوية من الجولة السابقة. إذا كنت تستخدم نظام الحصص النسبية ، فاحسب نسبة الحصة إلى الحد الأدنى لحجم العينة على المستوى الذي يتم فيه تنفيذ الحصة (لذلك إذا كان لديك حد أدنى لحجم العينة لكل طبقة 110 مع حصة 100 مربي الماشية ، فسيكون 100 / 110 = 91٪ (الحد الأقصى الذي يجب أن تكتبه هو 100٪). | H18: 0.91 | I18: 0.91
C19: Expected percentage of respondents involved in fishery | D19: 2% (Source: YEM10) | E19: 2% (Source: YEM10) | F19: If the survey is representative and has no quotas, write the proportion of rural households involved in fisheries or aquaculture, otherwise if you are using quotas, calculate the ratio of the quota over the sample size at the level where the quota is implemented. (so if you haven't set a quota, and you expect to have a representative proportion of fishermen, just write the percentage of fishermen in the population you are targeting, in the example to the right, 5%) | G19: إذا كان المسح تمثيليًا وليس له حصص نسبية ، فاكتب نسبة الأسر الريفية العاملة في مصايد الأسماك أو تربية الأحياء المائية على المستوى الوطني. وإلا إذا كنت تستخدم الحصص النسبية ، فاحسب نسبة الحصة إلى حجم العينة على المستوى الذي يتم فيه تنفيذ الحصة. (لذلك إذا لم تحدد حصة ، وكنت تتوقع أن يكون لديك نسبة تمثيلية من الصيادين ، فاكتب فقط النسبة المئوية للصيادين من السكان الذين تستهدفهم ، في المثال على اليمين ، 5٪). | H19: 0.05 | I19: 0.05

Sheet Admin 2 info
A1: adm2_name | B1: adm2_name_local | C1: adm2_pcode | D1: adm1_name | E1: adm1_pcode | F1: adm0_name | G1: adm0_ISO3
A2: Ar Radmah | B2: الرضمة | C2: YE1103 | D2: Ibb | E2: YE11 | F2: Yemen | G2: YEM
A3: An Nadirah | B3: النادرة | C3: YE1104 | D3: Ibb | E3: YE11 | F3: Yemen | G3: YEM
A4: Ash Sha'ir | B4: الشعر | C4: YE1105 | D4: Ibb | E4: YE11 | F4: Yemen | G4: YEM
A5: Sibah | B5: سباح | C5: YE1205 | D5: Abyan | E5: YE12 | F5: Yemen | G5: YEM
A6: As Saddah | B6: السدة | C6: YE1106 | D6: Ibb | E6: YE11 | F6: Yemen | G6: YEM
A7: Al Makhadir | B7: المخادر | C7: YE1107 | D7: Ibb | E7: YE11 | F7: Yemen | G7: YEM
A8: Hubaysh | B8: حبيش | C8: YE1108 | D8: Ibb | E8: YE11 | F8: Yemen | G8: YEM
A9: Far Al Udayn | B9: فرع العدين | C9: YE1110 | D9: Ibb | E9: YE11 | F9: Yemen | G9: YEM
A10: Al Udayn | B10: العدين | C10: YE1111 | D10: Ibb | E10: YE11 | F10: Yemen | G10: YEM
A11: Jiblah | B11: جبلة | C11: YE1112 | D11: Ibb | E11: YE11 | F11: Yemen | G11: YEM
A12: Ba'dan | B12: بعدان | C12: YE1113 | D12: Ibb | E12: YE11 | F12: Yemen | G12: YEM
... A334: Al Qafr | B334: القفر | C334: YE1101 | D334: Ibb | E334: YE11 | F334: Yemen | G334: YEM
