Workbook

Sheet survey
A1: GeoPoll Submission Form
A2: FAO - Household Questionnaire | S2: Additional notes
A3: Q # | B3: Q Name | C3: Suggested Qname | D3: English | E3: Length | F3: fr_French | G3: Length | H3: sw_Swahili | I3: Length | J3: Q Type | K3: Randomize | L3: Conditional | M3: Programming Instructions | N3: Codes | O3: Skip Pattern | P3: GeoPoll Comments | Q3: Default skip patterns & conditional | R3: Specify skip pattern variable | T3: Estimated percentage of repondents | W3: Mandatory | AA3: Duration | AB3: Weighted duration | AC3: Core questions only
A4: A. PRESENTATION OF THE SURVEY AND ELIGIBILITY CRITERIA SELECTION | W4: no | AB4: =IF(AA4="","",AA4*Y4) | AC4: =IF(W4="yes",AB4,"")
A5: NA | B5: Optin | D5: Optin | E5: =LEN(D5) | F5: Optin | G5: =LEN(F5) | H5: optin | I5: =LEN(H5) | J5: Open Ended | K5: NA | L5: NA | M5: Form Type - TextBox | N5: NA | O5: Any Response = calldispo | Q5: NA | W5: no | AA5: 0 | AB5: =IF(AA5="","",AA5*T5) | AC5: =IF(W5="yes",AB5,"")
A6: NA | B6: calldispo | C6: calldispo | D6: Phone number: #CATI_MOBILENUMBER# 1)Someone answers 2)No answer 3)Refusal 4)Call back 5)Non-Working Number | E6: =LEN(D6) | F6: Numéro de téléphone: #CATI_MOBILENUMBER# 1)Quelqu’un répond 2)Pas de réponse 3)Refuse 4)Doit être rappelé 5)Numéro non fonctionnel | G6: =LEN(F6) | H6: Nambari ya simu: #CATI_MOBILENUMBER# 1)Mtu ana jibu 2)Hakuna jibu 3)Kukatala 4)Piga simu tena 5)Namba isiyofanya kazi | I6: =LEN(H6) | J6: Single Choice | K6: NA | L6: NA | M6: Form Type - Buttons | N6: NA | O6: 1 = resp_language 2 = NoAnswer 3 = Refusal 4 = WhenCallBack 5 = NonWorkingNumber | Q6: NA | W6: no | AA6: 14.695308 | AB6: =IF(AA6="","",AA6*T6) | AC6: =IF(W6="yes",AB6,"")
A7: NA | B7: NoAnswer | C7: calldispo_noanswer | D7: Phone rang and no one answered. Inclusive of voicemail, answering machine and temporary issues with network connection. | E7: =LEN(D7) | F7: Le téléphone a sonné et personne n'a répondu. Y compris la messagerie vocale, le répondeur et les problèmes temporaires de connexion au réseau. | G7: =LEN(F7) | H7: Simu iliita na hakuna wa ku pokea. | I7: =LEN(H7) | J7: NA | K7: NA | L7: NA | M7: NA | N7: NA | O7: End Poll NoAnswer | Q7: NA | W7: no | AA7: 0 | AB7: =IF(AA7="","",AA7*T7) | AC7: =IF(W7="yes",AB7,"")
A8: NA | B8: NonWorkingNumber | C8: calldispo_NonWorkingNumber | D8: Phone number is not in service, not working, or not valid. | E8: =LEN(D8) | F8: Le numéro de téléphone n'est pas en service, ne fonctionne pas ou n'est pas valide. | G8: =LEN(F8) | H8: Simu ilikata au haikutumike. | I8: =LEN(H8) | J8: NA | K8: NA | L8: NA | M8: NA | O8: End Poll NonWorkingNumber | Q8: NA | R8: NA
A9: NA | B9: resp_language | C9: resp_language | D9: Which language do you wish to proceed with? [OPERATOR: READ ANSWER CHOICES. SINGLE RESPONSE.] 1)English 2)French 3)Swahili | E9: =LEN(D9) | F9: Quelle langue souhaitez-vous utiliser? [OPÉRATEUR/OPÉRATRICE: LIRE LES CHOIX, RÉPONSE UNIQUE] 1)Anglais 2)Français 3)Swahili | G9: =LEN(F9) | H9: Unataka kuendelea na lugha gani? [OPERATOR: SOMA MAJIBU. CHAGUA JIBU MOJA.] 1)English 2)Kifaransa 3)Kiswahili | I9: =LEN(H9) | J9: Single Choice | K9: NA | L9: NA | M9: Form Type - Buttons | N9: NA | O9: 1 = introduction [English] 2 = introduction [French] 3 = introduction [Swahili] | Q9: For any response, go to introduction | S9: Insert most common national languages here [max 4 for translation with GeoPoll]. | W9: no | AA9: 3.1032724 | AB9: =IF(AA9="","",AA9*T9) | AC9: =IF(W9="yes",AB9,"")
A10: NA | B10: introduction | C10: introduction | D10: Hello sir/ma'am, my name is #OPERATOR#, and I am calling from GeoPoll Polling Agency on behalf of the Food and Agriculture Organization of the United Nations [FAO]. We are conducting a survey on household livelihoods and the ability to access food in your area. I would like to ask you some questions about your household. The survey usually takes 20-30 minutes to complete. Any information that you provide will be kept strictly confidential, only used for the purpose of the survey and will not be shown to other people. Your voluntary participation in the outcome of this interview is NOT IN ANY WAY linked to your personal chance of receiving any assistance. This is voluntary and you can choose not to answer any or all of the questions if you want. However, we hope that you will participate since your views are important. You will receive #TOPUP#! of communication credit as an incentive for the participation of the survey. Please note that this call may be recorded for quality purposes. Do you have any questions? [OPERATOR: ADDRESS QUESTIONS FROM RESPONDENT, IF ANY.] 1)CONTINUE | E10: =LEN(D10) | F10: Bonjour Monsieur/Madame, mon nom est #OPERATOR#. Je vous appelle de la part de l'agence de sondage GeoPoll pour le compte de l'Organisation des Nations Unies pour l'alimentation et l'agriculture [la FAO]. Nous menons une enquête sur les moyens d'existence et la capacité des ménages à accéder à la nourriture dans votre région. J'aimerais vous poser quelques questions sur votre ménage. L'enquête dure généralement entre 20-30 minutes. Toutes les informations que vous fournirez resteront strictement confidentielles; elles ne seront utilisées que dans le cadre de cette enquête et ne seront pas communiquées à d'autres personnes. Votre participation volontaire à cet entretien n'est en AUCUN CAS liée à la possibilité de recevoir une quelconque aide. Votre participation est volontaire et, si vous le souhaitez, vous pouvez choisir de ne pas répondre à une partie ou à la totalité des questions. Cependant, nous espérons que vous voudrez bien participer car votre avis est important. Vous recevrez #TOPUP#! de crédit téléphonique comme incitation à participer à l'enquête. Veuillez noter que cet appel peut être enregistré à des fins de contrôle qualité. Avez-vous des questions? [OPÉRATEUR/OPÉRATRICE: LE CAS ÉCHÉANT, RÉPONDRE AUX QUESTIONS DE LA PERSONNE INTERROGÉE.] 1)CONTINUER | G10: =LEN(F10) | H10: Habari bwana/mama, jina langu ni #OPERATOR#, napiga simu kutoka Shirika la Kupigia Kura la GeoPoll kwa niaba ya Shirika la Chakula na Kilimo la Umoja wa Mataifa [FAO]. Tunafanya utafiti kuhusu maisha ya kaya na uwezo ya kupata chakula katika eneo lako.Nilipenda kukuuliza baadhi ya maswali kuhusu kaya yako. Utafiti kwa kawaida huchukua dakika 20-30 kukamilika. Taarifa yote uta peleka itawekwa kwa siri kabisa, itatumika tu kwa madhumuni ya utafiti na haitaonyeshwa kwa watu wengine. Kushiriki kwako kwa hiari katika matokeo ya mahojiano haya HAUKUHUSIWI KWA NJIA YOYOTE na nafasi yako ya kibinafsi ya kupokea usaidizi wowote. Hili ni la hiari na unaweza kuchagua kutojibu yote au maswali yote ikiwa unataka. Hata hivyo, tunatumai kuwa utashiriki kwa kuwa maoni yako ni muhimu. Utapokea #TOPUP#! mikopo ya mawasiliano kama motisha ya ushiriki wa utafiti. Tafadhali kumbuka kuwa simu hii inaweza kurekodiwa kwa madhumuni ya ubora. Una maswali ? [OPERATOR: ANWANI MASWALI KUTOKA KWA MTAJIWA, IKIWA YAPO.] 1)ENDELEA | I10: =LEN(H10) | J10: Single Choice | K10: NA | L10: NA | M10: Form Type - Buttons | N10: NA | O10: 1 = Agree | Q10: For any response, go to Agree | S10: Set the amount of incentive here, if any. | W10: no | AA10: 37.418449 | AB10: =IF(AA10="","",AA10*T10) | AC10: =IF(W10="yes",AB10,"")
A11: NA | B11: Agree | C11: resp_agree | D11: Are you interested in participating in this survey? [OPERATOR: SINGLE RESPONSE] 1)Yes 2)Not now but another time in the week 3)No | E11: =LEN(D11) | F11: Souhaitez-vous participer à cette enquête? [OPÉRATEUR/OPÉRATRICE: RÉPONSE UNIQUE] 1)Oui 2)Pas maintenant mais à un autre moment de la semaine 3)Non | G11: =LEN(F11) | H11: Una nia ya kushiriki katika utafiti huu?_x000D_ _x000D_ [OPERATOR: JIBU MOJA]_x000D_ _x000D_ 1)Ndiyo_x000D_ 2)Sio sasa lakini wakati mwingine katika wiki_x000D_ 3)Hapana | I11: =LEN(H11) | J11: StartRecording | K11: NA | L11: NA | M11: Form Type - Buttons | N11: NA | O11: 1 = id_panel 2 = WhenCallBack 3 = resp_refusalwhy | Q11: if Agree = 1, go to id_panel OR resp_firstname if Agree = 2, go to WhenCallBack if Agree = 3, go to resp_refusalwhy | S11: It is highly recommended to include the question id_panel if a panelist approach is used. | T11: 1 | W11: no | AA11: 3.8059516 | AB11: =IF(AA11="","",AA11*T11) | AC11: =IF(W11="yes",AB11,"")
A12: NA | B12: id_panel | C12: id_panel | D12: Have you or any member of your household received a call on behalf of FAO regarding this topic in the past two years? [OPERATOR: SINGLE RESPONSE.] 1)YES 2)NO 3)DON'T KNOW | E12: =LEN(D12) | F12: Est-ce que vous ou un membre de votre ménage avez reçu un appel pour le compte de la FAO sur ce sujet au cours des deux dernières années? [OPÉRATEUR/OPÉRATRICE: RÉPONSE UNIQUE] 1)OUI 2)NON 3)NE SAIT PAS | G12: =LEN(F12) | H12: Je, wewe au mwanachama yeyote wa familia yako mmepokea simu kwa niaba ya FAO kuhusu mada hii katika miaka miwili iliyopita? [OPERATOR: JIBU MOJA.] 1)NDIYO 2)HAPANA 3)SIJUE | I12: =LEN(H12) | J12: Single Choice | K12: NA | L12: NA | M12: Form Type - Buttons | N12: NA | O12: 1-3 = resp_firstname | Q12: For any response, go to resp_firstname | T12: 1 | W12: no
A13: NA | B13: resp_refusalwhy | C13: resp_refusalwhy | D13: Please let us know why you have REFUSED to take the survey. [OPERATOR: SINGLE RESPONSE] 1)Not interested 2)Do not want to be recorded 3)Other [specify] | E13: =LEN(D13) | F13: Pourriez-vous m'indiquer pourquoi vous refusez de répondre à l'enquête. [OPÉRATEUR/OPÉRATRICE: RÉPONSE UNIQUE] 1)Pas intéressé 2)Ne veut pas être enregistré 3)Autre [préciser] | G13: =LEN(F13) | H13: Tafadhali tufahamishe kwa nini UMEKUKATALA kufanya uchunguzi. [OPERATOR: JIBU MOJA] 1)Sipendezwi 2)Sitaki kurekodiwa 3)Yingine [taja] | I13: =LEN(H13) | J13: Open Ended-Single Choice | K13: NA | L13: NA | M13: Form Type - RadioList | N13: NA | O13: 1-3 = Refusal | Q13: For any response, go to Refusal | T13: 1 | W13: no | AA13: 0 | AB13: =IF(AA13="","",AA13*T13) | AC13: =IF(W13="yes",AB13,"")
A14: NA | B14: WhenCallBack | C14: resp_whencallback | D14: When would it be a good time to call you back? [RECORD HH/MM/DD/MM OF CALLBACK] | E14: =LEN(D14) | F14: À quel moment pourrais-je vous rappeler? [ENREGISTRER HH/MM/JJ/MM DU RAPPEL] | G14: =LEN(F14) | H14: Ni wakati gani mzuri wa kukupigia simu tena?_x000D_ _x000D_ [REKODI HH/MM/DD/MM WA KUPIGIWA SIMU] | I14: =LEN(H14) | J14: Open Ended | K14: NA | L14: NA | M14: Form Type - TextBox IsCallBackDemographic | N14: NA | O14: Any Response = CallbackMessageEN | Q14: For any response, go to CallbackMessageEN | T14: 1 | W14: no | AA14: 0 | AB14: =IF(AA14="","",AA14*T14) | AC14: =IF(W14="yes",AB14,"")
A15: NA | B15: CallbackMessageEN | C15: callbackmessage_en | D15: Thank you, we will call you back at {WhenCallBack} you requested. Thank you again and have a great day! [OPERATOR: ENTER CALL NOTES BELOW, WHO YOU SPOKE TO AND WHAT THEY SAID] | E15: =LEN(D15) | F15: Merci, nous vous rappellerons à {WhenCallBack}. Merci encore et bonne journée! [OPÉRATEUR/OPÉRATRICE: SAISIR LES DONNÉES D'APPEL CI-DESSOUS, LE NOM DE LA PERSONNE À LAQUELLE VOUS AVEZ PARLÉ ET CE QU'ELLE A DIT] | G15: =LEN(F15) | H15: Asante, tutakupigia tena kwa {WhenCallBack} uliyoomba. Asante tena na siku njema kwako! [OPERATOR: WEKA MAELEZO YA SIMU HAPA CHINI, NANI ULIONGEA NAYE NA WALICHOSEMA] | I15: =LEN(H15) | J15: Open Ended | K15: NA | L15: NA | M15: Form Type - TextBox | N15: NA | O15: Any Response = End poll callback | Q15: NA | T15: 1 | W15: no | AA15: 0 | AB15: =IF(AA15="","",AA15*T15) | AC15: =IF(W15="yes",AB15,"")
A16: NA | B16: Ineligible | C16: NA | D16: You are ineligible for this survey. Thank you for your time and please look out for future surveys! | E16: =LEN(D16) | F16: Vous êtes inéligible pour participer à cette enquête. Merci pour votre temps et renseignez-vous sur les prochains sondages! | G16: =LEN(F16) | H16: Hujastahiki utafiti huu. Asante kwa muda wako na tafadhali angalia tafiti zijazo! | I16: =LEN(H16) | J16: NA | K16: NA | L16: NA | M16: NA | N16: NA | O16: End Poll Ineligible | Q16: NA | T16: 1 | W16: no | AA16: 0 | AB16: =IF(AA16="","",AA16*T16) | AC16: =IF(W16="yes",AB16,"")
A17: NA | B17: Refusal | C17: NA | D17: Thank you for your time, you will be removed from today's survey. | E17: =LEN(D17) | F17: Merci pour votre temps. Vous allez être retiré de l'enquête d'aujourd'hui. | G17: =LEN(F17) | H17: Asante kwa muda wako, utaondolewa kwenye utafiti wa leo. | I17: =LEN(H17) | J17: NA | K17: NA | L17: NA | M17: NA | N17: NA | O17: End poll declined | Q17: NA | T17: 1 | W17: no | AA17: 0 | AB17: =IF(AA17="","",AA17*T17) | AC17: =IF(W17="yes",AB17,"")
A18: B. GENERAL INFORMATION & ELIGIBILITY CRITERIA | AB18: =IF(AA18="","",AA18*T18) | AC18: =IF(W18="yes",AB18,"")
A19: 1 | B19: resp_firstname | C19: resp_firstname | D19: What is your first name? [OPERATOR: RECORD THE RESPONDENT'S FIRST NAME. ENTER 999 FOR REFUSED.] | E19: =LEN(D19) | F19: Quel est votre prénom? [OPÉRATEUR/OPÉRATRICE: SAISIR LE PRÉNOM DE LA PERSONNE INTÉRROGÉE. SAISIR 999 POUR REFUSÉ.] | G19: =LEN(F19) | H19: Jina lako la jamii ni nani? [OPERETERA: REKODI JINA YA KWANZA YA MUJIBU. INGIZA 999 KWA KUKATALA.] | I19: =LEN(H19) | J19: Open Ended | K19: NA | L19: NA | M19: Form Type - TextBox | N19: NA | O19: Any Response = resp_lastname | Q19: For any response, go to resp_lastname | T19: =1 | W19: yes | AA19: 25.874027 | AB19: =IF(AA19="","",AA19*T19) | AC19: =IF(W19="yes",AB19,"")
A20: 2 | B20: resp_lastname | C20: resp_lastname | D20: What is your last name? [OPERATOR: RECORD THE RESPONDENT'S LAST NAME. ENTER 999 FOR REFUSED.] | E20: =LEN(D20) | F20: Quel est votre nom de famille? [OPÉRATEUR/OPÉRATRICE: SAISIR LE NOM DE FAMILLE DE LA PERSONNE INTÉRROGÉE. SAISIR 999 POUR REFUSÉ.] | G20: =LEN(F20) | H20: Jina lako ya mwisho ni nani?_x000D_ _x000D_ [OPERETERA: REKODI JINA LA MWISHO YA MUDIBU. INGIZA 999 KWA KUKATALA.] | I20: =LEN(H20) | J20: Open Ended | K20: NA | L20: NA | M20: Form Type - TextBox | N20: NA | O20: Any Response = resp_age | Q20: For any response, go to resp_age | T20: =1 | W20: yes | AA20: 8.5994816 | AB20: =IF(AA20="","",AA20*T20) | AC20: =IF(W20="yes",AB20,"")
A21: 3 | B21: resp_age | C21: resp_age | D21: How old are you? [OPERATOR: RECORD AGE IN NUMBER OF YEARS. ROUND UP TO NEAREST WHOLE NUMBER. IF THE RESPONDENT GIVES BIRTH YEAR, REPEAT THE QUESTION. ENTER 00 FOR DON'T KNOW.] | E21: =LEN(D21) | F21: Quel âge avez-vous [en années]? [OPÉRATEUR/OPÉRATRICE: SAISIR L'ÂGE EN ANNÉES. ARRONDIR AU NOMBRE ENTIER LE PLUS PROCHE. SI LE RÉPONDANT DONNE SON ANNÉE DE NAISSANCE, RÉPÉTER LA QUESTION. SAISIR 00 POUR "NE SAIT PAS".] | G21: =LEN(F21) | H21: Una miaka mingapi?_x000D_ _x000D_ [OPERATOR: REKODI UMRI KATIKA IDADI YA MIAKA. ZUNGUSHA HADI NAMBA NZIMA KARIBU. IKIWA MHOJIWA AMEJIFUNGUA MWAKA WA KUZALIWA, RUDIA SWALI. INGIA 00 KWA SIJUE.] | I21: =LEN(H21) | J21: Range | K21: NA | L21: NA | M21: Form Type - TextBox | N21: NA | O21: 0-17 = Ineligible 18-100 = resp_gender 00 = Ineligible | Q21: Only respondents from 18-100 will be eligible for the survey. | T21: =1 | W21: yes | AA21: 9.8907185 | AB21: =IF(AA21="","",AA21*T21) | AC21: =IF(W21="yes",AB21,"")
A22: =A21+1 | B22: resp_gender | C22: resp_gender | D22: What is the gender of the respondent? [OPERATOR: DO NOT ASK THIS QUESTION OUT LOUD. LISTEN TO THE VOICE AND SELECT THE GENDER.] 1)Male 2)Female 3)DON'T KNOW 4)REFUSED | E22: =LEN(D22) | F22: Quel est le sexe du répondant? [OPÉRATEUR/OPÉRATRICE: NE PAS POSER CETTE QUESTION À VOIX HAUTE. ÉCOUTER LA VOIX ET DÉTERMINER LE SEXE.] 1)Homme 2)Femme 3)NE SAIT PAS 4)REFUSÉ | G22: =LEN(F22) | H22: Jinsia ya mujibu ni nini?_x000D_ _x000D_ [OPERATOR: USIULIZE SWALI HILI KWA SAUTI. SIKILIZA SAUTI NA UCHAGUE JINSIA.]_x000D_ _x000D_ 1)Mwanaume_x000D_ 2)Mwanamke_x000D_ 3)SIJUE_x000D_ 4)KUKATALA | I22: =LEN(H22) | J22: Single Choice | K22: NA | L22: NA | M22: Form Type - Buttons | N22: NA | O22: 1-4 = phone_number_conf | Q22: For any response, go to phone_number_conf | T22: =1 | W22: yes | AA22: 1.7156482 | AB22: =IF(AA22="","",AA22*T22) | AC22: =IF(W22="yes",AB22,"")
A23: =A22+1 | B23: phone_number_conf | C23: phone_number_conf | D23: Is the phone number I am calling you on yours or a household members? [OPERATOR: SINGLE RESPONSE.] 1)YES 2)NO 3)DON'T KNOW 4)REFUSED | E23: =LEN(D23) | F23: Le numéro de téléphone sur lequel je vous appelle est-il le vôtre ou celui d'un membre de votre famille? [OPÉRATEUR/OPÉRATRICE: RÉPONSE UNIQUE.] 1)OUI 2)NON 3)NE SAIT PAS 4)REFUSÉ | G23: =LEN(F23) | H23: Je, namba ya simu nina kupigia ni yako au ni ya moja wa jamii yako? [OPERATOR: JIBU MOJA.] 1)NDIYO 2)HAPANA 3)SIJUE 4)KUKATALA | I23: =LEN(H23) | J23: Single Choice | K23: NA | L23: NA | M23: Form Type - Buttons | N23: NA | O23: 1 = contact_2 2 = phone_number_personal 3-4 = contact_2 | Q23: if phone_number_conf = 1, go to contact_2 if phone_number_conf = 2, go to phone_number_personal if phone_number_conf = 3-4, go to contact_2 | T23: =1 | W23: yes - panel | AA23: 6.375237 | AB23: =IF(AA23="","",AA23*T23) | AC23: =IF(W23="yes",AB23,"")
A24: =A23+1 | B24: phone_number_personal | C24: phone_number_pers | D24: What is your phone number? [OPERATOR: RECORD THE NUMBER GIVEN] | E24: =LEN(D24) | F24: Quel est votre numéro de téléphone? [OPÉRATEUR/OPÉRATRICE: SAISIR LE NUMERO.] | G24: =LEN(F24) | H24: Namba ya simu yako iko je?_x000D_ _x000D_ [OPERATOR: REKODI NAMBA ANA PELEKA] | I24: =LEN(H24) | J24: Range | K24: NA | L24: NA | M24: Form Type - TextBox | N24: NA | O24: 1000000-999999999999 = contact_2 | Q24: For any response, go to contact_2 | T24: =1 | W24: yes - panel | AA24: 28.700001 | AB24: =IF(AA24="","",AA24*T24) | AC24: =IF(W24="yes",AB24,"")
A25: =A24+1 | B25: contact_2 | C25: contact_2 | D25: Can you give me an additional phone number belonging to you, another household member or a close relation living outside of the household at which you can be reached? [OPERATOR: SINGLE RESPONSE.] 1)YES - mine 2)YES - other household member 3)YES - friend or relative [non-household member] 4)NO 5)DON'T KNOW 6)REFUSED | E25: =LEN(D25) | F25: Pouvez-vous me donner un numéro de téléphone supplémentaire, le vôtre, celui d'un autre membre du ménage ou d’un proche vivant en dehors du ménage, auquel vous pouvez être joint? [OPÉRATEUR/OPÉRATRICE: RÉPONSE UNIQUE.] 1)OUI - le mien 2)OUI - un autre membre du ménage 3)OUI - un ami ou un parent [non membre du ménage]. 4)NON 5)NE SAIT PAS 6)REFUSÉ | G25: =LEN(F25) | H25: Je, unaweza kunipa nambari nyingine ya simu inayomilikiwa na wewe, mwanachama mwingine wa familia yako, au ndugu aliye nje ya familia ambapo unaweza kupatikana? [MWENDESHAJI: JIBU MOJA.] 1)NDIYO – yangu 2)NDIYO – mwanakaya mwingine 3)Ndiyo – rafiki au jamaa [asiye mwanakaya] 4)HAPANA 5)SIJUE 6)NILIKUKATALA | I25: =LEN(H25) | J25: Single Choice | K25: NA | L25: NA | M25: Form Type - Buttons | N25: NA | O25: 1-3 = phone_number_2 4-6 = hh_admin1 | Q25: if contact_2 = 1-3, go to phone_number_2 if contact_2 = 4-6, go to contact_3 | T25: =1 | W25: yes - panel | AA25: 10.141817 | AB25: =IF(AA25="","",AA25*T25) | AC25: =IF(W25="yes",AB25,"")
A26: =A25+1 | B26: phone_number_2 | C26: phone_number_2 | D26: What is the additional phone number? [OPERATOR: RECORD THE NUMBER GIVEN] | E26: =LEN(D26) | F26: Quel est cet autre numéro de téléphone? [OPÉRATEUR/OPÉRATRICE: SAISIR LE NUMERO.] | G26: =LEN(F26) | H26: Nambari ya simu ingine ni nini?_x000D_ _x000D_ [OPERATOR: REKODI NAMBA ANA PELEKA] | I26: =LEN(H26) | J26: Range | K26: NA | L26: NA | M26: Form Type - TextBox | N26: NA | O26: 1000000-999999999999 = contact_2_name | Q26: For any response, go to contact_2_name | T26: =1 | W26: yes - panel | AA26: 21.659983 | AB26: =IF(AA26="","",AA26*T26) | AC26: =IF(W26="yes",AB26,"")
A27: =A26+1 | B27: contact_2_name | C27: contact_2_name | D27: What is the name of the contact? [OPERATOR: RECORD THE NAME OF THE CONTACT FOR THE PHONE NUMBER.] | E27: =LEN(D27) | F27: Quel est le nom du contact associé à ce numéro de téléphone? [OPÉRATEUR/OPÉRATRICE: SAISIR LENOM DU CONTACT POUR CE NUMERO DE TÉLÉPHONE.] | G27: =LEN(F27) | H27: Jina la mawasiliano ni nani? [OPERATOR: REKODI JINA LA ANAYEWASILIANA KWA NAMBA YA SIMU.] | I27: =LEN(H27) | J27: Open Ended | K27: NA | L27: Send if "contact_2" "Equals" "YES - other household member" Or "contact_2" "Equals" "YES - friend or relative [non-household member]" if not satisfied go to "contact_3" | M27: Form Type - TextBox | N27: NA | O27: Any Response = contact_3 | Q27: Asked if response to contact_2 was "YES - other household member" or "YES - friend or relative [non-household member]". Otherwise, it skips to "contact_3". For any response, go to contact_3 | T27: =1 | W27: yes - panel | AA27: 11.821796 | AB27: =IF(AA27="","",AA27*T27) | AC27: =IF(W27="yes",AB27,"")
A28: =A27+1 | B28: contact_3 | C28: contact_3 | D28: Can you give me an additional phone number belonging to you, another household member or a close relation living outside of the household at which you can be reached? [OPERATOR: SINGLE RESPONSE.] 1)YES - mine 2)YES - other household member 3)YES - friend or relative [non-household member] 4)NO 5)DON'T KNOW 6)REFUSED | E28: =LEN(D28) | F28: Pouvez-vous me donner un numéro de téléphone supplémentaire, le vôtre, celui d'un autre membre du ménage ou d’un proche vivant en dehors du ménage, auquel vous pouvez être joint? [OPÉRATEUR/OPÉRATRICE: RÉPONSE UNIQUE.] 1)OUI - le mien 2)OUI - un autre membre du ménage 3)OUI - un ami ou un parent [non membre du ménage]. 4)NON 5)NE SAIT PAS 6)REFUSÉ | G28: =LEN(F28) | H28: Je, unaweza kunipa nambari nyingine ya simu inayomilikiwa na wewe, mwanachama mwingine wa familia yako, au ndugu aliye nje ya familia ambapo unaweza kupatikana? [MWENDESHAJI: JIBU MOJA.] 1)NDIYO – yangu 2)NDIYO – mwanakaya mwingine 3)NDIYO – rafiki au jamaa [asiye mwanakaya] 4)HAPANA 5)SIJUE 6)NILIKUKATALA | I28: =LEN(H28) | J28: Single Choice | K28: NA | L28: NA | M28: Form Type - Buttons | N28: NA | O28: 1-3= phone_number_3 4-6 = hh_admin1 | Q28: if contact_3 = 1-3, go to phone_number_3 if contact_3 = 4-6, go to hh_admin1 | T28: =1 | W28: yes - panel | AA28: 3.163594 | AB28: =IF(AA28="","",AA28*T28) | AC28: =IF(W28="yes",AB28,"")
A29: =A28+1 | B29: phone_number_3 | C29: phone_number_3 | D29: What is the additional phone number? [OPERATOR: RECORD THE NUMBER GIVEN] | E29: =LEN(D29) | F29: Quel est cet autre numéro de téléphone? [OPÉRATEUR/OPÉRATRICE: SAISIR LE NUMERO.] | G29: =LEN(F29) | H29: Namba ya simu yako ingine ni nini? [OPERATOR: REKODI NAMBA ULIYOPEWA] | I29: =LEN(H29) | J29: Range | K29: NA | L29: NA | M29: Form Type - TextBox | N29: NA | O29: 1000000-999999999999 = contact_3_name | Q29: For any response, go to contact_3_name | T29: =1 | W29: yes - panel | AA29: 10.830144 | AB29: =IF(AA29="","",AA29*T29) | AC29: =IF(W29="yes",AB29,"")
A30: =A29+1 | B30: contact_3_name | C30: phone_number_3_name | D30: What is the name of the contact? [OPERATOR: RECORD THE NAME OF THE CONTACT FOR THE PHONE NUMBER.] | E30: =LEN(D30) | F30: Quel est le nom du contact associé à ce numéro de téléphone? [OPÉRATEUR/OPÉRATRICE: SAISIR LENOM DU CONTACT POUR CE NUMERO DE TÉLÉPHONE.] | G30: =LEN(F30) | H30: Jina la mawasiliano ni nani?_x000D_ _x000D_ [OPERATOR: REKODI JINA KUFUATANA NA NAMBA YA SIMU.] | I30: =LEN(H30) | J30: Open Ended | K30: NA | L30: Send if "contact_3" "Equals" "YES - other household member" Or "contact_3" "Equals" "YES - friend or relative [non-household member]" if not satisfied go to "hh_admin1" | M30: Form Type - TextBox | N30: NA | O30: Any Response = hh_admin1 | Q30: Asked if response to contact_3 was "YES - other household member" or "YES - friend or relative [non-household member]". Otherwise, it skips to "hh_admin1". For any response, go to hh_admin1 | T30: =1 | W30: yes - panel | AA30: 11.260417 | AB30: =IF(AA30="","",AA30*T30) | AC30: =IF(W30="yes",AB30,"")
A31: =A30+1 | B31: hh_admin1 | C31: hh_admin1 | D31: Currently, in which $ADMIN1$ does your household reside? [OPERATOR: SINGLE SELECTION.] [HINT: HOUSEHOLD CONSISTS OF ALL MEMBERS LIVING TOGETHER, SHARING RESOURCES & EATING FROM THE SAME POT.] 1)ADMIN1 2)DON'T KNOW 3)REFUSED | E31: =LEN(D31) | F31: Actuellement, dans quel $ADMIN1$ votre ménage vit-il? [OPÉRATEUR/OPÉRATRICE: RÉPONSE UNIQUE.] [NOTE: LE MÉNAGE EST COMPOSÉ DE TOUTES LES PERSONNES VIVANT ENSEMBLE, METTANT EN COMMUN LEURS RESSOURCES ET PARTAGEANT LEURS REPAS.] 1)ADMIN1 2)NE SAIT PAS 3)REFUSÉ | J31: Single Choice | K31: NA | L31: NA | M31: Form Type - Buttons IsDemographic - ADM1 | N31: NA | O31: 1 = Ineligible 2 = Ineligible 3 = Ineligible 4 = Ineligible 5 = Ineligible 6 = hh_admin2_6 7 = Ineligible 8 = Ineligible 9 = Ineligible 10 = Ineligible 11 = Ineligible 12 = Ineligible 13 = Ineligible 14 = Ineligible 15 = Ineligible 16 = Ineligible 17 = Ineligible 18 = Ineligible 19 = hh_admin2_19 20 = Ineligible 21 = Ineligible 22 = hh_admin2_22 23 = Ineligible 24 = hh_admin2_24 25 = Ineligible 26 = Ineligible 27-28 = Ineligible | T31: =1 | W31: yes | AA31: 13.957259 | AB31: =IF(AA31="","",AA31*T31) | AC31: =IF(W31="yes",AB31,"")
A32: =A31+1 | B32: hh_admin2_1 | C32: hh_admin2_6 | D32: Currently, in which $ADMIN2$ does your household reside? [OPERATOR: SINGLE RESPONSE.] 1)ADMIN2 2)DON'T KNOW 3)REFUSED | E32: =LEN(D32) | F32: Actuellement, dans quel $ADMIN2$ votre ménage vit-il? [OPÉRATEUR/OPÉRATRICE: RÉPONSE UNIQUE.] 1)ADMIN2 2)NE SAIT PAS 3)REFUSÉ | H32: Kaya yako iko Ku territoire/ville gani? [OPERATEUR/OPERATRICE: USISOME CHAGUZI. JIBU MOJA TU] 1)ARU 2)BUNIA 3)DJUGU 4)IRUMU 5)MAHAGI 6)MAMBASA 7)SIJUE 8)KUKATALA | J32: Single Choice | K32: NA | L32: NA | M32: Form Type - Dropdown IsDemographic - ADM2 | N32: NA | O32: 1-6 = quotareached 7-8 = Ineligible | P32: GeoPoll [5/6/2025]. Excluded the locations of ARIWARA, INGBOKOLO, and MONGWALU despite being within the Admin2 info sheet because they are not currently in the quota table and are locations within other existing territories. For example, Ariwara is a town in Aru territory. This is consistent with the approach taken during previous rounds. Kindly correct as needed. FAO: COnfirm to keep same choices as previous round. Thanks
A33: =A32+1 | B33: quotareached | C33: quotareached | D33: [OPERATOR: DO NOT READ. ANSWER QUESTION BELOW.] THIS RESPONDENT REPORTED THEY LIVE IN: {ADM1} {ADM2} 1)THE GOAL FOR THIS LOCATION HAS BEEN ACHIEVED - END SURVEY 2)THE GOAL FOR THIS LOCATION IS OPEN - CONTINUE SURVEY | E33: =LEN(D33) | F33: [OPÉRATEUR/OPÉRATRICE: NE PAS LIRE. RÉPONDRE À LA QUESTION CI-DESSOUS.] CE RÉPONDANT DIT VIVRE À: {ADM1} {ADM2} 1)L'OBJECTIF DANS CETTE ZONE A ÉTÉ ATTEINT - FIN DU SONDAGE 2)L'OBJECTIF DANS CETTE ZONE N'EST PAS ENCORE ATTEINT - CONTINUER LE SONDAGE | G33: =LEN(F33) | H33: [OPERATOR: USISOME. JIBU SWALI HAPA CHINI.]_x000D_ _x000D_ MUJIBU HUYU ALIRIPOTI WANAISHI:_x000D_ _x000D_ {ADM1}_x000D_ {ADM2}_x000D_ _x000D_ 1)LENGO YA ENEO HILI LIMEFIKIWA - MUSHIO YA UTAFUTI_x000D_ 2)LENGO YA ENEO HILI LIMEFUNGUA - ENDELEA UTAFITI | I33: =LEN(H33) | J33: Single Choice | K33: NA | L33: NA | M33: Form Type - Buttons | N33: NA | O33: 1 = End Poll Quota Reached 2 = hh_agricactivity
A34: =A33+1 | B34: hh_agricactivity | C34: hh_agricactivity | D34: Has anybody in your household produced crops or livestock for household consumption or for sale in the past 12 months, including household members currently away for transhumance? [OPERATOR: SINGLE RESPONSE. THIS IS THE MAIN SCREENING QUESTION.] [HINT FOR PROBING: Do you cultivate any plants to sale or consume? Do you raise any animals with the intent of selling or consuming them or their products like meat, milk, wool or leather? Is one of your household member currently away with cattle or other animals for transhumance?] 1)Yes - crop production 2)Yes - livestock production 3)Yes - both crop and livestock production 4)No 5)DON'T KNOW 6)REFUSED | E34: =LEN(D34) | F34: Est-ce que quelqu'un dans votre ménage a produit des cultures ou du bétail pour la consommation du ménage ou pour la vente au cours des 12 derniers mois, y compris des membres du ménage actuellement partis pour la transhumance? [OPÉRATEUR / OPÉRATRICE : RÉPONSE UNIQUE. IL S'AGIT DE LA PRINCIPALE QUESTION DE SÉLECTION.] [CONSEILS POUR PRÉCISER : Cultivez-vous des végétaux afin de les vendre ou de les consommer ? Élevez-vous des animaux afin de les vendre ou de les consommer, y compris les produits issus de l'élevage, comme la viande, le lait, la laine ou le cuir ? L'un des membres de votre ménage est-il actuellement parti avec du bétail pour la transhumance ?] 1)Oui - production végétale 2)Oui - production animale 3)Oui - production végétale et animale 4)Non 5)NE SAIT PAS 6)REFUSÉ | G34: =LEN(F34) | H34: Je, kuna mtu yote katika nyumba yako amezalisha mazao au mifugo kwa ajili ya matumizi ya kaya au kwa ajili ya kuuza katika kipindi cha miezi 12 iliyopita, ikiwa ni pamoja na wanakaya ambao hawapo kwa sasa kwa ajili ya kubadilisha ubinadamu? [OPERATOR: JIBU MOJA. HILI NDILO SWALI KUU LA UCHUNGUZI.] [DOKEZO LA KUJARIBU: Je, unalima mimea yoyote ili kuuza au kutumia? Je, unafuga wanyama wowote kwa nia ya kuuza au kula au bidhaa yako kama nyama, maziba, pamba au ngozi? Je, moja wa wanakaya wako kwa sasa yuko mbali na ngombe au wanyama wengine kwa ajili ya kubadilisha ubinadamu?] 1)Ndiyo - uzalishaji wa mazao 2)Ndiyo - uzalishaji wa mifugo 3)Ndiyo - uzalishaji wa mazao na mifugo 4)Hapana 5)SIJUE 6)KUKATALA | I34: =LEN(H34) | J34: Single Choice | K34: NA | L34: NA | M34: Form Type - Buttons | N34: NA | O34: 1-4 = hh_fish 5-6 = Ineligible | Q34: if hh_agricactivity = 1-4, go to resp_id or hh_fish. Otherwise, the respondent is ineligible. | T34: =1 | W34: yes | AA34: 24.410839 | AB34: =IF(AA34="","",AA34*T34) | AC34: =IF(W34="yes",AB34,"")
A35: =A34+1 | B35: hh_fish | C35: hh_fish | D35: Has anybody in your household been engaged in aquatic production [fish catch or aquaculture farming] for household consumption or for sales in the past 12 months? [OPERATOR: SINGLE RESPONSE.] [HINT FOR PROBING: It should not include sports fishing. It should be about production of aquatic products [fish catch or aquaculture farming] for household consumption or sales.] 1)YES 2)NO 3)DON'T KNOW 4)REFUSED | E35: 116 | F35: Quelqu'un dans votre ménage a-t-il été impliqué dans la production aquatique [prise de poisson ou aquaculture] pour la consommation du ménage ou pour la vente au cours des 12 derniers mois ? [OPÉRATEUR/OPÉRATRICE: RÉPONSE UNIQUE.] [CONSEIL LORS DU SONDAGE : cette question et réponse ne devraient pas inclure la pêche sportive. Il s'agit plutôt de la production de produits aquatiques [prise de poisson ou aquaculture] pour la consommation ou la vente des ménages.] 1)OUI 2)NON 3)NE SAIT PAS 4)REFUSÉ | G35: =LEN(F35) | H35: Je, kuna mtu yeyote katika familia yako ambaye amekuwa akijishughulisha na uzalishaji wa majini [kuvua samaki au ufugaji wa samaki] kwa matumizi ya familia au kwa mauzo katika kipindi cha miezi 12 iliyopita? [MWENDESHAJI: JIBU MOJA.] [KIASHIRIA CHA KUCHUNGUZA: Haipaswi kujumuisha uvuvi wa michezo. Inapaswa kuwa juu ya uzalishaji wa mazao ya majini [samaki wanaovuliwa au ufugaji wa samaki] kwa matumizi ya famille au mauzo.] 1)NDIYO 2)HAPANA 3)SIJUE 4)NILIKUKATALA | I35: =LEN(H35) | J35: Single Choice | K35: NA | L35: NA | M35: Form Type - Buttons | N35: NA | O35: 1-2 = resp_id 3-4 = Ineligible | Q35: if hh_fish = 1-2, go to resp_id. Otherwise, the respondent is ineligible. | S35: Use this question if the survey seeks to gather important information on fisheries and/or aquaculture in the country.
A36: B. GENERAL HOUSEHOLD INFORMATION | AB36: =IF(AA36="","",AA36*T36) | AC36: =IF(W36="yes",AB36,"")
A37: =A35+1 | B37: resp_id | C37: resp_id | D37: Are you the head of household? [OPERATOR: SINGLE RESPONSE.] 1)YES 2)NO 3)DON'T KNOW 4)REFUSED | E37: 96 | F37: Êtes-vous le chef de ménage? [OPÉRATEUR/OPÉRATRICE: RÉPONSE UNIQUE.] 1)OUI 2)NON 3)NE SAIT PAS 4)REFUSÉ | G37: =LEN(F37) | H37: Wewe ni mkuu wa nyumba? [OPERATOR: JIBU MOJA.] 1)NDIYO 2)HAPANA 3)SIJUE 4)KUKATALA | I37: =LEN(H37) | J37: Single Choice | K37: NA | L37: NA | M37: Form Type - Buttons | N37: NA | O37: 1 = hh_education 2-4 = hh_age | Q37: if resp_id = 1, go to hh_education. Otherwise, go to hh_gender. | T37: 1 | W37: yes | AA37: 10.5 | AB37: =IF(AA37="","",AA37*T37) | AC37: =IF(W37="yes",AB37,"")
A38: =A37+1 | B38: hh_age | C38: hh_age | D38: How old is the head of household? [OPERATOR: SINGLE RESPONSE.] 1)Under 18 2)18 to 40 3)41 to 65 4)Over 65 5)DON'T KNOW 6)REFUSED | E38: =LEN(D38) | F38: Quel âge a le chef de famille? [OPÉRATEUR/OPÉRATRICE: RÉPONSE UNIQUE.] 1)Moins de 18 ans 2)entre 18 et 40 ans 3)entre 41 et 65 ans 4)Plus de 65 ans 5)NE SAIT PAS 6)REFUSÉ | G38: =LEN(F38) | H38: Mkuu wa nyumba ana umri gani? [OPERATOR: JIBU MOJA.] 1)Chini ya miaka 18 2)18 hadi 40 3)41 hadi 65 4)Zaidi ya 65 5)SIJUE 6)KUKATALA | I38: =LEN(H38) | J38: Single Choice | K38: NA | L38: NA | M38: Form Type - Buttons | N38: NA | O38: 1-6 = hh_gender | P38: GeoPoll [5/6/2025]: Would suggest changing the order so this question comes directly after resp_id and updating the conditional logic so respondent is only asked if they are not the head of household. Kindly advise if ok? FAO=OK | Q38: For any response, go to [next question] | T38: =1 | W38: no | AA38: 7.0248413 | AB38: =IF(AA38="","",AA38*T38) | AC38: =IF(W38="yes",AB38,"")
A39: =A38+1 | B39: hh_gender | C39: hh_gender | D39: Is the head of your household male or female? [OPERATOR: SINGLE RESPONSE.] 1)Male 2)Female 3)DON'T KNOW 4)REFUSED | E39: =LEN(D39) | F39: Le chef de votre ménage est-il un homme ou une femme? [OPÉRATEUR/OPÉRATRICE: RÉPONSE UNIQUE.] 1)Homme 2)Femme 3)NE SAIT PAS 4)REFUSÉ | G39: =LEN(F39) | H39: Je, mkuu wa nyumba yako ni mwanamume au mwanamke?_x000D_ _x000D_ [OPERATOR: JIBU MOJA.]_x000D_ _x000D_ 1)Mwanaume_x000D_ 2)Mwanamke_x000D_ 3)SIJUE_x000D_ 4)KUKATALA | I39: =LEN(H39) | J39: Single Choice | K39: NA | L39: NA | M39: Form Type - Buttons | N39: NA | O39: 1-4 = hh_education | Q39: if hh_gender = 1-4, go to hh_education. | T39: =1 | W39: yes | AA39: 10.504534 | AB39: =IF(AA39="","",AA39*T39) | AC39: =IF(W39="yes",AB39,"")
A40: =A39+1 | B40: hh_education | C40: hh_education | D40: What is the educational level attained by the head of household? [OPERATOR: SINGLE RESPONSE.] 1)None or did not complete primary school 2)Completed primary school 3)Completed secondary school 4)Completed higher education [University / College] degree 5)Religious or informal education only 6)DON'T KNOW 7)REFUSED | E40: =LEN(D40) | F40: Quel est le niveau d'éducation du chef de votre ménage ? [OPÉRATEUR/OPÉRATRICE: RÉPONSE UNIQUE.] 1)Aucun ou n'a pas terminé l'école primaire 2)A terminé l'école primaire 3)A terminé l'école secondaire 4)Diplôme de l'enseignement supérieur [Université] 5)Enseignement religieux ou informel uniquement 6)NE SAIT PAS 7)REFUSÉ | G40: =LEN(F40) | H40: Je, mkuu wa nyumba ana kiwango gani cha elimu? [OPERATOR: JIBU MOJA.] 1)Hakuna au hakumaliza shule ya msingi 2)Kumaliza shule ya msingi 3)Kumaliza shule ya sekondari 4)Alimaliza elimu ya juu [Chuo kikuu/Chuo] 5)Elimu ya dini au isiyo rasmi pekee 6)SIJUE 7)KUKATALA | I40: =LEN(H40) | J40: Single Choice | K40: NA | L40: NA | M40: Form Type - Buttons | N40: NA | O40: 1-7 = hh_wealth_water | Q40: if hh_education = 1-7, go to hh_wealth. | T40: =1 | W40: yes | AA40: 12.421899 | AB40: =IF(AA40="","",AA40*T40) | AC40: =IF(W40="yes",AB40,"")
A41: =A40+1 | B41: hh_wealth_water | C41: hh_wealth_water | D41: Where does the water that you drink at home come from? [OPERATOR: SINGLE CHOICE.] 1)Private tap from piped water 2)Public tap 3)Protected well 4)Bottled water 5)Other safe source 6)River 7)Unprotected well 8)Spring water 9)Surface water [e.g. canals/ ponds/ dams] 10)Other unsafe source 11)DON'T KNOW 12)REFUSED | E41: =LEN(D41) | F41: Où vous procurez-vous habituellement l'eau que vous buvez dans votre foyer? [OPÉRATEUR/OPÉRATRICE: RÉPONSE UNIQUE.] 1)Robinet privé avec eau courante 2)Robinet public 3)Puits protégé 4)Eau en bouteille 5)Autre source sûre 6)Rivière 7)Puits non protégé 8)Eau de source 9)Eaux de surface [par ex. canaux/ étangs/ barrages] 10)Autre source non sûre 11)NE SAIT PAS 12)REFUSÉ | G41: =LEN(F41) | H41: Maji munakunywaka nyumbani inatokaka wapi?_x000D_ _x000D_ [OPERATOR: CHAGUO MOJA.]_x000D_ _x000D_ 1)Bomba la kibinafsi kutoka kwa maji ya bomba_x000D_ 2)Bomba la umma_x000D_ 3)Imelindwa vizuri_x000D_ 4)Maji ya chupa_x000D_ 5)Chanzo kingine salama_x000D_ 6)Mto_x000D_ 7)Haijahifadhiwa mzuri_x000D_ 8)Maji ya chemchemi_x000D_ 9)Maji ya usoni [k.m. mifereji / mabwawa / mabwawa]_x000D_ 10)Chanzo kingine kisicho salama_x000D_ 11)SIJUE_x000D_ 12)KUKATALA | I41: =LEN(H41) | J41: Single Choice | K41: NA | L41: NA | M41: Form Type - Buttons | N41: NA | O41: 1-12 = hh_wealth_toilet | Q41: For any response, go to [income_main OR other optional question] | S41: Select wealth indicators based on baseline information available; you can delete those that you do not want to use. If none of these indicators work in the context of your country, other wealth proxies are proposed in the optional questions below. Remember that baseline data will be necessary, and the variable should be defined properly in the "weight_input_table". | T41: =1 | W41: yes | AA41: 16.615656 | AB41: =IF(AA41="","",AA41*T41) | AC41: =IF(W41="yes",AB41,"")
A42: =A41+1 | B42: hh_wealth_toilet | C42: hh_wealth_toilet | D42: Where do household members typically go to use a toilet? [OPERATOR: SINGLE CHOICE.] 1)Flush latrine [toilet with water] 2)Traditional pit latrine [no water] 3)Open pit [hole in the ground for excrement without water/ roof or wall] 4)Communal latrine [with or without water] 5)None – bush 6)DON'T KNOW 7)REFUSED | E42: =LEN(D42) | F42: Quel genre de toilettes les membres de votre ménage utilisent-ils? [OPÉRATEUR/OPÉRATRICE: RÉPONSE UNIQUE.] 1)Latrines à chasse d'eau [toilettes avec eau] 2)Latrines traditionnelles à fosse [sans eau] 3)Fosse ouverte [trou dans le sol pour les excréments/ sans eau/ toit ni mur] 4)Latrines communautaires [avec ou sans eau] 5)Aucune – brousse 6)NE SAIT PAS 7)REFUSÉ | G42: =LEN(F42) | H42: Wanafamilia wa nyumba huenda wapi kutumia choo? [OPERATOR: JIBU MOJA] 1)Safisha choo [choo na maji] 2)Choo cha shimo cha kitamaduni [hakuna maji] 3)Shimo wazi [shimo ardhini kwa kinyesi bila maji / paa au ukuta] 4)Choo cha jumuiya [yenye au bila maji] 5)Hakuna - kichaka 6)SIJUE 7)KUKATALA | I42: =LEN(H42) | J42: Single Choice | K42: NA | L42: NA | M42: Form Type - Buttons | N42: NA | O42: 1-7 = hh_wealth_light | Q42: For any response, go to [income_main OR other optional question] | T42: =1 | W42: yes | AA42: 12.600021 | AB42: =IF(AA42="","",AA42*T42) | AC42: =IF(W42="yes",AB42,"")
A43: =A42+1 | B43: hh_wealth_light | C43: hh_wealth_light | D43: What is the main source of light in your dwelling? [OPERATOR: SINGLE RESPONSE.] 1)Electricity [from generator or electrical grid] 2)Candle 3)Petrol lamp 4)Lamp with batteries 5)Solar panel 6)Other [no electric supply to the house] 7)DON'T KNOW 8)REFUSED | E43: =LEN(D43) | F43: Quelle est la principale source de lumière de votre logement? [OPÉRATEUR/OPÉRATRICE: RÉPONSE UNIQUE.] 1)Électricité [générateur ou réseau électrique] 2)Bougie 3)Lampe à pétrole 4)Lampe à piles 5)Panneaux solaires 6)Autre [pas d'alimentation électrique dans la maison] 7)NE SAIT PAS 8)REFUSÉ | G43: =LEN(F43) | H43: Ni nini chanzo kikuu cha mwanga katika makao yako? [OPERATOR: JIBU MOJA.] 1)Umeme [kutoka kwa jenereta au gridi ya umeme] 2)Mshumaa 3)Taa ya petroli 4)Taa yenye betri 5)Paneli ya jua 6)Yingine [hakuna usambazaji wa umeme kwa nyumba] 7)SIJUE 8)KUKATALA | I43: =LEN(H43) | J43: Single Choice | K43: NA | L43: NA | M43: Form Type - Buttons | N43: NA | O43: 1-8 = hh_size | Q43: For any response, go to [income_main OR other optional question] | T43: =1 | W43: yes | AA43: 11.655923 | AB43: =IF(AA43="","",AA43*T43) | AC43: =IF(W43="yes",AB43,"")
A44: =A43+1 | B44: hh_size | C44: hh_size | D44: How many people are part of the household? [OPERATOR: RECORD NUMBER OF MEMBERS IN HOUSEHOLD. ENTER 88 FOR DON'T KNOW & 99 FOR REFUSED.] [HINT: TO BE A PART OF THE SAME HOUSEHOLD, MEMBERS MUST LIVE UNDER THE SAME ROOF, SHARE THE SAME RESOURCES & EAT FROM THE SAME POT.] | E44: =LEN(D44) | F44: De combien de personnes est composé votre ménage? [OPÉRATEUR/OPÉRATRICE: ENREGISTRER LE NOMBRE DE MEMBRES DU MÉNAGE. ENTRER 88 POUR «NE SAIT PAS» ET 99 POUR «REFUSÉ».] [CONSEIL: POUR FAIRE PARTIE D'UN MÊME MÉNAGE, LES MEMBRES DOIVENT VIVRE ENSEMBLE, METTRE EN COMMUN LEURS RESSOURCES ET PARTAGER LEURS REPAS.] | G44: =LEN(F44) | H44: Je, nyumba yako ina watu wangapi? [OPERATOR: REKODI IDADI YA WAJUMBE KATIKA KAYA. INGIA 88 KWA SIJUE & 99 KWA KUKUKATALA.] [DOKEZO: ILI KUWA SEHEMU YA KAYA MOJA, WAJUMBE LAZIMA WAISHI CHINI YA PAA MOJA, WASHIRIKIANE RASILIMALI ILE ILE NA KULA KUTOKA KATIKA SUFURIA MOJA.] | I44: =LEN(H44) | J44: Range | K44: NA | L44: NA | M44: Form Type - TextBox | N44: NA | O44: 1-50 = hh_asset_prod 88-88 = hh_asset_prod 99-99 = hh_asset_prod | Q44: For any response, go to [next question] | T44: =1 | W44: no | AA44: 16.902294 | AB44: =IF(AA44="","",AA44*T44) | AC44: =IF(W44="yes",AB44,"")
A45: =A44+1 | B45: o_hh_size_005 | D45: How many household members are between the ages of 0 and 5 years old? [OPERATOR: ENTER 888 FOR DON'T KNOW & 999 FOR REFUSED.] | E45: =LEN(D45) | F45: Combien de membres de votre foyer ont entre 0 et 5 ans ? [OPÉRATEUR : ENTRER 888 POUR « JE NE SAIS PAS » ET 999 POUR « REFUS ».] | J45: Range | K45: NA | L45: NA | M45: Form Type -TextBox Validation rule: Answer to this question is VALID if "hh_size" is IsGreaterThan "CurrentAnswer" - Unmatched Response [Vous avez donné un chiffre supérieur au nombre de personnes dans votre ménage. Veuillez indiquer le nombre correct de membres] | O45: 0-50 = o_hh_size_613 888-888 = o_hh_size_613 999-999 = o_hh_size_613
A46: =A45+1 | B46: o_hh_size_613 | D46: How many household members are between the ages of 6 and 13 years old? [OPERATOR: ENTER 888 FOR DON'T KNOW & 999 FOR REFUSED.] | E46: =LEN(D46) | F46: Combien de membres de votre foyer ont entre 6 et 13 ans ? [OPÉRATEUR : ENTRER 888 POUR « JE NE SAIS PAS » ET 999 POUR « REFUS ».] | J46: Range | K46: NA | L46: NA | M46: Form Type - TextBox Validation rule: Answer to this question is VALID if "<Expression>hh_size - o_hh_size_005" is GreaterThan "CurrentAnswer" - Unmatched Response - [Vous avez donné un chiffre supérieur au nombre de personnes dans votre ménage. Veuillez indiquer le nombre correct de membres] | O46: 0-50 = o_hh_size_1417 888-888 = o_hh_size_1417 999-999 = o_hh_size_1417 | Q46: For any response, go to [next question]
A47: =A46+1 | B47: o_hh_size_1417 | D47: How many household members are between the ages of 14 and 17 years old? [OPERATOR: ENTER 888 FOR DON'T KNOW & 999 FOR REFUSED.] | E47: =LEN(D47) | F47: Combien de membres de votre foyer ont entre 14 et 17 ans ? [OPÉRATEUR : ENTRER 888 POUR « JE NE SAIS PAS » ET 999 POUR « REFUS ».] | J47: Range | K47: NA | L47: NA | M47: Form Type - TextBox Validation rule: Answer to this question is VALID if "<Expression>hh_size - o_hh_size_613" is GreaterThan "CurrentAnswer" - Unmatched Response - [Vous avez donné un chiffre supérieur au nombre de personnes dans votre ménage. Veuillez indiquer le nombre correct de membres] | O47: 0-50 = o_hh_size_1824 888-888 = o_hh_size_1824 999-999 = o_hh_size_1824 | Q47: For any response, go to [next question]
A48: =A47+1 | B48: o_hh_size_1824 | D48: How many household members are between the ages of 18 and 24 years old? [OPERATOR: ENTER 888 FOR DON'T KNOW & 999 FOR REFUSED.] | E48: =LEN(D48) | F48: Combien de membres de votre foyer ont entre 18 et 24 ans ? [OPÉRATEUR : ENTRER 888 POUR « JE NE SAIS PAS » ET 999 POUR « REFUS ».] | J48: Range | K48: NA | L48: NA | M48: Form Type - TextBox Validation rule: Answer to this question is VALID if "<Expression>hh_size - o_hh_size_005 - o_hh_size_613 - o_hh_size_1417" is GreaterThanorEqualto "CurrentAnswer" - Unmatched Response - [Vous avez donné un chiffre supérieur au nombre de personnes dans votre ménage. Veuillez indiquer le nombre correct de membres] | O48: 0-50 = o_hh_size_2564 888-888 = o_hh_size_2564 999-999 = o_hh_size_2564 | Q48: For any response, go to [next question]
A49: =A48+1 | B49: o_hh_size_2564 | D49: How many household members are between the ages of 25 and 64 years old? [OPERATOR: ENTER 888 FOR DON'T KNOW & 999 FOR REFUSED.] | E49: =LEN(D49) | F49: Combien de membres de votre foyer ont entre 25 et 64 ans ? [OPÉRATEUR : ENTRER 888 POUR « JE NE SAIS PAS » ET 999 POUR « REFUS ».] | J49: Range | K49: NA | L49: NA | M49: Form Type - TextBox Validation rule: Answer to this question is VALID if "<Expression>hh_size - o_hh_size_005 -o_hh_size_613 - o_hh_size_1417 - o_hh_size_1824" is GreaterThanorEqualto "CurrentAnswer" - Unmatched Response - [Vous avez donné un chiffre supérieur au nombre de personnes dans votre ménage. Veuillez indiquer le nombre correct de membres] | O49: 0-50 = o_hh_size_65 888-888 = o_hh_size_65 999-999 = o_hh_size_65 | Q49: For any response, go to [next question]
A50: =A49+1 | B50: o_hh_size_65 | D50: How many household members are more than 65 years old? [OPERATOR: ENTER 888 FOR DON'T KNOW & 999 FOR REFUSED.] | E50: =LEN(D50) | F50: Combien de membres de votre foyer ont plus de 65 ans ? [OPÉRATEUR : ENTRER 888 POUR « JE NE SAIS PAS » ET 999 POUR « REFUS ».] | J50: Range | K50: NA | L50: NA | M50: Form Type - TextBox Validation rule: Answer to this question is VALID if "<Expression>hh_size - o_hh_size_005 -o_hh_size_613 - o_hh_size_1417 - o_hh_size_1824 - o_hh_size_2564" is GreaterThanorEqualto "CurrentAnswer" - Unmatched Response - Vous avez donné un chiffre supérieur au nombre de personnes dans votre ménage. Veuillez indiquer le nombre correct de membres] | O50: 0-50 = o_pregnant 888-888 = o_pregnant 999-999 = o_pregnant | Q50: For any response, go to [next question]
A51: =A50+1 | B51: o_pregnant_lactating | D51: Is there any woman pregnant in your household? [OPERATOR: SINGLE RESPONSE.] 1)Yes 2)No 3)Don't know 4)REFUSED | E51: =LEN(D51) | F51: Y-a-t-il une ou plusieurs femmes enceintes dans votre ménage ? [OPÉRATEUR/OPÉRATRICE: RÉPONSE UNIQUE.] 1)Oui 2)Non 3)NE SAIT PAS 4)REFUSÉ | J51: Range | K51: NA | L51: NA | M51: Form Type - Buttons | O51: 1-4=hh_asset_prod
A52: =A51+1 | B52: hh_asset_prod | C52: hh_asset_prod_ 1) hh_asset_prod_process 2) hh_asset_prod_farmmach 3) hh_asset_prod_sewing 4) hh_asset_prod_taxi 5) hh_asset_prod_truck 6) hh_asset_prod_other 7) hh_asset_prod_none 8) hh_asset_prod_dk 9) hh_asset_prod_ref | D52: Does your household own any of the following productive assets? [OPERATOR: MULTIPLE RESPONSES POSSIBLE. READ ANSWER OPTIONS OUT LOUD.] 1)Processing assets [e.g. grinding/crushing machine/ mill/ oil press/ fish tanks] 2)Farm or fishing machinery [e.g. tractor/ plough/ sickle/ boats/ engines] 3)Sewing machine or weaving tool 4)Taxi 5)Truck 6)Other productive machines or assets 7)No productive machines or assets 8)DON'T KNOW 9)REFUSED | E52: =LEN(D52) | F52: Votre ménage possède-t-il l'un des actifs productifs suivants? [OPÉRATEUR / OPÉRATRICE : PLUSIEURS RÉPONSES POSSIBLES. LIRE LES OPTIONS DE RÉPONSE À HAUTE VOIX.] 1)Actifs de transformation [par ex. broyeur/ moulin/ presse à huile/ aquarium] 2)Machine agricole ou de pêche [par ex. tracteur/ charrue/ faucille/ bateaux/ moteurs] 3)Machine à coudre ou métier à tisser 4)Taxi 5)Camion 6)Autres machines ou actifs productifs 7)Aucune machine ou actif productif 8)NE SAIT PAS 9)REFUSÉ | G52: =LEN(F52) | H52: Kaya yako inamiliki mojawapo ya mali zifuatazo za uzalishaji? [OPERATOR: MAJIBU MENGI YANAWEZEKANA. SOMA CHAGUO ZA MAJIBU KWA SAUTI.] 1)Usindikaji wa bidhaa [mali] [kwa mfano. mashine ya kusaga/kinu/vyombo vya habari vya mafuta/mizinga ya samaki] 2)Mashine za kilimo au uvuvi [kwa mfano. trekta/Jembe la kulima/mundu/boti/mitambo] 3)Cherehani au weaving chombo 4)Teksi 5)Lori 6)Mashine yingine za uzalishaji au mali 7)Hakuna mashine za uzalishaji au mali 8)SIJUE 9)KUKATALA | I52: =LEN(H52) | J52: Select All That Apply | K52: NA | L52: NA | M52: Form Type - Checklist 7,8,9 = IsNone | N52: 1)hh_asset_prod_process 2)hh_asset_prod_farmmach 3)hh_asset_prod_sewing 4)hh_asset_prod_taxi 5)hh_asset_prod_truck 6)hh_asset_prod_other 7)hh_asset_prod_none 8)hh_asset_prod_dk 9)hh_asset_prod_ref | O52: 1-9 = hh_asset_transp | Q52: For any response, go to [next question] | S52: This wealth indicator may be useful to Identify poor households in middle income countries. It could be interesting for F2F surveys, to be used as baseline reference for follow-up surveys. | T52: =1 | W52: no | AA52: 16.957804 | AB52: =IF(AA52="","",AA52*T52) | AC52: =IF(W52="yes",AB52,"")
A53: =A52+1 | B53: hh_asset_transp | C53: hh_asset_transp_ 1) hh_asset_transp_bici 2) hh_asset_transp_cart 3) hh_asset_transp_boatmotor 4) hh_asset_transp_boatnomotor 5) hh_asset_transp_motorbike 6) hh_asset_transp_car 7) hh_asset_transp_van 8) hh_asset_transp_other 9) hh_asset_transp_none 10) hh_asset_transp_dk 11) hh_asset_transp_ref | D53: Do you or any member of your household own any of the following transportation assets? [OPERATOR: MULTIPLE RESPONSES POSSIBLE. READ ANSWER OPTIONS OUT LOUD.] 1)Bicycle 2)Cart [animal drawn] 3)Boat with an engine [inboard or outboard] 4)Unmotorized boat [e.g. canoe] 5)Motorbike / scooter / auto rickshaw 6)Car 7)Van or small truck 8)Other motor vehicle 9)None of the above 10)DON'T KNOW 11)REFUSED | E53: =LEN(D53) | F53: Est-ce que vous ou un membre de votre ménage possède un des véhicules suivants? [OPÉRATEUR / OPÉRATRICE : PLUSIEURS RÉPONSES POSSIBLES. LIRE LES OPTIONS DE RÉPONSE À HAUTE VOIX.] 1)Bicyclette 2)Chariot [tiré par un animal] 3)Bateau avec moteur [in-bord ou hors-bord] 4)Bateau non motorisé [par ex. canoë] 5)Moto/scooter/pousse-pousse 6)Voiture 7)Fourgonnette ou petit camion 8)Autre véhicule motorisé 9)Aucun des véhicules proposés 10)NE SAIT PAS 11)REFUSÉ | G53: =LEN(F53) | H53: Wewe au mwanakaya yeyote anamiliki mojawapo ya mali muna fuataka usafiri? [OPERATOR: MAJIBU MENGI YANAWEZEKANA. SOMA CHAGUO YA MAJIBU KWA SAUTI.] 1)Baiskeli 2)Mkokoteni [wanyama waliochorwa] 3)Mashua yenye injini [injini ndani au injini nje] 4)Mashua isiyo na injini [kwa mfano - [mashua [canon] 5)pikipiki/Skuta/pikipiki ya kukodisha 6)Gari 7)Gari ndogo au Lori dogo 8)Gari la injini nyingine 9)Hakuna kati ya hapo juu 10)SIJUE 11)KUKATALA | I53: =LEN(H53) | J53: Select All That Apply | K53: NA | L53: NA | M53: Form Type - Checklist 9,10,11 = IsNone | N53: 1)hh_asset_transp_bici 2)hh_asset_transp_cart 3)hh_asset_transp_boatmotor 4)hh_asset_transp_boatnomotor 5)hh_asset_transp_motorbike 6)hh_asset_transp_car 7)hh_asset_transp_van 8)hh_asset_transp_other 9)hh_asset_transp_none 10)hh_asset_transp_dk 11)hh_asset_transp_ref | O53: 1-11 =resp_residencetype | Q53: For any response, go to [next question] | S53: This wealth indicator may be useful to Identify poor households in middle income countries. It could be interesting for F2F surveys, to be used as baseline reference for follow-up surveys. | T53: =1 | W53: no | AA53: 11.022029 | AB53: =IF(AA53="","",AA53*T53) | AC53: =IF(W53="yes",AB53,"")
A54: =A53+1 | B54: resp_residencetype | C54: resp_residencetype | D54: How would you describe your residence status? Are you a... [OPERATOR: READ OUT THE OPTIONS. SINGLE RESPONSE.] [HINT: IF RESPONDENT IS ONLY AWAY FROM THE HOUSEHOLD FOR SHORT SEASONAL WORK (<6 MONTHS) OR TRANSHUMANCE, MAKE SURE TO REFER TO THEIR HOUSEHOLD WHERE THEY TYPICALLY ARE LOCATED.] 1)Permanent resident - You have been living in your village / town for longer than two years and this is what you consider your habitual residence 2)Returnee - You have only come back to this residence in the last two years after having been forced to move to another location having fled conflict or natural disaster 3)Internally displaced person [IDP] - You were forced to flee your village or town because of conflict or natural disaster and you are now an internally displaced person in your current place of residence 4)Refugee - you were forced to flee your country because of conflict or natural disaster and you are now a refugee in your current place of residence 5)DON'T KNOW 6)REFUSED | E54: =LEN(D54) | F54: Comment décririez-vous votre statut de résidence? Êtes-vous un(e)... [OPÉRATEUR/OPÉRATRICE: LIRE LES OPTIONS, RÉPONSE UNIQUE]. [CONSEIL: SI LA PERSONNE INTERROGÉE N'EST ÉLOIGNÉE DU FOYER QUE POUR UN TRAVAIL SAISONNIER DE COURTE DURÉE (<6 MOIS) OU POUR LA TRANSHUMANCE, FAIRE RÉFÉRENCE AU FOYER OÙ ELLE VIT HABITUELLEMENT]. 1)Résident[e] permanent[e] - vous vivez dans votre village/ville depuis plus de deux ans et vous le/la considérez comme votre lieu de résidence habituel 2)Personne retournée - vous êtes revenu dans votre lieu de résidence au cours des deux dernières années après avoir été contraint de vous déplacer pour fuir un conflit ou une catastrophe naturelle [si le retour a eu lieu il y a plus de deux ans/ le répondant est considéré comme un résident permanent 3)Personne déplacée à l'intérieur de son pays - vous avez été forcé de fuir votre village ou votre ville en raison d'un conflit ou d'une catastrophe naturelle et/ dans votre lieu de résidence actuel/ vous êtes une personne déplacée à l'intérieur de son propre pays 4)Réfugié - vous avez été forcé de fuir votre pays en raison d'un conflit ou d'une catastrophe naturelle et/ dans votre lieu de résidence actuel/ vous êtes un réfugié 5)NE SAIT PAS 6)REFUSÉ | G54: =LEN(F54) | H54: Je, unaweza kuelezeaje hali yako ya ukaaji? Je, wewe ni... [OPERATOR: SOMA CHAGUO, MAJIBU MOJA]. [KIDOKEZO: IWAPO MHOJIWA YUPO MBALI NA NYUMBANI TU KWA KAZI YA MUDA MFUPI (< MIEZI 6) AU KWA AJILI YA KUPELEKA, REJEA NYUMBANI WANAPOISHI KAWAIDA]. 1) Mkazi wa kudumu - umeishi katika kijiji/mji wako kwa zaidi ya miaka miwili na unaona kuwa ni makazi yako ya kawaida. 2) Mrejeshwaji - ulirudi kwenye makazi yako ndani ya miaka miwili iliyopita baada ya kulazimishwa kuhama kutoroka migogoro au maafa ya asili [ikiwa kurudi kulifanyika zaidi ya miaka miwili iliyopita/ mhojiwa anachukuliwa kuwa mkazi wa kudumu. 3) Mkimbizi wa ndani - umelazimika kukimbia kijiji au mji wako kwa sababu ya migogoro au maafa ya asili na/ katika makazi yako ya sasa / wewe ni mkimbizi wa ndani. 4) Mkimbizi - umelazimika kuikimbia nchi yako kwa sababu ya migogoro au maafa ya asili na/ katika makazi yako ya sasa/ wewe ni mkimbizi. 5) SIJUE 6) KUKATALA | I54: =LEN(H54) | J54: Single Choice | K54: NA | L54: NA | M54: Form Type - Buttons IsDemographic - resp_residencetype | N54: 1)hh_residencecomp_permresident 2)hh_residencecomp_returnee 3)hh_residencecomp_idp 4)hh_residencecomp_refugee 5)hh_residencecomp_dk 6)hh_residencecomp_ref | O54: 1 = hh_residencecomp 2-4 = hh_arrivaltime 5-6 = hh_shelter | P54: GeoPoll [5/6/2025]. Added the definitions of each residence status that are present in other FAO tools for countries including Haiti. Kindly advise if ok/responsive. FAO: Perfect thanks | Q54: If response is "Returnee", "IDP" or "Refugee", go to hh_arrivaltime. If response is "Permanent resident", skip to hh_residencecomp. For "Don't know" or "Refused", move to hh_shelter. | W54: yes
A55: =A54+1 | B55: hh_arrivaltime | C55: hh_arrivaltime | D55: How long ago did you arrive in this place? [OPERATOR: INDICATE THE NUMBER OF MONTHS. YOU MAY NEED TO CALCULATE THIS. ENTER 888 FOR DON'T KNOW & 999 FOR REFUSED.] | E55: =LEN(D55) | F55: Depuis quand vivez-vous dans ce lieu? [OPÉRATEUR/OPÉRATRICE: INDIQUER LE NOMBRE DE MOIS, QU'IL FAUDRA PEUT-ETRE CALCULER. SAISIR 888 POUR «NE SAIT PAS» ET 999 POUR «REFUSÉ».] | G55: =LEN(F55) | H55: Umeishi mahali hapa kwa muda gani? [OPERATOR: ONYESHA IDADI YA MIEZI INAYOWEZA KUHITAJI KUHESABIWA. INGIA 888 KWA "SIJUE" NA 999 KWA "KUKATALA."] | I55: =LEN(H55) | J55: Range | K55: NA | L55: NA | M55: Form Type - TextBox | N55: NA | O55: 0-100 = hh_displacementfreq 888-888 = hh_displacementfreq 999-999 = hh_displacementfreq | Q55: For any response, go to hh_displacementfreq. | W55: yes
A56: =A55+1 | B56: hh_displacementfreq | C56: hh_displacementfreq | D56: How many times have you [respondent] been forced to move due to conflict, insecurity or disaster? [OPERATOR: ENTER 888 FOR DON'T KNOW & 999 FOR REFUSED.] | E56: =LEN(D56) | F56: Combien de fois avez-vous [le répondant] été contraint de déménager en raison d'un conflit, de l'insécurité ou d'une catastrophe? [OPÉRATEUR/OPÉRATRICE: SAISIR 888 POUR «NE SAIT PAS» ET 999 POUR «REFUSÉ».] | G56: =LEN(F56) | H56: Je, ni mara ngapi wewe [mhojiwa] umelazimika kuhama kwa sababu ya migogoro, ukosefu wa usalama au maafa tangu ulipohamishwa kwa mara ya kwanza? [OPERATOR: PEMBEJEO 888 KWA "SIJUE" NA 999 KWA "ALIYEKUKATALA".] | I56: =LEN(H56) | J56: Range | K56: NA | L56: NA | M56: Form Type - TextBox | N56: NA | O56: 0-100 = hh_disp_impact 888-888 = hh_disp_impact 999-999 = hh_disp_impact | P56: GeoPoll [5/6/2025]. Due to the skip patterns, should the minimum eligible response be 1, or is 0 a logical response? FAO: Change can be made. Thanks for pointing this out. Skip patterm will be 1-100 | Q56: For any response, go to hh_residencecomp. | W56: yes
A57: =A56+1 | B57: hh_disp_impact | C57: hh_disp_impact 1)hh_disp_imp_livelihood 2)hh_disp_imp_housing 3)hh_disp_imp_edu 4)hh_disp_imp_health 5)hh_disp_imp_supportnet 6)hh_disp_imp_mentalhealth 7)hh_disp_imp_community 8)hh_disp_imp_inc_cost 9)hh_disp_imp_essentialserv 10)hh_disp_imp_safety 11)hh_disp_imp_other 12)hh_disp_imp_none 13)hh_disp_imp_dk 14)hh_disp_imp_ref | D57: What have been the most significant impacts of displacement on your household? [OPERATION: UP TO THREE RESPONSES ALLOWED.] 1)Loss of income/ livelihood or productive assets 2)Difficulty accessing adequate housing 3)Limited access to education for children 4)Limited access to healthcare 5)Separation from family members or support networks 6)Increased stress or mental health challenges 7)Loss of broader community or social connections 8)Increased cost of living 9)Reduced access to essential services [water/ electricity/ transport] 10)Safety or security concerns 11)Other [specify] 12)No significant impact felt 13)DON'T KNOW 14)REFUSED | E57: =LEN(D57) | F57: Quels ont été les impacts les plus importants du déplacement sur votre ménage ? [OPÉRATEUR/OPÉRATRICE : JUSQU'À TROIS RÉPONSES POSSIBLES]. 1)Perte de revenus/ de moyens de subsistance ou de biens de production 2)Difficultés d'accès à un logement adéquat 3)Accès limité à l'éducation pour les enfants 4)Accès limité aux soins de santé 5)Séparation des membres de la famille ou des réseaux de soutien 6)Augmentation du stress ou des problèmes de santé mentale 7)Perte de liens communautaires ou sociaux 8)Augmentation du coût de la vie 9)Accès réduit aux services essentiels [eau/ électricité/ transport] 10)Problèmes de sécurité 11)Autre [précisez] 12)Aucun impact ressenti 13)NE SAIT PAS 14)REFUS | G57: =LEN(F57) | H57: Je, ni athari gani kuu za kuhama kwa kaya yako? [OPERATOR: HADI MAJIBU MATATU YANAWEZEKANA]. 1) Upotevu wa mapato/ riziki au mali za uzalishaji 2) Ugumu wa kupata makazi ya kutosha 3) Upatikanaji mdogo wa elimu kwa watoto 4) Upatikanaji mdogo wa huduma za afya 5) Kutengana na wanafamilia au mitandao ya usaidizi 6) Kuongezeka kwa matatizo au matatizo ya afya ya akili 7) Kupoteza uhusiano wa kijamii au kijamii 8) Kuongezeka kwa gharama ya maisha 9) Kupunguza upatikanaji wa huduma muhimu [maji/umeme/usafiri] 10) Masuala ya usalama 11) Nyingine [taja] 12) Hakuna athari inayoonekana 13) SIJUE 14) KUKATAA | I57: =LEN(H57) | J57: Open Ended-Select All That Apply | K57: NA | L57: NA | M57: Form Type - Checklist 12,13,14 = IsNone MinAns = 1 MaxAns = 3 | N57: 1)hh_disp_imp_livelihood 2)hh_disp_imp_housing 3)hh_disp_imp_edu 4)hh_disp_imp_health 5)hh_disp_imp_supportnet 6)hh_disp_imp_mentalhealth 7)hh_disp_imp_community 8)hh_disp_imp_inc_cost 9)hh_disp_imp_essentialserv 10)hh_disp_imp_safety 11)hh_disp_imp_other 12)hh_disp_imp_none 13)hh_disp_imp_dk 14)hh_disp_imp_ref | O57: 1-14 =hh_residencecomp | P57: GeoPoll [5/6/2025]. Given up to three responses are allowed, slightly modified phrasing on the English side to reference "impacts" as plural. Kindly advise if this update is ok and we will proceed to make adjustments to French and Swahili. FAO: ok | Q57: For any response, go to income_main or optional question.
A58: =A57+1 | B58: hh_residencecomp | C58: hh_residencecomp 1)hh_residencecomp_none 2)hh_residencecomp_permresident 3)hh_residencecomp_returnee 4)hh_residencecomp_idp 5)hh_residencecomp_refugee 6)hh_residencecomp_dk 7)hh_residencecomp_ref | D58: Does your household include members with a different status type than the one you reported? And if so, which one(s)? [OPERATOR: MULTIPLE RESPONSES POSSIBLE. SELECT ALL THAT APPLY.] 1)No other status 2)DON'T KNOW 3)REFUSED | E58: =LEN(D58) | F58: Votre ménage comprend-il des membres dont le statut de résidence est différent du votre ? Si oui, quels sont ces statuts ? [OPÉRATEUR/OPÉRATRICE: PLUSIEURS RÉPONSES POSSIBLES. SÉLECTIONNER TOUTES CELLES QUI S'APPLIQUENT]. 1)Aucun autre statut 2)NE SAIT PAS 3)REFUSÉ | G58: =LEN(F58) | H58: Je, kaya yako inajumuisha watu ambao hali yao ya makazi ni tofauti na yako? Ikiwa ndio, hali hizi ni zipi? [OPERATOR: MAJIBU KADHAA YANAWEZEKANA. CHAGUA YOTE YANAYOTUMIKA]. 1)Hakuna hali nyingine 2)SIJUE 3)KUKATALA | I58: =LEN(H58) | J58: Select All That Apply | K58: NA | L58: NA | M58: Form Type - Checklist Included unselected "resp_residencetype" 1,2,3= IsNone | N58: 1)hh_residencecomp_none 2)hh_residencecomp_dk 3)hh_residencecomp_ref | O58: Dynamic = hh_site 1-3 = hh_site | Q58: For any response, go to income_main or optional question. | W58: yes
A59: =A58+1 | B59: hh_site | C59: hh_site | D59: Which of the following best describes where you live? [OPERATOR: READ ANSWERS OUT LOUD. SINGLE RESPONSE.] 1)Formal camp or settlement 2)Informal camp or settlement 3)Outside of a camp or settlement with a host family 4)Outside of a camp or settlement on my own 5)DON'T KNOW 6)REFUSED | E59: =LEN(D59) | F59: Laquelle de ces propositions décrit le mieux l'endroit où vous vivez? [OPÉRATEUR/OPÉRATRICE: LIRE LES RÉPONSES À HAUTE VOIX. UNE SEULE RÉPONSE POSSIBLE]. 1)Camp ou campement formel 2)Camp ou campement informel 3)En dehors d'un camp ou d'un campement dans une famille d'accueil 4)En dehors d'un camp ou d'un campement seul[e] 5)NE SAIT PAS 6)REFUSÉ | G59: =LEN(F59) | H59: Ni ipi kati ya hizi inaelezea vyema zaidi unapoishi? [OPERATOR: SOMA MAJIBU KWA SAUTI. JIBU MOJA TU LINAWEZEKANA]. 1)Kambi rasmi au kambi 2)Kambi isiyo rasmi au kambi 3)Nje ya kambi au kambi-na familia mwenyeji. 4)Nje ya kambi au kambi - peke yake 5)SIJUE 6)KUKATALA | I59: =LEN(H59) | J59: Single Choice | K59: NA | L59: Send if "resp_residencetype" "Equals" "Internally displaced person [IDP] - You were forced to flee your village or town because of conflict or natural disaster and you are now an internally displaced person in your current place of residence" Or "resp_residencetype" "Equals" "Returnee - You have only come back to this residence in the last two years after having been forced to move to another location having fled conflict or natural disaster" Or "resp_residencetype" "Equals" "Refugee - you were forced to flee your country because of conflict or natural disaster and you are now a refugee in your current place of residence" if not satisfied go to "hh_shelter" | M59: Form Type - Buttons | N59: NA | O59: 1-6 = hh_shelter | Q59: For any response, go to income_main or optional question.
A60: =A59+1 | B60: hh_shelter | C60: hh_shelter | D60: What kind of shelter is your household living in? [OPERATOR: SINGLE RESPONSE.] 1)Apartment/house- good condition 2)Apartment/house- damaged/destroyed/ bad condition 3)Hotel/motel/short term rental 4)Unfinished or abandoned building 5)Tent/makeshift shelter 6)Mud or block structure 7)Container/caravan 8)Public building or collective shelter 9)Other shelter [eg garage/ farm building etc] 10)DON'T KNOW 11)REFUSED | E60: =LEN(D60) | F60: Dans quel type d'abri vit votre ménage? [OPÉRATEUR/OPÉRATRICE: RÉPONSE UNIQUE]. 1)Appartement/maison en bon état 2)Appartement/maison endommagé/détruit/ en mauvais état 3)Hôtel/motel/location à court terme 4)Bâtiment inachevé ou abandonné 5)Tente/abri de fortune 6)Structure faite de boue ou de blocs 7)Conteneur/caravane 8)Bâtiment public ou abri collectif 9)Autre abri [garage/ bâtiment agricole etc.] 10)NE SAIT PAS 11)REFUSÉ | G60: =LEN(F60) | H60: Je, kaya yako inaishi katika makazi ya aina gani? [OPERATOR: JIBU MOJA]. 1)Ghorofa/nyumba katika hali nzuri 2)Ghorofa/nyumba iliyoharibika/kuharibika-katika hali mbaya 3)Hoteli/moteli/kukodisha kwa muda mfupi 4)Jengo ambalo halijakamilika au kutelekezwa 5)Hema/makazi ya kujitengenezea 6)Muundo uliotengenezwa kwa matope au vitalu 7)Kontena/ msafara 8)Hadhara jengo au makazi ya pamoja 9)Makazi mengine [gereji/jengo la kilimo/n.k.] 10)SIJUE 11)KUKATALA | I60: =LEN(H60) | J60: Single Choice | K60: NA | L60: NA | M60: Form Type - Buttons | N60: NA | O60: 1-11 = hh_predisp_agricactivity | Q60: For any response, go to income_main or optional question.
A61: =A60+1 | B61: hh_predisp_agricactivity | C61: hh_predisp_agricactivity | D61: Did you or other displaced persons in your household engage in agricultural activities prior to being displaced? [OPERATOR: SINGLE RESPONSE.] 1)YES 2)NO 3)DON'T KNOW 4)REFUSED | E61: =LEN(D61) | F61: Avez-vous, vous ou d'autres membres déplacés de votre ménage, été impliqué dans des activités agricoles avant votre déplacement ? [OPÉRATEUR/OPÉRATRICE: RÉPONSE UNIQUE]. 1)OUI 2)NON 3)NE SAIT PAS 4)REFUSÉ | G61: =LEN(F61) | H61: Je, wewe au wanajamii wenzako mlijihusisha na shughuli za kilimo kabla ya kuhamia hapa? [OPERATOR: JIBU MOJA.] 1)NDIYO 2)HAPANA 3)SIJUE 4)KUKATALA | I61: =LEN(H61) | J61: Single Choice | K61: NA | L61: Send if "resp_residencetype" "Equals" "Internally displaced person [IDP] - You were forced to flee your village or town because of conflict or natural disaster and you are now an internally displaced person in your current place of residence" Or "resp_residencetype" "Equals" "Returnee - You have only come back to this residence in the last two years after having been forced to move to another location having fled conflict or natural disaster" Or "resp_residencetype" "Equals" "Refugee - you were forced to flee your country because of conflict or natural disaster and you are now a refugee in your current place of residence" Or "hh_residencecomp" "Contains" "Refugee - you were forced to flee your country because of conflict or natural disaster and you are now a refugee in your current place of residence" if not satisfied go to "hh_agri_plotaccess" | M61: Form Type - Buttons | N61: NA | O61: 1 = hh_predisp_agricactivity_type 2-4 = hh_agri_plotaccess | Q61: If "Yes", go to hh_predisp_agricactivity_type; otherwise, go to income_main or optional question.
A62: =A61+1 | B62: hh_predisp_agricactivity_type | C62: hh_predisp_agricactivity_type 1)hh_predisp_crpprod 2)hh_predisp_lsprod 3)hh_predisp_fishprod 4)hh_predisp_dk 5)hh_predisp_ref | D62: Can you or anyone in your household access land or water to grow food, raise animals, or raise/catch fish? [OPERATOR: SINGLE RESPONSE.] 1)YES 2)NO 3)DON'T KNOW 4)REFUSED | E62: =LEN(D62) | F62: Est-ce que vous ou quelqu'un de votre ménage peut avoir accès à la terre ou à l'eau pour les cultures, élever des animaux ou élever/pêcher des poissons ? [OPÉRATEUR/OPÉRATRICE: RÉPONSE UNIQUE]. 1)OUI 2)NON 3)NE SAIT PAS 4)REFUSÉ | G62: =LEN(F62) | H62: Je, wewe au mtu yeyote katika kaya yako anaweza kupata ardhi au maji kwa ajili ya kupanda mazao, kufuga wanyama, kufuga/kuvua samaki? [OPERATOR: JIBU MOJA.] 1)NDIYO 2)HAPANA 3)SIJUE 4)KUKATALA | I62: =LEN(H62) | J62: Single Choice | K62: NA | L62: NA | M62: Form Type - Buttons | N62: NA | O62: 1 =income_main 2 = hh_plotaccess 3-4 = income_main | Q62: For any response, go to income_main or optional question.
A63: =A62+1 | B63: hh_agri_plotaccess | C63: hh_agri_plotaccess | D63: Can you or anyone in your household access land or water to grow food, raise animals, or raise/catch fish? [OPERATOR: SINGLE RESPONSE.] 1)YES 2)NO 3)DON'T KNOW 4)REFUSED | E63: =LEN(D63) | F63: Est-ce que vous ou quelqu'un de votre ménage peut avoir accès à la terre ou à l'eau pour les cultures, élever des animaux ou élever/pêcher des poissons ? [OPÉRATEUR/OPÉRATRICE: RÉPONSE UNIQUE]. 1)OUI 2)NON 3)NE SAIT PAS 4)REFUSÉ | G63: =LEN(F63) | H63: Je, wewe au mtu yeyote katika kaya yako anaweza kupata ardhi au maji kwa ajili ya kupanda mazao, kufuga wanyama, kufuga/kuvua samaki? [OPERATOR: JIBU MOJA.] 1)NDIYO 2)HAPANA 3)SIJUE 4)KUKATALA | I63: =LEN(H63) | J63: Single Choice | K63: NA | L63: Send if "hh_predisp_agricactivity" "Equals" "YES" Or "hh_agricactivity" "Equals" "Yes - crop production" Or "hh_agricactivity" "Equals" "Yes - livestock production" Or "hh_agricactivity" "Equals" "Yes - both crop and livestock production" Or "hh_fish" "Equals" "YES" if not satisfied go to "hh_plotaccess" | M63: Form Type - Buttons | N63: NA | O63: 1 =income_main 2 = hh_plotaccess 3-4 = income_main | Q63: If "NO", go to hh_plotaccess. Otherwise, go to income_main or optional question.
A64: =A63+1 | B64: hh_plotaccess | C64: hh_plotaccess 1)hh_plotaccess_high_costs 2)hh_plotaccess_distance 3)hh_plotaccess_unsafe_insec 4)hh_plotaccess_unsafe_infra 5)hh_plotaccess_scarcity 6)hh_plotaccess_authorities 7)hh_plotaccess_poor_resource 8)crp_plotaccess_other 9)crp_plotaccess_dk 10)crp_plotaccess_ref | D64: Why are you unable to access land or water for agricultural, livestock or fishing? [OPERATOR: MULTIPLE RESPONSES POSSIBLE.] 1)Too expensive to rent or buy 2)Too remote or far away 3)Access to the area is unsafe due to insecurity 4)Access roads and infrastructure is in poor condition 5)Scarcity - there is no land or water available 6)Authorities [formal or customary] do not allow us to access land or water 7)Land or water is degraded or infertile 8)Other [specify] 9)DON’T KNOW 10)REFUSED | E64: =LEN(D64) | F64: Pourquoi n'avez-vous pas accès à la terre ou à l'eau pour l'agriculture, l'élevage ou la pêche ? [OPÉRATEUR : PLUSIEURS RÉPONSES POSSIBLES]. 1)Location ou achat trop cher 2)Trop éloigné 3)L'accès à la zone n'est pas sûr en raison de l'insécurité 4)Les routes d'accès et les infrastructures sont en mauvais état 5)Pénurie - il n'y a pas de terre ou d'eau disponible 6)Les autorités [officielles ou coutumières] ne nous autorisent pas à accéder à la terre ou à l'eau 7)La terre ou l'eau est dégradée ou infertile 8)Autre [préciser] 9)NE SAIT PAS 10)REFUSÉ | G64: =LEN(F64) | H64: Kwa nini huna ardhi au maji kwa ajili ya kilimo, ufugaji wa mifugo au uvuvi? [OPERATOR: MAJIBU MENGI YANAWEZEKANA]. 1) Kukodisha au kununua ghali sana 2) Mbali sana 3) Upatikanaji wa eneo si salama kutokana na ukosefu wa usalama 4) Barabara za kuingia na miundombinu iko katika hali mbaya 5) Uhaba - hakuna ardhi au maji yanayopatikana 6) Mamlaka [rasmi au kimila] hazituruhusu kupata ardhi au maji 7) Ardhi au maji yameharibika au hayana rutuba 8) Nyingine [taja] 9) SIJUE 10) KUKATALA | I64: =LEN(H64) | J64: Open Ended-Select All That Apply | K64: NA | L64: NA | M64: Form Type - Checklist 9,10 = IsNone | N64: 1)hh_plotaccess_high_costs 2)hh_plotaccess_distance 3)hh_plotaccess_unsafe_insec 4)hh_plotaccess_unsafe_infra 5)hh_plotaccess_scarcity 6)hh_plotaccess_authorities 7)hh_plotaccess_poor_resource 8)crp_plotaccess_other 9)crp_plotaccess_dk 10)crp_plotaccess_ref | O64: 1-10 = income_main | Q64: For any response, go to income_main or optional question.
A65: C. INCOME SOURCES, LIVELIHOOD AND SHOCKS | AB65: =IF(AA65="","",AA65*T65) | AC65: =IF(W65="yes",AB65,"")
A66: =A64+1 | B66: income_main | C66: income_main | D66: What was your household's main source of income in the past 3 months? [OPERATOR: SINGLE RESPONSE. REFUSED OPTION SHOULD BE AVOIDED AS MUCH AS POSSIBLE.] 1)Production and sale of staple crops 2)Production and sale of vegetable or fruit 3)Production and sale of cashcrops 4)Production and sale of livestock or livestock products 5)Production and sale of honey or bee products 6)Production and sale of fish or aquatic products 7)Collection and sale of forestry or bush products 8)Agricultural trade EXCLUDING producers [formal or informal] 9)Daily wage on farms and other casual employment in agricultural sector 10)Stable employment in agricultural sector 11)Non-agricultural self-employed or liberal profession / doctor / architect / lawyer / including restaurant 12)Off-farm daily wages and other non-agricultural casual employment 13)Stable employment in non-agricultural sector 14)Public employment 15)Income not derived from work / Charity 16)Income not derived from work / Welfare transfer/ pension/ humanitarian aid 17)Income not derived from work / Remittances 18)Income not derived from work / Income from other rents 19)No income source in the last 3 months and used exclusively savings / debt 20)REFUSED | E66: =LEN(D66) | F66: Quelle était la principale source de revenus de votre ménage au cours des trois derniers mois? [OPÉRATEUR/OPÉRATRICE: RÉPONSE UNIQUE. L'OPTION «REFUSÉ» DOIT ÊTRE, AUTANT QUE POSSIBLE, ÉVITÉE.] 1)Production et vente de cultures vivrières 2)Production et vente de légumes ou de fruits 3)Production et vente de cultures de rente 4)Production et vente de bétail ou de produits animaux 5)Production et vente de miel ou de produits apicoles 6)Production et vente de poisson ou de produits aquatiques 7)Collecte et vente de produits forestiers ou de brousse 8)Commerce agricole EXCLUANT les producteurs [formel ou informel] 9)Salaire journalier dans une exploitation et autres emplois occasionnels dans le secteur agricole 10)Emploi stable dans le secteur agricole 11)Indépendant non-agricole ou profession libérale / médecin / architecte / avocat / y compris restaurant 12)Salaire journalier hors exploitation et autres emplois occasionnels non agricoles 13)Emploi stable dans le secteur non-agricole 14)Emploi public 15)Revenu non tiré du travail / Charité 16)Revenu non tiré du travail / Transferts sociaux/ pension/ aide humanitaire 17)Revenu non tiré du travail / Envois de fonds des migrants 18)Revenu non tiré du travail / Revenu d'autres loyers 19)Aucune source de revenus au cours des trois derniers mois et recours exclusif à l'épargne / création de dettes 20)REFUSÉ | G66: =LEN(F66) | H66: Ni nini kilikuwa chanzo kikuu cha mapato ya kaya yako katika kipindi cha miezi 3 iliyopita? [OPERATOR: JIBU MOJA. CHAGUO LILILOKUKATALA LINAPASWA KUEPUKWA KADIRI IWEZEKANAVYO.] 1)Uzalishaji na uuzaji wa mazao ya msingi 2)Uzalishaji na uuzaji wa mboga mboga au matunda 3)Uzalishaji na uuzaji wa mazao ya fedha 4)Uzalishaji na uuzaji wa mifugo au bidhaa za mifugo 5)Uzalishaji na uuzaji wa asali au mazao ya nyuki 6)Uzalishaji na uuzaji wa samaki au bidhaa za majini 7)Ukusanyaji na uuzaji wa mazao ya misitu au misitu 8)Biashara ya kilimo BILA KUWAHITIMIZA wazalishaji [rasmi au isiyo rasmi] 9)Mshahara wa kila siku kwenye mashamba na ajira yingine za kawaida katika sekta ya kilimo 10)Ajira imara katika sekta ya kilimo 11)Kazi isiyo ya kilimo au taaluma ya huria / daktari / mbunifu / mwanasheria / pamoja na mgahawa 12)Mshahara wa kila siku nje ya shamba na ajira yingine za kawaida zisizo za kilimo 13)Ajira imara katika sekta isiyo ya kilimo 14)Ajira za umma 15)Mapato yasiyotokana na kazi / Hisabati 16)Mapato yasiyotokana na kazi / Uhamisho wa ustawi / pensheni / misaada ya kibinadamu 17)Mapato yasiyotokana na kazi/Pesa 18)Mapato yasiyotokana na kazi / Mapato kutoka kwa kodi zingine 19)Hakuna chanzo cha mapato katika miezi 3 iliyopita na imetumia akiba/deni pekee 20)KUKATALA" | I66: =LEN(H66) | J66: Single Choice | K66: NA | L66: NA | M66: Form Type - Buttons IsDemographic income_main | N66: NA | O66: 1-3 = income_main_crop_check 4 = income_main_ls_check 5 = income_main_amount 6 = income_main_fish_check 7-18 = income_main_amount 19-20 = shock | Q66: if options #1-3 selected go to income_main_crop_check if options #4 selected go to income_main_ls_check if options #6 selected go to income_main_fish_check if options #5, 7-18 selected, go to [income_main_comp OR optional question] if options #19-20 selected, go to shock | T66: =1 | W66: yes | AA66: 31.888334 | AB66: =IF(AA66="","",AA66*T66) | AC66: =IF(W66="yes",AB66,"")
A67: =A66+1 | B67: income_main_crop_check | C67: income_main_crop_check | D67: Are the crops sold also produced by you or anyone in your household? [OPERATOR: SINGLE RESPONSE.] 1)YES 2)NO 3)DON'T KNOW 4)REFUSED | E67: =LEN(D67) | F67: Les cultures vendues sont-elles également produites par vous ou quelqu'un de votre ménage? [OPÉRATEUR/OPÉRATRICE: RÉPONSE UNIQUE.] 1)OUI 2)NON 3)NE SAIT PAS 4)REFUSÉ | G67: =LEN(F67) | H67: Je, mazao yanayouzwa pia yamezalishwa na wewe au mtu yeyote katika famille yako? [OPERATOR: JIBU MOJA.] 1)NDIYO 2)HAPANA 3)SIJUE 4)KUKATALA | I67: =LEN(H67) | J67: Single Choice | K67: NA | L67: NA | M67: Form Type - Buttons | N67: NA | O67: 1-4 = income_main_amount | Q67: if income_main_crop_check = 1-4, go to [income_main_comp OR optional question] | T67: =1 | W67: yes | AA67: 8 | AB67: =IF(AA67="","",AA67*T67) | AC67: =IF(W67="yes",AB67,"")
A68: =A67+1 | B68: income_main_ls_check | C68: income_main_ls_check | D68: Are the livestock or livestock products sold also produced by you or anyone in your household? [OPERATOR: SINGLE RESPONSE.] 1)YES 2)NO 3)DON'T KNOW 4)REFUSED | E68: =LEN(D68) | F68: Le bétail ou les produits du bétail vendus sont-ils également produits par vous ou quelqu'un de votre ménage? [OPÉRATEUR/OPÉRATRICE: RÉPONSE UNIQUE.] 1)OUI 2)NON 3)NE SAIT PAS 4)REFUSÉ | G68: =LEN(F68) | H68: Je, mifugo au bidhaa za mifugo zinazouzwa pia zimezalishwa na wewe au mtu yeyote katika famille yako? [OPERATOR: JIBU MOJA.] 1)NDIYO 2)HAPANA 3)SIJUE 4)KUKATALA | I68: =LEN(H68) | J68: Single Choice | K68: NA | L68: NA | M68: Form Type - Buttons | N68: NA | O68: 1-4 = income_main_amount | Q68: if income_main_ls_check = 1-4, go to [income_main_comp OR optional question] | T68: =1 | W68: yes | AA68: 8 | AB68: =IF(AA68="","",AA68*T68) | AC68: =IF(W68="yes",AB68,"")
A69: =A68+1 | B69: income_main_fish_check | C69: income_main_fish_check | D69: Are the fish or aquatic products sold also captured/harvested by you or anyone in your household? [OPERATOR: SINGLE RESPONSE.] 1)YES 2)NO 3)DON'T KNOW 4)REFUSED | E69: =LEN(D69) | F69: Le poisson ou les produits aquatiques vendus sont-ils également capturés/récoltés par vous ou un membre de votre ménage? [OPÉRATEUR/OPÉRATRICE: RÉPONSE UNIQUE.] 1)OUI 2)NON 3)NE SAIT PAS 4)REFUSÉ | G69: =LEN(F69) | H69: Je, samaki au bidhaa za majini zinazouzwa pia zimevuliwa/kuvunwa na wewe au mtu yeyote katika famille yako? [OPERATOR: JIBU MOJA.] 1)NDIYO 2)HAPANA 3)SIJUE 4)KUKATALA | I69: =LEN(H69) | J69: Single Choice | K69: NA | L69: NA | M69: Form Type - Buttons | N69: NA | O69: 1-4 = income_main_amount | Q69: if income_main_fish_check = 1-4, go to [income_main_comp OR optional question] | T69: =1 | W69: yes | AA69: 8 | AB69: =IF(AA69="","",AA69*T69) | AC69: =IF(W69="yes",AB69,"")
A70: =A69+1 | B70: income_main_amount | C70: income_main_amount | D70: How much was earned [in CDF] from your main income source, {income_main}, in the past 3 months ? [OPERATOR: MAKE SURE THE INFORMATION IS RECORDED IN THE CORRECT CURRENCY. ENTER 88888888 FOR DON'T KNOW AND 99999999 FOR REFUSED.] | E70: =LEN(D70) | F70: Quelle somme [en CDF] a rapporté votre principale source de revenus, {income_main}, au cours des trois derniers mois? [OPÉRATEUR/OPÉRATRICE: VÉRIFIER QUE LA RÉPONSE EST ENREGISTRÉE DANS LA BONNE DEVISE. SAISIR 88888888 POUR «NE SAIT PAS» ET 99999999 POUR «REFUSÉ».] | G70: =LEN(F70) | H70: Ni kiasi gani kilipatikana [katika CDF] kutoka kwa chanzo chako kikuu cha mapato, {income_main}, katika kipindi cha miezi 3 iliyopita ? [OPERATOR: HAKIKISHA HABARI IMEREKODIWA KWA SARAFU SAHIHI. INGIA 888888888 KWA SIJUE NA 999999999 KWA KUKATALA.] | I70: =LEN(H70) | J70: Range | K70: NA | L70: NA | M70: Form Type - TextBox | N70: NA | O70: 10000 - 2000000 =income_main_gender 2000001 - 30000000 = income_main_amount_conf 88888888-88888888 =income_main_gender 99999999-99999999 = income_main_gender | P70: GeoPoll [5/6/2025]. Would suggest updating the minimum to 10000 (instead of 0) and updating maximum to 30000000 for all income questions. Kindly advise if responsive. FAO= ok thanks | Q70: If the income amount is over the threshold set in "Additional information", the respondent will be asked to confirm with income_main_amount_conf. Otherwise, go to income_main_comp or optional question. | S70: We recommend using this pair of questions together. | T70: =1 | W70: no | AA70: 31.963766 | AB70: =IF(AA70="","",AA70*T70) | AC70: =IF(W70="yes",AB70,"")
A71: =A70+1 | B71: income_main_amount_conf | C71: income_main_amount_conf | D71: Can you confirm the amount of income you just stated is correct? [OPERATOR: IF THE AMOUNT EARNED FROM THIS INCOME SOURCE OVER THE PAST 3 MONTH IS INDEED OVER 2000000, CLICK ON CONTINUE. OTHERWISE, GO BACK AND CHANGE THE AMOUNT ENTERED.] 1)CONTINUE | E71: =LEN(D71) | F71: Pouvez-vous confirmer que le montant que vous venez de déclarer est correct? [OPÉRATEUR/OPÉRATRICE: SI LE MONTANT ISSU DE CETTE SOURCE DE REVENU AU COURS DES TROIS DERNIERS MOIS EST SUPÉRIEUR AU 2000000, CLIQUER SUR CONTINUER. SINON, REVENIR EN ARRIÈRE ET MODIFIER LE MONTANT SAISI.] 1)CONTINUER | G71: =LEN(F71) | H71: Unaweza kuthibitisha kiasi cha mapato ulichosema ni sahihi? [OPERATOR: IWAPO KIASI KILICHOCHUKUA KUTOKA KWA CHANZO HIKI CHA MAPATO KATIKA MIEZI 3 ILIYOPITA NI ZAIDI YA 2000000, ENDELESHA. VINGINEVYO, RUDI NYUMA NA KUBADILI KIASI ILICHOINGIWA.] 1)ENDELEA | I71: =LEN(H71) | J71: Single Choice | K71: NA | L71: NA | M71: Form Type - Buttons | N71: NA | O71: 1 = income_main_gender | Q71: if income_main_amount_conf = 1, go to income_main_comp or optional question | T71: =1 | W71: no | AA71: 2.2273674 | AB71: =IF(AA71="","",AA71*T71) | AC71: =IF(W71="yes",AB71,"")
A72: =A71+1 | B72: income_main_gender | C72: income_main_gender | D72: What is the gender of the household member[s] generating income from this source? [OPERATOR: SINGLE RESPONSE.] 1)Male 2)Female 3)Joint [both male & female] 4)DON'T KNOW 5)REFUSED | E72: =LEN(D72) | F72: Quel est le sexe du ou des membres du ménage qui génèrent des revenus de cette source? [OPÉRATEUR/OPÉRATRICE: RÉPONSE UNIQUE]. 1)Homme 2)Femme 3)Mixte [homme et femme] 4)NE SAIT PAS 5)REFUSÉ | G72: =LEN(F72) | H72: Je, ni jinsia gani ya wanakaya wanaozalisha mapato kutoka kwa chanzo hiki?_x000D_ _x000D_ [OPERATOR: JIBU MOJA.]_x000D_ _x000D_ 1)Mwanaume_x000D_ 2)Mwanamke_x000D_ 3)Viungo [wote wa kiume na wa kike]_x000D_ 4)SIJUE_x000D_ 5)KUKATALA | I72: =LEN(H72) | J72: Single Choice | K72: NA | L72: NA | M72: Form Type - Buttons | N72: NA | O72: 1-5 = income_main_control | Q72: if income_main_gender = 1-5, go to income_main_comp or optional question | T72: =1 | W72: no | AA72: 4.7874017 | AB72: =IF(AA72="","",AA72*T72) | AC72: =IF(W72="yes",AB72,"")
A73: =A72+1 | B73: income_main_control | C73: income_main_control | D73: Who controls the revenue that is earned from this source? [OPERATOR: SINGLE RESPONSE.] 1)Male household member[s] 2)Female household member[s] 3)Joint household members [both female & male] 4)DON'T KNOW 5)REFUSED | E73: =LEN(D73) | F73: Qui contrôle les revenus qui proviennent de cette source? [OPÉRATEUR/OPÉRATRICE: RÉPONSE UNIQUE]. 1)Membre[s] masculin[s] du ménage 2)Membre[s] féminin[s] du ménage 3)Membres du ménage conjointement [femme et homme] 4)NE SAIT PAS 5)REFUSÉ | G73: =LEN(F73) | H73: Nani anadhibiti mapato yanayopatikana kutokana na chanzo hiki? [OPERATOR: JIBU MOJA.] 1)Mwanafamilia wa kiume 2)Wanakaya wa kike 3)Wanakaya wa pamoja [wanaume na wanawake] 4)SIJUE 5)KUKATALA | I73: =LEN(H73) | J73: Single Choice | K73: NA | L73: NA | M73: Form Type - Buttons | N73: NA | O73: 1-5 = income_main_comp | Q73: if income_main_control = 1-5, go to income_main_comp | T73: =1 | W73: no | AA73: 20.918367 | AB73: =IF(AA73="","",AA73*T73) | AC73: =IF(W73="yes",AB73,"")
A74: =A73+1 | B74: income_main_comp | C74: income_main_comp | D74: Has your household's income from {income_main} changed in the last 3 months compared to the same period of last year? [OPERATOR: SINGLE RESPONSE.] 1)A lot more [increased by more than 50%] 2)Slightly more 3)Same 4)Slightly less 5)A lot less [less than half as much] 6)DON'T KNOW 7)REFUSED | E74: =LEN(D74) | F74: Le revenu de votre ménage provenant de {income_main} a-t-il changé au cours des trois derniers mois par rapport à la même période de l'année dernière? [OPÉRATEUR/OPÉRATRICE: RÉPONSE UNIQUE.] 1)Très supérieur [augmentation de plus de 50%] 2)Légèrement supérieur 3)Identique 4)Légèrement inférieur 5)Très inférieur [moins de la moitié] 6)NE SAIT PAS 7)REFUSÉ | G74: =LEN(F74) | H74: "Je, mapato ya famille yako kutoka kwa {income_main} yamebadilika katika miezi 3 iliyopita ikilinganishwa na kipindi kama hicho mwaka uliopita? [OPERATOR: JIBU MOJA.] 1)Mengi zaidi [imeongezeka kwa zaidi ya 50%] 2)Zaidi kidogo 3)Sawa 4)Kidogo kidogo 5)Chini sana [chini ya nusu zaidi] 6)SIJUE 7)KUKATALA | I74: =LEN(H74) | J74: Single Choice | K74: NA | L74: NA | M74: Form Type - Buttons | N74: NA | O74: 1-7= income_sec | Q74: if income_main_comp = 1-7, go to income_sec | T74: =1 | W74: yes | AA74: 22.126215 | AB74: =IF(AA74="","",AA74*T74) | AC74: =IF(W74="yes",AB74,"")
A75: =A74+1 | B75: income_sec | C75: income_sec | D75: What was your household's second most important source of income in the past 3 months? [OPERATOR: SINGLE RESPONSE. DON'T KNOW AND REFUSED OPTIONS SHOULD BE AVOIDED AS MUCH AS POSSIBLE.] 1)Production and sale of staple crops 2)Production and sale of vegetable or fruit 3)Production and sale of cashcrops 4)Production and sale of livestock or livestock products 5)Production and sale of honey or bee products 6)Production and sale of fish or aquatic products 7)Collection and sale of forestry or bush products 8)Agricultural trade EXCLUDING producers [formal or informal] 9)Daily wage on farms and other casual employment in agricultural sector 10)Stable employment in agricultural sector 11)Non-agricultural self-employed or liberal profession / doctor / architect / lawyer / including restaurant 12)Off-farm daily wages and other non-agricultural casual employment 13)Stable employment in non-agricultural sector 14)Public employment 15)Income not derived from work / Charity 16)Income not derived from work / Welfare transfer/pension/ humanitarian aid 17)Income not derived from work / Remittances 18)Income not derived from work / Income from other rents 19)No second most important source of income 20)DON'T KNOW 21)REFUSED | E75: =LEN(D75) | F75: Quelle était la deuxième source principale de revenus de votre ménage au cours des trois derniers mois? [OPÉRATEUR/OPÉRATRICE: RÉPONSE UNIQUE. LES OPTIONS «NE SAIT PAS» ET «REFUSÉ» DOIVENT ÊTRE ÉVITÉES AUTANT QUE POSSIBLE]. 1)Production et vente de cultures vivrières 2)Production et vente de légumes ou de fruits 3)Production et vente de cultures de rente 4)Production et vente de bétail ou de produits animaux 5)Production et vente de miel ou de produits apicoles 6)Production et vente de poisson ou de produits aquatiques 7)Collecte et vente de produits forestiers ou de brousse 8)Commerce agricole EXCLUANT les producteurs [formel ou informel] 9)Salaire journalier dans une exploitation et autres emplois occasionnels dans le secteur agricole 10)Emploi stable dans le secteur agricole 11)Indépendant non-agricole ou profession libérale / médecin / architecte / avocat / y compris restaurant 12)Salaire journalier hors exploitation et autres emplois occasionnels non agricoles 13)Emploi stable dans le secteur non-agricole 14)Emploi public 15)Revenu non tiré du travail / Charité 16)Revenu non tiré du travail / Transferts sociaux/ pension/ aide humanitaire 17)Revenu non tiré du travail / Envois de fonds des migrants 18)Revenu non tiré du travail / Revenu d'autres loyers 19)Pas de deuxième source principale de revenus 20)NE SAIT PAS 21)REFUSÉ | G75: =LEN(F75) | H75: Ni chanzo gani cha pili cha mapato kwa kaya yako katika kipindi cha miezi 3 iliyopita? [OPERATOR: JIBU MOJA. SIJUE NA CHAGUO ZILIZOKUKATALA ZINAPASWA KUEPUKWA KADRI IWEZEKANAVYO.] 1)Uzalishaji na uuzaji wa mazao ya msingi 2)Uzalishaji na uuzaji wa mboga mboga au matunda 3)Uzalishaji na uuzaji wa mazao ya fedha 4)Uzalishaji na uuzaji wa mifugo au bidhaa za mifugo 5)Uzalishaji na uuzaji wa asali au mazao ya nyuki 6)Uzalishaji na uuzaji wa samaki au bidhaa za majini 7)Ukusanyaji na uuzaji wa mazao ya misitu au misitu 8)Biashara ya kilimo BILA KUWAHITIMIZA wazalishaji [rasmi au isiyo rasmi] 9)Mshahara wa kila siku kwenye mashamba na ajira yingine za kawaida katika sekta ya kilimo 10)Ajira imara katika sekta ya kilimo 11)Kazi isiyo ya kilimo au taaluma ya huria / daktari / mbunifu / mwanasheria / pamoja na mgahawa 12)Mshahara wa kila siku nje ya shamba na ajira yingine za kawaida zisizo za kilimo 13)Ajira imara katika sekta isiyo ya kilimo 14)Ajira za umma 15)Mapato yasiyotokana na kazi / Hisabati 16)Mapato yasiyotokana na kazi / Uhamisho wa ustawi / pensheni / misaada ya kibinadamu 17)Mapato yasiyotokana na kazi/Pesa 18)Mapato yasiyotokana na kazi / Mapato kutoka kwa kodi zingine 19)Hakuna chanzo cha pili muhimu zaidi cha mapato 20)SIJUE 21)KUKATALA | I75: =LEN(H75) | J75: Single Choice | K75: NA | L75: NA | M75: Form Type - Buttons exclude selected "income_main" IsDemographic - income_sec | N75: NA | O75: 1-3 = income_sec_crop_check 4 = income_sec_ls_check 5 = income_sec_amount 6 = income_sec_fish_check 7-18 = income_sec_amount 19-21 = shock | Q75: if options #1-3 selected, go to income_sec_crop_check if options #4 selected, go to income_sec_ls_check if options #6 selected, go to income_sec_fish_check if options #5, 7-18 selected, go to [income_sec_comp OR optional question] if options #19-21 selected, go to shock | T75: =1 | W75: yes | AA75: 18.710653 | AB75: =IF(AA75="","",AA75*T75) | AC75: =IF(W75="yes",AB75,"")
A76: =A75+1 | B76: income_sec_crop_check | C76: income_sec_crop_check | D76: Are the crops sold also produced by you or anyone in your household? [OPERATOR: SINGLE RESPONSE.] 1)YES 2)NO 3)DON'T KNOW 4)REFUSED | E76: =LEN(D76) | F76: Les cultures vendues sont-elles également produites par vous ou quelqu'un de votre ménage? [OPÉRATEUR/OPÉRATRICE: RÉPONSE UNIQUE.] 1)OUI 2)NON 3)NE SAIT PAS 4)REFUSÉ | G76: =LEN(F76) | H76: Je, mazao yanayouzwa pia yamezalishwa na wewe au mtu yeyote katika famille yako? [OPERATOR: JIBU MOJA.] 1)NDIYO 2)HAPANA 3)SIJUE 4)KUKATALA | I76: =LEN(H76) | J76: Single Choice | K76: NA | L76: NA | M76: Form Type - Buttons | N76: NA | O76: 1-4 = income_sec_amount | Q76: if income_sec_crop_check = 1-4, go to [income_sec_comp OR optional question] | T76: =1 | W76: yes | AA76: 8 | AB76: =IF(AA76="","",AA76*T76) | AC76: =IF(W76="yes",AB76,"")
A77: =A76+1 | B77: income_sec_ls_check | C77: income_sec_ls_check | D77: Are the livestock or livestock products sold also produced by you or anyone in your household? [OPERATOR: SINGLE RESPONSE.] 1)YES 2)NO 3)DON'T KNOW 4)REFUSED | E77: =LEN(D77) | F77: Le bétail ou les produits du bétail vendus sont-ils également produits par vous ou quelqu'un de votre ménage? [OPÉRATEUR/OPÉRATRICE: RÉPONSE UNIQUE.] 1)OUI 2)NON 3)NE SAIT PAS 4)REFUSÉ | G77: =LEN(F77) | H77: Je, mifugo au bidhaa za mifugo zinazouzwa pia zimezalishwa na wewe au mtu yeyote katika famille yako? [OPERATOR: JIBU MOJA.] 1)NDIYO 2)HAPANA 3)SIJUE 4)KUKATALA | I77: =LEN(H77) | J77: Single Choice | K77: NA | L77: NA | M77: Form Type - Buttons | N77: NA | O77: 1-4 = income_sec_amount | Q77: if income_sec_ls_check = 1-4, go to [income_sec_comp OR optional question] | T77: =1 | W77: yes | AA77: 8 | AB77: =IF(AA77="","",AA77*T77) | AC77: =IF(W77="yes",AB77,"")
A78: =A77+1 | B78: income_sec_fish_check | C78: income_sec_fish_check | D78: Are the fish or aquatic products sold also captured/harvested by you or anyone in your household? [OPERATOR: SINGLE RESPONSE.] 1)YES 2)NO 3)DON'T KNOW 4)REFUSED | E78: =LEN(D78) | F78: Le poisson ou les produits aquatiques vendus sont-ils également capturés/récoltés par vous ou un membre de votre ménage? [OPÉRATEUR/OPÉRATRICE: RÉPONSE UNIQUE.] 1)OUI 2)NON 3)NE SAIT PAS 4)REFUSÉ | G78: =LEN(F78) | H78: Je, samaki au bidhaa za majini zinazouzwa pia zimevuliwa/kuvunwa na wewe au mtu yeyote katika famille yako? [OPERATOR: JIBU MOJA.] 1)NDIYO 2)HAPANA 3)SIJUE 4)KUKATALA | I78: =LEN(H78) | J78: Single Choice | K78: NA | L78: NA | M78: Form Type - Buttons | N78: NA | O78: 1-4 = income_sec_amount | Q78: if income_sec_fish_check = 1-4, go to [income_sec_comp OR optional question] | T78: =1 | W78: yes | AA78: 8 | AB78: =IF(AA78="","",AA78*T78) | AC78: =IF(W78="yes",AB78,"")
A79: =A78+1 | B79: income_sec_amount | C79: income_sec_amount | D79: How much was earned [in CDF] from your second main income source, {income_sec}, in the past 3 months ? [OPERATOR: MAKE SURE THE INFORMATION IS RECORDED IN THE CORRECT CURRENCY. ENTER 88888888 FOR DON'T KNOW AND 99999999 FOR REFUSED.] | E79: =LEN(D79) | F79: Quelle somme [en CDF] a rapporté votre deuxième principale source de revenu, {income_sec}, au cours des trois derniers mois? [OPÉRATEUR/OPÉRATRICE: VÉRIFIER QUE LA RÉPONSE EST ENREGISTRÉE DANS LA BONNE DEVISE. SAISIR 88888888 POUR «NE SAIT PAS» ET 99999999 POUR «REFUSÉ».] | G79: =LEN(F79) | H79: Je, ni kiasi gani kilipatikana [katika CDF] kutoka kwa chanzo chako kikuu cha pili cha mapato, {income_sec}, katika kipindi cha miezi 3 iliyopita ? [OPERATOR: HAKIKISHA HABARI IMEREKODIWA KWA SARAFU SAHIHI. INGIA 888888888 KWA SIJUE NA 999999999 KWA KUKUKATALA.] | I79: =LEN(H79) | J79: Range | K79: NA | L79: NA | M79: Form Type - TextBox | N79: NA | O79: 10000 - 2000000 = income_sec_gender 2000001 - 30000000 = income_sec_amount_conf 88888888-88888888 = income_sec_gender 99999999-99999999 = income_sec_gender | Q79: If the income amount is over the threshold set in "Additional information", the respondent will be asked to confirm with income_sec_amount_conf. Otherwise, go to income_sec_comp. | S79: We recommend using this pair of questions together. | T79: =1 | W79: no | AA79: 23.20038 | AB79: =IF(AA79="","",AA79*T79) | AC79: =IF(W79="yes",AB79,"")
A80: =A79+1 | B80: income_sec_amount_conf | C80: income_sec_amount_conf | D80: Can you confirm the amount of income you just stated is correct? [OPERATOR: IF THE AMOUNT EARNED FROM THIS INCOME SOURCE OVER THE PAST 3 MONTH IS INDEED OVER 2000000, CLICK ON CONTINUE. OTHERWISE, GO BACK AND CHANGE THE AMOUNT ENTERED.] 1)CONTINUE | E80: =LEN(D80) | F80: Pouvez-vous confirmer que le montant que vous venez de déclarer est correct? [OPÉRATEUR/OPÉRATRICE: SI LE MONTANT ISSU DE CETTE SOURCE DE REVENU AU COURS DES TROIS DERNIERS MOIS EST SUPÉRIEUR AU 2000000, CLIQUER SUR CONTINUER. SINON, REVENIR EN ARRIÈRE ET MODIFIER LE MONTANT SAISI.] 1)CONTINUER | G80: =LEN(F80) | H80: Unaweza kuthibitisha kiasi cha mapato ulichosema ni sahihi? [OPERATOR: IWAPO KIASI KILICHOCHUKUA KUTOKA KWA CHANZO HIKI CHA MAPATO KATIKA MIEZI 3 ILIYOPITA NI ZAIDI YA 2000000, ENDELESHA. VINGINEVYO, RUDI NYUMA NA KUBADILI KIASI ILICHOINGIWA.] 1)ENDELEA | I80: =LEN(H80) | J80: Single Choice | K80: NA | L80: NA | M80: Form Type - Buttons | N80: NA | O80: 1 = income_sec_gender | Q80: if income_sec_amount_conf = 1, go to income_sec_comp | T80: =1 | W80: no | AA80: 1.9277389 | AB80: =IF(AA80="","",AA80*T80) | AC80: =IF(W80="yes",AB80,"")
A81: =A80+1 | B81: income_sec_gender | C81: income_sec_gender | D81: What is the gender of the household member[s] generating income from this source? [OPERATOR: SINGLE RESPONSE.] 1)Male 2)Female 3)Joint [both male & female] 4)DON'T KNOW 5)REFUSED | E81: =LEN(D81) | F81: Quel est le sexe du ou des membres du ménage qui génèrent des revenus de cette source? [OPÉRATEUR/OPÉRATRICE: RÉPONSE UNIQUE]. 1)Homme 2)Femme 3)Mixte [homme et femme] 4)NE SAIT PAS 5)REFUSÉ | G81: =LEN(F81) | H81: Ni jinsia gani ya wanakaya wanaozalisha mapato kutoka kwa chanzo hiki? [OPERATOR: JIBU MOJA.] 1)Mwanaume 2)Mwanamke 3)Viungo [wote wa kiume na wa kike] 4)SIJUE 5)KUKATALA | I81: =LEN(H81) | J81: Single Choice | K81: NA | L81: NA | M81: Form Type - Buttons | N81: NA | O81: 1-5 = income_sec_control | Q81: if income_sec_gender = 1-5, go to income_sec_comp or optional question | T81: =1 | W81: no | AA81: 4.7874017 | AB81: =IF(AA81="","",AA81*T81) | AC81: =IF(W81="yes",AB81,"")
A82: =A81+1 | B82: income_sec_control | C82: income_sec_control | D82: Who controls the revenue that is earned from this source? [OPERATOR: SINGLE RESPONSE.] 1)Male household member[s] 2)Female household member[s] 3)Joint household members [both female & male] 4)DON'T KNOW 5)REFUSED | E82: =LEN(D82) | F82: Qui contrôle les revenus qui proviennent de cette source? [OPÉRATEUR/OPÉRATRICE: RÉPONSE UNIQUE]. 1)Membre[s] masculin[s] du ménage 2)Membre[s] féminin[s] du ménage 3)Membres du ménage conjointement [femme et homme] 4)NE SAIT PAS 5)REFUSÉ | G82: =LEN(F82) | H82: Nani anadhibiti mapato yanayopatikana kutokana na chanzo hiki? [OPERATOR: JIBU MOJA.] 1)Mwanafamilia wa kiume 2)Wanakaya wa kike 3)Wanakaya wa pamoja [wanaume na wanawake] 4)SIJUE 5)KUKATALA | I82: =LEN(H82) | J82: Single Choice | K82: NA | L82: NA | M82: Form Type - Buttons | N82: NA | O82: 1-5 = income_sec_comp | Q82: if income_sec_control = 1-5, go to income_sec_comp | T82: =1 | W82: no | AA82: 20.918367 | AB82: =IF(AA82="","",AA82*T82) | AC82: =IF(W82="yes",AB82,"")
A83: =A82+1 | B83: income_sec_comp | C83: income_sec_comp | D83: Has your household's income from {income_sec} changed in the last 3 months compared to the same period of last year? [OPERATOR: SINGLE RESPONSE.] 1)A lot more [increased by more than 50%] 2)Slightly more 3)Same 4)Slightly less 5)A lot less [less than half as much] 6)DON'T KNOW 7)REFUSED | E83: =LEN(D83) | F83: Le revenu de votre ménage provenant de {income_sec} a-t-il changé au cours des trois derniers mois par rapport à la même période de l'année dernière? [OPÉRATEUR/OPÉRATRICE: RÉPONSE UNIQUE.] 1)Très supérieur [augmentation de plus de 50%] 2)Légèrement supérieur 3)Identique 4)Légèrement inférieur 5)Très inférieur [moins de la moitié] 6)NE SAIT PAS 7)REFUSÉ | G83: =LEN(F83) | H83: Je, mapato ya famille yako kutoka kwa {income_sec} yamebadilika katika miezi 3 iliyopita ikilinganishwa na kipindi kama hicho mwaka uliopita? [OPERATOR: JIBU MOJA.] 1)Mengi zaidi [imeongezeka kwa zaidi ya 50%] 2)Zaidi kidogo 3)Sawa 4)Kidogo kidogo 5)Chini sana [chini ya nusu zaidi] 6)SIJUE 7)KUKATALA | I83: =LEN(H83) | J83: Single Choice | K83: NA | L83: NA | M83: Form Type - Buttons | N83: NA | O83: 1-7= income_thirdaaaaaaaa | Q83: if income_sec_comp = 1-7, go to income_third | T83: =1 | W83: yes | AA83: 17.261402 | AB83: =IF(AA83="","",AA83*T83) | AC83: =IF(W83="yes",AB83,"")
A84: =A83+1 | B84: income_third | C84: income_third | D84: What was your household's third most important source of income in the past 3 months? [OPERATOR: SINGLE RESPONSE. DON'T KNOW AND REFUSED OPTIONS SHOULD RARELY/NOT AVOIDED AS MUCH AS POSSIBLE.] 1)Production and sale of staple crops 2)Production and sale of vegetable or fruit 3)Production and sale of cashcrops 4)Production and sale of livestock or livestock products 5)Production and sale of honey or bee products 6)Production and sale of fish or aquatic products 7)Collection and sale of forestry or bush products 8)Agricultural trade EXCLUDING producers [formal and informal] 9)Daily wage on farms and other casual employment in agricultural sector 10)Stable employment in agricultural sector 11)Non-agricultural self-employed or liberal profession / doctor / architect / lawyer / including restaurant 12)Off-farm daily wages and other non-agricultural casual employment 13)Stable employment in non-agricultural sector 14)Public employment 15)Income not derived from work / Charity 16)Income not derived from work / Welfare transfer/ pension/ humanitarian aid 17)Income not derived from work / Remittances 18)Income not derived from work / Income from other rents 19)No third most important source of income 20)DON'T KNOW 21)REFUSED | E84: =LEN(D84) | F84: Quelle était la troisième source principale de revenus de votre ménage au cours des trois derniers mois? [OPÉRATEUR/OPÉRATRICE: RÉPONSE UNIQUE. LES OPTIONS «NE SAIT PAS» ET «REFUSÉ» DOIVENT ÊTRE ÉVITÉES AUTANT QUE POSSIBLE]. 1)Production et vente de cultures vivrières 2)Production et vente de légumes ou de fruits 3)Production et vente de cultures de rente 4)Production et vente de bétail ou de produits animaux 5)Production et vente de miel ou de produits apicoles 6)Production et vente de poisson ou de produits aquatiques 7)Collecte et vente de produits forestiers ou de brousse 8)Commerce agricole EXCLUANT les producteurs [formel ou informel] 9)Salaire journalier dans une exploitation et autres emplois occasionnels dans le secteur agricole 10)Emploi stable dans le secteur agricole 11)Indépendant non-agricole ou profession libérale / médecin / architecte / avocat / y compris restaurant 12)Salaire journalier hors exploitation et autres emplois occasionnels non agricoles 13)Emploi stable dans le secteur non-agricole 14)Emploi public 15)Revenu non tiré du travail / Charité 16)Revenu non tiré du travail / Transferts sociaux/ pension/ aide humanitaire 17)Revenu non tiré du travail / Envois de fonds des migrants 18)Revenu non tiré du travail / Revenu d'autres loyers 19)Pas de troisième source principale de revenus 20)NE SAIT PAS 21)REFUSÉ | G84: =LEN(F84) | H84: Ni nini kilikuwa chanzo cha tatu cha mapato kwa kaya yako katika kipindi cha miezi 3 iliyopita? [OPERATOR: JIBU MOJA. SIJUE NA CHAGUO ZILIZOKUKATALA SI KWA MARA KWA MARA/SIZOEPUKWA KADIRI IWEZEKANAVYO.] 1)Uzalishaji na uuzaji wa mazao ya msingi 2)Uzalishaji na uuzaji wa mboga mboga au matunda 3)Uzalishaji na uuzaji wa mazao ya fedha 4)Uzalishaji na uuzaji wa mifugo au bidhaa za mifugo 5)Uzalishaji na uuzaji wa asali au mazao ya nyuki 6)Uzalishaji na uuzaji wa samaki au bidhaa za majini 7)Ukusanyaji na uuzaji wa mazao ya misitu au misitu 8)Biashara ya kilimo BILA KUWAHITIMIZA wazalishaji [rasmi au isiyo rasmi] 9)Mshahara wa kila siku kwenye mashamba na ajira yingine za kawaida katika sekta ya kilimo 10)Ajira imara katika sekta ya kilimo 11)Kazi isiyo ya kilimo au taaluma ya huria / daktari / mbunifu / mwanasheria / pamoja na mgahawa 12)Mshahara wa kila siku nje ya shamba na ajira yingine za kawaida zisizo za kilimo 13)Ajira imara katika sekta isiyo ya kilimo 14)Ajira za umma 15)Mapato yasiyotokana na kazi / Hisabati 16)Mapato yasiyotokana na kazi / Uhamisho wa ustawi / pensheni / misaada ya kibinadamu 17)Mapato yasiyotokana na kazi/Pesa 18)Mapato yasiyotokana na kazi / Mapato kutoka kwa kodi zingine 19)Hakuna chanzo cha tatu muhimu zaidi cha mapato 20)SIJUE 21)KUKATALA | I84: =LEN(H84) | J84: Single Choice | K84: NA | L84: NA | M84: Form Type - Buttons exclude selected "income_main" exclude selected "income_sec" IsDemographic - income_third | N84: NA | O84: 1-3 = income_third_crop_check 4 = income_third_ls_check 5 = income_third_amount 6 = income_third_fish_check 7-18 = income_third_amount 19-21 = shock | Q84: if options #1-3 selected, go to income_third_crop_check if options #4 selected, go to income_third_ls_check if option #6 selected, go to income_third_fish_check if options #5, 7-18 selected, go to [income_third_comp OR optional question] if options #19-21 selected, go to shock | T84: =1 | W84: yes | AA84: 14.475392 | AB84: =IF(AA84="","",AA84*T84) | AC84: =IF(W84="yes",AB84,"")
A85: =A84+1 | B85: income_third_crop_check | C85: income_third_crop_check | D85: Are the crops sold also produced by you or anyone in your household? [OPERATOR: SINGLE RESPONSE.] 1)YES 2)NO 3)DON'T KNOW 4)REFUSED | E85: =LEN(D85) | F85: Les cultures vendues sont-elles également produites par vous ou quelqu'un de votre ménage? [OPÉRATEUR/OPÉRATRICE: RÉPONSE UNIQUE.] 1)OUI 2)NON 3)NE SAIT PAS 4)REFUSÉ | G85: =LEN(F85) | H85: Je, mazao yanayouzwa pia yamezalishwa na wewe au mtu yeyote katika famille yako? [OPERATOR: JIBU MOJA.] 1)NDIYO 2)HAPANA 3)SIJUE 4)KUKATALA | I85: =LEN(H85) | J85: Single Choice | K85: NA | L85: NA | M85: Form Type - Buttons | N85: NA | O85: 1-4 = income_third_amount | Q85: if income_third_crop_check = 1-4, go to [income_third_comp OR optional question] | T85: =1 | W85: yes | AA85: 8 | AB85: =IF(AA85="","",AA85*T85) | AC85: =IF(W85="yes",AB85,"")
A86: =A85+1 | B86: income_third_ls_check | C86: income_third_ls_check | D86: Are the livestock or livestock products sold also produced by you or anyone in your household? [OPERATOR: SINGLE RESPONSE.] 1)YES 2)NO 3)DON'T KNOW 4)REFUSED | E86: =LEN(D86) | F86: Le bétail ou les produits du bétail vendus sont-ils également produits par vous ou quelqu'un de votre ménage? [OPÉRATEUR/OPÉRATRICE: RÉPONSE UNIQUE.] 1)OUI 2)NON 3)NE SAIT PAS 4)REFUSÉ | G86: =LEN(F86) | H86: Je, mifugo au bidhaa za mifugo zinazouzwa pia zimezalishwa na wewe au mtu yeyote katika famille yako? [OPERATOR: JIBU MOJA.] 1)NDIYO 2)HAPANA 3)SIJUE 4)KUKATALA | I86: =LEN(H86) | J86: Single Choice | K86: NA | L86: NA | M86: Form Type - Buttons | N86: NA | O86: 1-4 = income_third_amount | Q86: if income_third_ls_check = 1-4, go to [income_third_comp OR optional question] | T86: =1 | W86: yes | AA86: 8 | AB86: =IF(AA86="","",AA86*T86) | AC86: =IF(W86="yes",AB86,"")
A87: =A86+1 | B87: income_third_fish_check | C87: income_third_fish_check | D87: Are the fish or aquatic products sold also captured/harvested by you or anyone in your household? [OPERATOR: SINGLE RESPONSE.] 1)YES 2)NO 3)DON'T KNOW 4)REFUSED | E87: =LEN(D87) | F87: Le poisson ou les produits aquatiques vendus sont-ils également capturés/récoltés par vous ou un membre de votre ménage? [OPÉRATEUR/OPÉRATRICE: RÉPONSE UNIQUE.] 1)OUI 2)NON 3)NE SAIT PAS 4)REFUSÉ | G87: =LEN(F87) | H87: Je, samaki au bidhaa za majini zinazouzwa pia zimevuliwa/kuvunwa na wewe au mtu yeyote katika famille yako? [OPERATOR: JIBU MOJA.] 1)NDIYO 2)HAPANA 3)SIJUE 4)KUKATALA | I87: =LEN(H87) | J87: Single Choice | K87: NA | L87: NA | M87: Form Type - Buttons | N87: NA | O87: 1-4 = income_third_amount | Q87: if income_third_fish_check = 1-4, go to [income_third_comp OR optional question] | T87: =1 | W87: yes | AA87: 8 | AB87: =IF(AA87="","",AA87*T87) | AC87: =IF(W87="yes",AB87,"")
A88: =A87+1 | B88: income_third_amount | C88: income_third_amount | D88: How much was earned [in CDF] from your third main source of income, {income_third}, in the past 3 months ? [OPERATOR: MAKE SURE THE INFORMATION IS RECORDED IN THE CORRECT CURRENCY. ENTER 88888888 FOR DON'T KNOW AND 99999999 FOR REFUSED.] | E88: =LEN(D88) | F88: Quelle somme [en CDF] a rapporté votre troisième principale source de revenu, {income_third}, au cours des trois derniers mois? [OPÉRATEUR/OPÉRATRICE: VÉRIFIER QUE LA RÉPONSE EST ENREGISTRÉE DANS LA BONNE DEVISE. SAISIR 88888888 POUR «NE SAIT PAS» ET 99999999 POUR «REFUSÉ».] | G88: =LEN(F88) | H88: Ni kiasi gani kilipatikana [katika CDF] kutoka kwa chanzo chako kikuu cha tatu cha mapato, {income_third}, katika kipindi cha miezi 3 iliyopita ? [OPERATOR: HAKIKISHA HABARI IMEREKODIWA KWA SARAFU SAHIHI. INGIA 888888888 KWA SIJUE NA 999999999 KWA KUKUKATALA.] | I88: =LEN(H88) | J88: Range | K88: NA | L88: NA | M88: Form Type - TextBox | N88: NA | O88: 10000 - 2000000 = income_third_comp 2000001 - 30000000 = income_third_amount_conf 88888888-88888888 = income_third_comp 99999999-99999999 = income_third_comp | Q88: If the income amount is over the threshold set in "Additional information", the respondent will be asked to confirm with income_third_amount_conf. Otherwise, go to income_third_comp or optional question. | S88: We recommend using this pair of questions together. | T88: =1 | W88: no | AA88: 24.401098 | AB88: =IF(AA88="","",AA88*T88) | AC88: =IF(W88="yes",AB88,"")
A89: =A88+1 | B89: income_third_amount_conf | C89: income_third_amount_conf | D89: Can you confirm the amount of income you just stated is correct? [OPERATOR: IF THE AMOUNT EARNED FROM THIS INCOME SOURCE OVER THE PAST 3 MONTH IS INDEED OVER 2000000, CLICK ON CONTINUE. OTHERWISE, GO BACK AND CHANGE THE AMOUNT ENTERED.] 1)CONTINUE | E89: =LEN(D89) | F89: Pouvez-vous confirmer que le montant que vous venez de déclarer est correct? [OPÉRATEUR/OPÉRATRICE: SI LE MONTANT ISSU DE CETTE SOURCE DE REVENU AU COURS DES TROIS DERNIERS MOIS EST SUPÉRIEUR AU 2000000, CLIQUER SUR CONTINUER. SINON, REVENIR EN ARRIÈRE ET MODIFIER LE MONTANT SAISI.] 1)CONTINUER | G89: =LEN(F89) | H89: Unaweza kuthibitisha kiasi cha mapato ulichosema ni sahihi? [OPERATOR: IWAPO KIASI KILICHOCHUKUA KUTOKA KWA CHANZO HIKI CHA MAPATO KATIKA MIEZI 3 ILIYOPITA NI ZAIDI YA 2000000, BENDELEASHA. VINGINEVYO, RUDI NYUMA NA KUBADILI KIASI ILICHOINGIWA.] 1)ENDELEA | I89: =LEN(H89) | J89: Single Choice | K89: NA | L89: NA | M89: Form Type - Buttons | N89: NA | O89: 1 = income_third_comp | Q89: if income_third_amount_conf = 1, go to income_third_comp or optional question | T89: =1 | W89: no | AA89: 2.47 | AB89: =IF(AA89="","",AA89*T89) | AC89: =IF(W89="yes",AB89,"")
A90: =A89+1 | B90: income_third_comp | C90: income_third_comp | D90: Has your household's income from {income_third} changed in the last 3 months compared to the same period of last year? [OPERATOR: SINGLE RESPONSE.] 1)A lot more [increased by more than 50%] 2)Slightly more 3)Same 4)Slightly less 5)A lot less [less than half as much] 6)DON'T KNOW 7)REFUSED | E90: =LEN(D90) | F90: Le revenu de votre ménage provenant de {income_third} a-t-il changé au cours des trois derniers mois par rapport à la même période de l'année dernière? [OPÉRATEUR/OPÉRATRICE: RÉPONSE UNIQUE.] 1)Très supérieur [augmentation de plus de 50%] 2)Légèrement supérieur 3)Identique 4)Légèrement inférieur 5)Très inférieur [moins de la moitié] 6)NE SAIT PAS 7)REFUSÉ | G90: =LEN(F90) | H90: Je, mapato ya famille yako kutoka kwa {income_third} yamebadilika katika miezi 3 iliyopita ikilinganishwa na kipindi kama hicho mwaka uliopita? [OPERATOR: JIBU MOJA.] 1)Mengi zaidi [imeongezeka kwa zaidi ya 50%] 2)Zaidi kidogo 3)Sawa 4)Kidogo kidogo 5)Chini sana [chini ya nusu zaidi] 6)SIJUE 7)KUKATALA | I90: =LEN(H90) | J90: Single Choice | K90: NA | L90: NA | M90: Form Type - Buttons | N90: NA | O90: 1-7= shock | Q90: if income_third_comp = 1-7, go to shock | T90: =1 | W90: yes | AA90: 15.876503 | AB90: =IF(AA90="","",AA90*T90) | AC90: =IF(W90="yes",AB90,"")
A91: =A90+1 | B91: shock | C91: shock_ 1) shock_noshock 2) shock_sicknessordeathofhh 3) shock_lostemplorwork 4) shock_otherintrahhshock 5) shock_higherfoodprices 6) shock_higherfuelprices 7) shock_mvtrestrict 8) shock_othereconomicshock 9) shock_pestoutbreak 10) shock_plantdisease 11) shock_animaldisease 12) shock_napasture 13) shock_othercropandlivests 14) shock_coldtemporhail 15) shock_flood 16) shock_hurricane 17) shock_drought 18) shock_earthquake 19) shock_landslides 20) shock_firenatural 21) shock_othernathazard 22) shock_violenceinsecconf 23) shock_theftofprodassets 24) shock_firemanmade 25) shock_othermanmadehazard 26) shock_dk 27) shock_ref | D91: Has your household or community faced any particular disaster or crisis affecting your household's ability to raise an income and/or to produce food for self consumption in the last 3 months, and if so, which one[s]? [OPERATOR: SELECT RELEVANT SHOCKS EXPERIENCED BY THE HOUSEHOLD. MULTIPLE RESPONSES POSSIBLE. REFER TO ECONOMIC SHOCKS, CROP AND LIVESTOCK SHOCKS, INTRA-HOUSEHOLD SHOCK, NATURAL HAZARDS AND HUMAN-INDUCED HAZARDS.] 1)No shock 2)Sickness or accident or death of household member[s] [sickness of breadwinner / unusually high medical expenditure / funeral expenses / death of breadwinner] 3)Lost employment or working opportunities [not due to illness/accident] 4)Other intra-household shock 5)Unusually high food prices 6)Unusually high fuel prices or transport prices 7)Population movement restrictions [e.g. due to epidemic or infrastructure damage] 8)Other economic shock 9)Pest outbreak 10)Plant disease 11)Animal disease [affecting many animals] or death 12)Lack of physical access to pasture 13)Other crop and livestock shock 14)Cold temperatures or hail 15)Flood / riverbank erosion 16)Hurricane / cyclone / tornado 17)Drought / heat stress 18)Earthquake 19)Landslides 20)Fire from natural disaster 21)Other natural hazard 22)Violence and insecurity / conflict 23)Theft of production assets [land / livestock / tools / etc] 24)Fire from human-induced disaster 25)Other human-induced hazard 26)DON'T KNOW 27)REFUSED | E91: =LEN(D91) | F91: Au cours des trois derniers mois, est-ce que votre ménage ou votre communauté ont été confrontés à une catastrophe ou une crise particulières qui a atteint votre capacité à dégager un revenu et/ou à produire des aliments pour votre propre consommation? Si oui, lesquelles? [OPÉRATEUR/OPÉRATRICE: SÉLECTIONNER LES CHOCS PERTINENTS SUBIS PAR LE MÉNAGE. PLUSIEURS RÉPONSES POSSIBLES. SE RÉFÉRER AUX CHOCS ÉCONOMIQUES, AUX CHOCS TOUCHANT LES RÉCOLTES ET LE BÉTAIL, AUX CHOCS INTRA-MÉNAGE, AUX RISQUES NATURELS ET AUX RISQUES D'ORIGINE HUMAINE] 1)Aucun choc 2)Maladie/ accident ou décès d'un ou plusieurs membres du ménage [maladie du soutien de famille / dépenses médicales anormalement élevées / frais funéraires / décès du soutien de famille] 3)Perte d'emploi ou d'opportunités de travail [non due à la maladie ou à un accident] 4)Autre choc interne au ménage 5)Prix des denrées alimentaires anormalement élevés 6)Prix des carburants ou des transports anormalement élevés 7)Restrictions de mouvements de population [par exemple en raison d'une épidémie ou de dommages causés aux infrastructures]. 8)Autre choc économique 9)Invasion d'organismes nuisibles 10)Maladie des plantes 11)Maladie animale [touchant de nombreux animaux] ou mort d'animaux 12)Accès difficile aux pâturages 13)Autre choc touchant les cultures et le bétail 14)Températures froides / grêle 15)Inondations / érosion des berges 16)Ouragan / cyclone / tornade 17)Sécheresse / stress dû à la chaleur 18)Tremblement de terre 19)Glissement de terrain 20)Incendie dû à une catastrophe naturelle 21)Autre risque naturel 22)Violence et insécurité / conflit 23)Vol d'actifs de production [terres/ bétail/ outils/ etc.] 24)Incendie dû à une catastrophe d'origine humaine 25)Autre risque d'origine humaine 26)NE SAIT PAS 27)REFUSÉ | G91: =LEN(F91) | H91: Kaya yako au jumuiya imekabiliwa na maafa au mgogoro wowote unaoathiri uwezo wa kaya yako kuongeza kipato na/au kuzalisha chakula kwa ajili ya matumizi binafsi katika muda wa miezi 3 iliyopita, na kama ni hivyo, ni ipi? [OPERATOR: CHAGUA MISHTUKO HUSIKA ILIYOPATWA NA KAYA. MAJIBU MENGI YANAWEZEKANA. REJEA MATUKIO YA KIUCHUMI, MISHTUKO YA MAZAO NA MIFUGO, MSHTUKO WA NDANI YA KAYA, MADHARA YA ASILI NA MADHARA YANAYOTOLEWA NA BINADAMU.] 1)Hakuna mshtuko 2)Ugonjwa au ajali au kifo cha wanakaya [ugonjwa wa mtunza riziki / matumizi makubwa ya matibabu / gharama za mazishi / kifo cha mlezi] 3)Kupoteza ajira au nafasi za kazi [si kwa sababu ya ugonjwa/ajali] 4)Mshtuko mwingine wa ndani ya kaya 5)Bei ya juu ya vyakula isiyo ya kawaida 6)Bei ya juu isiyo ya kawaida ya mafuta au bei za usafiri 7)Vizuizi vya harakati za idadi ya watu [k.m. kutokana na janga au uharibifu wa miundombinu] 8)Mshtuko mwingine wa kiuchumi 9)Mlipuko wa wadudu 10)Ugonjwa wa mimea 11)Ugonjwa wa wanyama [unaoathiri wanyama wengi] au kifo 12)Ukosefu wa kupata malisho ya kimwili 13)Mshtuko mwingine wa mazao na mifugo 14)Baridi au mvua ya mawe 15)Mmomonyoko wa mafuriko/kingo za mto 16)Kimbunga / kimbunga / kimbunga 17)Mkazo wa ukame / joto 18)Tetemeko la ardhi 19)Maporomoko ya ardhi 20)Moto kutoka kwa maafa ya asili 21)Hatari yingine ya asili 22)Vurugu na ukosefu wa usalama / migogoro 23)Wizi wa mali za uzalishaji [ardhi / mifugo / zana / nk] 24)Moto kutokana na maafa yanayosababishwa na binadamu 25)Hatari yingine inayosababishwa na binadamu 26)SIJUE 27)KUKATALA | I91: =LEN(H91) | J91: Select All That Apply | K91: NA | L91: NA | M91: Form Type - Checklist 1,26,27 = IsNone | N91: 1)shock_noshock 2)shock_sicknessordeathofhh 3)shock_lostemplorwork 4)shock_otherintrahhshock 5)shock_higherfoodprices 6)shock_higherfuelprices 7)shock_mvtrestrict 8)shock_othereconomicshock 9)shock_pestoutbreak 10)shock_plantdisease 11)shock_animaldisease 12)shock_napasture 13)shock_othercropandlivests 14)shock_coldtemporhail 15)shock_flood 16)shock_hurricane 17)shock_drought 18)shock_earthquake 19)shock_landslides 20)shock_firenatural 21)shock_othernathazard 22)shock_violenceinsecconf 23)shock_theftofprodassets 24)shock_firemanmade 25)shock_othermanmadehazard 26)shock_dk 27)shock_ref | O91: 1-27 = confl_wellbeing | Q91: if shock = 1-27, go to [crp_intro or optional question] | T91: =1 | W91: yes | AA91: 37.85363 | AB91: =IF(AA91="","",AA91*T91) | AC91: =IF(W91="yes",AB91,"")
A92: D. CROP PRODUCTION | AB92: =IF(AA92="","",AA92*T92) | AC92: =IF(W92="yes",AB92,"")
A93: 67 | B93: confl_wellbeing | C93: confl_wellbeing 1)confl_wb_none 2)confl_wb_livelihood 3)confl_wb_health 4)confl_wb_transport 5)confl_wb_edu 6)confl_wb_housing 7)confl_wb_food_water 8)confl_wb_safety 9)confl_wb_land_sec 10)confl_wb_nat_disaster 11)confl_wb_corrupt 12)confl_wb_fin_crisis 13)confl_wb_assistance 14)confl_wb_other 15)confl_wb_dk 16)confl_wb_ref | D93: What are the main problems affecting your household's wellbeing? [OPERATOR: UP TO THREE RESPONSES ALLOWED.] 1)There are no issues or concerns 2)Unemployment / lack of livelihoods options 3)Health concerns / health care [lack of or inadequate] 4)Transportation [lack of or inadequate] 5)Education [lack of or inadequate] 6)Access to shelter or housing [lack of or inadequate] 7)Access to food/water [lack of or inadequate] 8)Insecurity and the safety of household members 9)Security of land or property [lack of or inadequate] 10)Natural disasters [droughts/ floods/ fires or erosion] 11)Informal payments / corruption 12)Economic / financial crisis [poor currency exchange] 13)Accessing or receiving assistance 14)Other [specify] 15)DON'T KNOW 16)REFUSED | E93: =LEN(D93) | F93: Quels sont les principaux problèmes qui affectent le bien-être de votre ménage ? [OPÉRATEUR : JUSQU'À TROIS RÉPONSES POSSIBLES]. 1)Aucun problème / préoccupation 2)Chômage / manque d'options de moyens d'existence 3)Problèmes de santé / soins de santé [insuffisants ou inadéquats] 4)Transports [manque ou inadéquation] 5)Éducation [insuffisante ou inadéquate] 6)Accès à un abri ou à un logement [insuffisant ou inadéquat] 7)Accès à la nourriture et à l'eau [insuffisant ou inadéquat] 8)Insécurité et la sécurité des membres du ménage 9)Sécurité des terres ou des biens [insuffisante ou inadéquate] 10)Catastrophes naturelles [sécheresses / inondations/ incendies ou érosion] 11)Paiements informels / corruption 12)Crise économique / financière [mauvais taux de change] 13)Accès à l'aide ou réception de l'aide 14)Autre [préciser] 15)NE SAIT PAS 16)REFUS | G93: =LEN(F93) | H93: Je, ni masuala gani kuu yanayoathiri ustawi wa jamii? [OPERATOR: HADI MAJIBU MATATU YANARUHUSIWA] 1)Hakuna matatizo/wasiwasi 2)Ajira/ riziki [ukosefu au kutotosheleza] 3)Huduma za afya [ukosefu au kutotosheleza] 4)Usafiri [ukosefu au kutotosheleza] 5)Elimu [ukosefu au kutotosheleza] 6)Upatikanaji wa makazi au hifadhi [ukosefu au kutotosha] 7)Upatikanaji wa chakula na maji [ukosefu au kutotosheleza] 8) Usalama wa wanafamilia 9) Usalama wa ardhi au mali [kutosha au kutotosheleza] 10) Majanga ya asili [ukame / mafuriko / moto au mmomonyoko wa ardhi] 11) Ufisadi 12) Ukosefu wa utawala 13) Kupata msaada au kupokea msaada 14)Nyingine [taja] 15)SIJUE 16)KUKATALA | I93: =LEN(H93) | J93: Open Ended-Select All That Apply | K93: NA | L93: NA | M93: Form Type - Checklist 1,15,16 = IsNone MinAns = 1 MaxANs = 3 | N93: 1)confl_wb_none 2)confl_wb_livelihood 3)confl_wb_health 4)confl_wb_transport 5)confl_wb_edu 6)confl_wb_housing 7)confl_wb_food_water 8)confl_wb_safety 9)confl_wb_land_sec 10)confl_wb_nat_disaster 11)confl_wb_corrupt 12)confl_wb_fin_crisis 13)confl_wb_assistance 14)confl_wb_other 15)confl_wb_dk 16)confl_wb_ref | O93: 1-16 = confl_internal_relations | Q93: For any response, go to confl_internal_relations.
A94: 68 | B94: confl_internal_relations | C94: confl_internal_relations | D94: Could you describe the relations between members of your community? [OPERATOR: SINGLE RESPONSE.] 1)Excellent 2)Good 3)Neither good nor bad 4)Somewhat bad 5)Very bad 6)DON'T KNOW 7)REFUSED | E94: =LEN(D94) | F94: Pouvez-vous décrire les relations entre les membres de votre communauté ? [OPÉRATEUR : RÉPONSE UNIQUE.] 1)Excellentes 2)Bonnes 3)Ni bonnes ni mauvaises 4)Plutôt mauvaises 5)Très mauvaises 6)JE NE SAIS PAS 7)REFUS | G94: =LEN(F94) | H94: Je, unaweza kuelezea uhusiano kati ya wanajamii wako? [OPERATOR: JIBU MOJA.] 1) Bora 2) Nzuri 3) Sio nzuri au mbaya 4) Badala yake mbaya 5) mbaya sana 6)SIJUE 7)KUKATALA | I94: =LEN(H94) | J94: Single Choice | K94: NA | L94: NA | M94: Form Type - Buttons | N94: NA | O94: 1-7 = confl_external_relations | Q94: For any response, go to confl_external_relations.
A95: 69 | B95: confl_external_relations | C95: confl_external_relations | D95: Could you describe the relations between your community and nearby or neigbhouring communities? [OPERATOR: SINGLE RESPONSE.] 1)Excellent 2)Good 3)Neither good nor bad 4)Somewhat bad 5)Very bad 6)DON'T KNOW 7)REFUSED | E95: =LEN(D95) | F95: Pouvez-vous décrire les relations entre votre communauté et les communautés voisines ou proches ? [OPÉRATEUR : RÉPONSE UNIQUE.] 1)Excellentes 2)Bonnes 3)Ni bonnes ni mauvaises 4)Plutôt mauvaises 5)Très mauvaises 6)NE SAIT PAS 7)REFUSÉ | G95: =LEN(F95) | H95: Je, unaweza kuelezea uhusiano kati ya jamii yako na jamii za jirani au zinazokaribiana? [MPIGA KAZI: JIBU MOJA TU.] 1) Nzuri sana 2) Nzuri 3) Wala nzuri wala mbaya 4) Mbaya kidogo 5) Mbaya sana 6) Sijue 7) KUKATALA | I95: =LEN(H95) | J95: Single Choice | K95: NA | L95: NA | M95: Form Type - Buttons | N95: NA | O95: 1-7 = confl_yn | Q95: For any response, go to confl_yn.
A96: 70 | B96: confl_yn | C96: confl_yn | D96: Have you or anyone within your household been exposed to any form of insecurity or conflict during the past 12 months? [OPERATOR: SINGLE RESPONSE.] 1)YES 2)NO 3)DON'T KNOW 4)REFUSED | E96: =LEN(D96) | F96: Est-ce que vous ou un membre de votre ménage avez été exposé à une quelconque forme d'insécurité ou de conflit au cours des 12 derniers mois? [OPÉRATEUR/OPÉRATRICE: UNE SEULE RÉPONSE]. 1)OUI 2)NON 3)NE SAIT PAS 4)REFUSÉ | G96: =LEN(F96) | H96: Je, wewe au mtu yeyote katika kaya yako alikumbana na aina yoyote ya ukosefu wa usalama au migogoro katika kipindi cha miezi 12 iliyopita? [OPERATOR: JIBU MOJA TU] 1)NDIYO 2)HAPANA 3)SIJUE 4)KUKATALA | I96: =LEN(H96) | J96: Single Choice | K96: NA | L96: NA | M96: Form Type - Buttons | N96: NA | O96: 1 = confl_prim_insec 2-4 = confl_agri_imp | Q96: if confl_yn = 1, go to confl_prim_insec. Otherwise, go to confl_agri_imp.
A97: 71 | B97: confl_prim_insec | C97: confl_prim_insec | D97: What has been the primary type of insecurity affecting your household? [OPERATOR: SINGLE RESPONSE.] 1)Disputes or conflicts over land/ water/ pasture or fishing grounds 2)Criminality/ banditry or armed group violence 3)Conflict between community groups 4)Armed conflict 5)Disputes or conflicts over assistance being provided 6)Other [specify] 7)DON'T KNOW 8)REFUSED | E97: =LEN(D97) | F97: Quel a été le principal type d'insécurité affectant votre ménage? [OPÉRATEUR/OPÉRATRICE: UNE SEULE RÉPONSE]. 1)Disputes ou conflits concernant la terre/ l'eau/ les pâturages ou les zones de pêche 2)Criminalité/ banditisme ou violence de groupes armés 3)Conflit entre groupes communautaires 4)Conflit armé 5)Différends ou conflits concernant l'assistance fournie 6)Autre [préciser] 7)NE SAIT PAS 8)REFUS | G97: =LEN(F97) | H97: Ni aina gani kuu ya ukosefu wa usalama iliyoathiri kaya yako? [OPERATOR: JIBU MOJA TU]. 1)Migogoro au migogoro kuhusu ardhi/maji au malisho 2)Uhalifu/unyanyasaji wa magenge au ujambazi 3)Migogoro kati ya makundi ya jamii 4)Migogoro ya kutumia silaha 5)Mizozo au migogoro kuhusu usaidizi unaotolewa 6)Nyingine [taja] 7)SIJUE 8)KUKATALA | I97: =LEN(H97) | J97: Open Ended-Single Choice | K97: NA | L97: NA | M97: Form Type - RadioList | N97: NA | O97: 1-8 = confl_agri_imp | Q97: if confl_prim_insec = 1-8, go to confl_agri_imp.
A98: 72 | B98: confl_agri_imp | C98: confl_agri_imp 1)confl_agri_none 2)confl_agri_access_field 3)confl_agri_inputs 4)confl_agri_prod_asset 5)confl_agri_water_infra 6)confl_agri_crp_damage 7)confl_agri_crp_theft_occup 8)confl_agri_ls_reduce_mob 9)confl_agri_ls_damage 10)confl_agri_ls_theft 11)confl_agri_land_contam 12)confl_agri_extortion 13)confl_agri_other 14)confl_agri_dk 15)confl_agri_ref | D98: How has broader impacts of conflict or insecurity affected your household's farming, livestock or fishing activities? [OPERATOR: SELECT UP TO THREE IMPACTS.] 1)No effect on my household's agricultural activities 2)Unsafe to access fields or fishing areas [risk of violence / injury / theft] 3)Could not access [or poor quality] agricultural inputs 4)Damage or destruction of productive assets [tools/ machinery] 5)Reduced access to agricultural water / damage to irrigation infrastructure 6)Damage or destruction of crops 7)Theft/occupation of agricultural land 8)Reduced livestock mobility due to insecurity 9)Killing or injury of livestock 10)Theft of livestock 11)Land contaminated by landmines and/or explosive remnants of war 12)Demands for agricultural produce [livestock/ fish/ crops] as payment to influential groups 13)Other [specify] 14)DON'T KNOW 15)REFUSED | E98: =LEN(D98) | F98: Comment l'insécurité ou le conflit généralisé a-t-il affecté les activités agricoles, d'élevage ou de pêche de votre ménage? [OPÉRATEUR/OPÉRATRICE: SÉLECTIONNER JUSQU'À TROIS IMPACTS] 1)Aucune conséquence sur les activités agricoles de mon ménage 2)Accès dangereux aux champs ou zones de pêche 3)Impossibilité d'accéder aux intrants [semences/ engrais] ou mauvaise qualité de ceux-ci 4)Dommages ou destruction des biens de production [outils/ machines] 5)Accès réduit à l'eau agricole / dommages aux infrastructures d'irrigation 6)Dommages ou destruction des cultures 7)Vol/occupation de terres agricoles 8)Mobilité réduite du bétail en raison de l'insécurité 9)Meurtre ou blessure du bétail 10)Vol de bétail 11)Terres contaminées par des mines terrestres et/ou des restes explosifs de guerre 12)Exigences de produits agricoles [bétail/ récoltes/ poisson] comme paiement aux groupes influents 13)Autre [préciser] 14)NE SAIT PAS 15)REFUSÉ | G98: =LEN(F98) | H98: Je, ukosefu wa usalama na/au migogoro imeathiri vipi shughuli za kaya yako za kilimo, mifugo au uvuvi? [OPERATOR: CHAGUA HADI ATHARI TATU] 1)Hakuna madhara kwa shughuli za kilimo za kaya yangu 2)Kutokuwa na uwezo wa kufikia au kupunguza ufikiaji wa mashamba/maeneo ya uvuvi 3)Kutoweza kupata pembejeo [mbegu/mbolea] au ubora wake 4)Uharibifu au uharibifu wa mali ya uzalishaji [zana/mashine] 5)Uharibifu wa miundombinu ya majimaji na/au kupunguza upatikanaji wa maji 6) Uharibifu au uharibifu wa mazao 7) Wizi/ukaaji wa ardhi ya kilimo 8) Kupunguza uhamaji wa mifugo kwa sababu ya ukosefu wa usalama 9) Kufa au kuumia mifugo 10)Wizi wa mifugo 11)Ardhi iliyochafuliwa na mabomu na/au. mabaki ya vita 12)Unyang'anyi [k.m. malipo yanayodaiwa na vikundi vyenye silaha] 13)Nyingine [taja] 14)SIJUE 15)KUKATALA | I98: =LEN(H98) | J98: Open Ended-Select All That Apply | K98: NA | L98: Send if "hh_agricactivity" "Equals" "Yes - crop production" Or "hh_agricactivity" "Equals" "Yes - livestock production" Or "hh_agricactivity" "Equals" "Yes - both crop and livestock production" Or "hh_fish" "Equals" "YES" if not satisfied go to "confl_foodsec_imp" | M98: Form Type - Checklist 1,14,15 = IsNone MinAns = 1 MaxAns = 3 | N98: 1)confl_agri_none 2)confl_agri_access_field 3)confl_agri_inputs 4)confl_agri_prod_asset 5)confl_agri_water_infra 6)confl_agri_crp_damage 7)confl_agri_crp_theft_occup 8)confl_agri_ls_reduce_mob 9)confl_agri_ls_damage 10)confl_agri_ls_theft 11)confl_agri_land_contam 12)confl_agri_extortion 13)confl_agri_other 14)confl_agri_dk 15)confl_agri_ref | O98: 1-15 = confl_foodsec_imp | Q98: if confl_agri_imp = 1-15, go to confl_foodsec_imp.
A99: 73 | B99: confl_foodsec_imp | C99: confl_foodsec_imp 1)confl_fs_none 2)confl_fs_high_cost 3)confl_fs_lack_food_mkt 4)confl_fs_access_mkt 5)confl_fs_reduced_income 6)confl_fs_access_assistance 7)confl_fs_theft_damage 8)confl_fs_illicit_pay 9)confl_fs_other 10)confl_fs_dk 11)confl_fs_ref | D99: How has insecurity affected your household's access to food? [OPERATOR: SELECT UP TO THREE IMPACTS.] 1)No effect on my access to food 2)High food costs 3)Lack of food in the markets 4)Unsafe to access markets [risk of violence / injury / theft] 5)Reduced income to buy food 6)Difficult to access assistance [food/ cash or vouchers] 7)Theft/damage to household food stores 8)Demands for informal payments or taxes 9)Other [specify] 10)DON'T KNOW 11)REFUSED | E99: =LEN(D99) | F99: Comment l'insécurité a-t-elle impacté l'accès de votre ménage à la nourriture? [OPÉRATEUR/OPÉRATRICE: SÉLECTIONNER JUSQU'À TROIS IMPACTS]. 1)Aucun effet sur mon accès à la nourriture 2)Coût élevé de la nourriture 3)Manque de nourriture sur les marchés 4)Accès dangereux aux marchés [risque de violence / blessure / vol] 5)Revenu réduit pour acheter de la nourriture 6)Difficultés d'accès à l'aide [nourriture/ argent ou bons d'achat]. 7)Vol/dommages aux réserves alimentaires des ménages 8)Demandes de paiements informels ou de taxes 9)Autre [préciser] 10)NE SAIT PAS 11)REFUSÉ | G99: =LEN(F99) | H99: Je/ ukosefu wa usalama umeathiri vipi upatikanaji wa chakula wa kaya yako? [OPERATOR: CHAGUA HADI ATHARI TATU]. 1)Hakuna athari kwa upatikanaji wangu wa chakula 2)Gharama kubwa ya chakula 3)Ukosefu wa chakula sokoni 4)Upatikanaji mgumu/hatari kwenye soko 5)Kupunguza mapato ya kununua chakula 6)Ugumu wa kupata msaada [chakula/pesa au vocha] 7)Wizi/uharibifu wa akiba ya chakula cha kaya 8)Mahitaji ya malipo haramu au kodi 9)Nyingine [taja] 10)SIJUE 11)KUKATALA | I99: =LEN(H99) | J99: Open Ended-Select All That Apply | K99: NA | L99: NA | M99: Form Type - Checklist 1,10,11 = IsNone MaxAns = 1 MaxAns = 3 | N99: 1)confl_fs_none 2)confl_fs_high_cost 3)confl_fs_lack_food_mkt 4)confl_fs_access_mkt 5)confl_fs_reduced_income 6)confl_fs_access_assistance 7)confl_fs_theft_damage 8)confl_fs_illicit_pay 9)confl_fs_other 10)confl_fs_dk 11)confl_fs_ref | O99: 1-11 = crp_intro | Q99: if confl_foodsec_imp = 1-11, go to crp_intro.
A100: 74 | B100: crp_intro | C100: crp_intro | D100: We will now ask you some questions about crop production which apply to you and anyone in your household that is involved in crop production or sales. All questions refer to the crops grown during Rainy season. 1)CONTINUE | E100: =LEN(D100) | F100: Nous allons maintenant vous poser quelques questions sur la production végétale. Ces questions vous concernent ainsi que toute personne de votre ménage impliquée dans la production ou la vente de cultures. Toutes les questions se rapportent aux cultures pratiquées pendant la Saison des pluies. 1)CONTINUER | G100: =LEN(F100) | H100: Sasa tutakuuliza baadhi ya maswali kuhusu uzalishaji wa mazao ambayo yanakuhusu wewe na mtu yeyote katika kaya yako anayehusika na uzalishaji au mauzo ya mazao. Maswali yote yanahusu mazao yanayolimwa wakati wa Mvua. 1)ENDELEA | I100: =LEN(H100) | J100: Single Choice | K100: NA | L100: Send if "hh_agricactivity" "Equals" "Yes - crop production" Or "hh_agricactivity" "Equals" "Yes - both crop and livestock production" Or "income_main_crop_check" "Equals" "YES" Or "income_sec_crop_check" "Equals" "YES" Or "income_third_crop_check" "Equals" "YES" if not satisfied go to "crp_salesmain" | M100: Form Type - Buttons | N100: NA | O100: 1 = crp_landsize_num | Q100: If hh_agricactivity = "Yes - crop production" or "Yes - both crop and livestock production" or if they reported production and sales of crops in one of the three main income sources and confirmed that they are involved in production, then this section will be asked to respondents. Otherwise, skip to crp_salesmain. Next question is crp_landsize_num | T100: ='Additional information'!$D$17 | W100: yes | AA100: 7.3040729 | AB100: =IF(AA100="","",AA100*T100) | AC100: =IF(W100="yes",AB100,"")
...

Sheet Crop list
C3: Select top 10 crops | D3: GeoPoll code | E3: Dataset code | F3: Label (EN) | G3: Label (FR)
C4: x | D4: {=_xlfn.SEQUENCE(90,1,1,1)} | E4: 1.1 | F4: Rice | G4: Riz
D5: 2 | E5: 1.2 | F5: Wheat | G5: Blé
C6: x | D6: 3 | E6: 1.3 | F6: Millet | G6: Mil
C7: x | D7: 4 | E7: 1.4 | F7: Sorghum | G7: Sorgho
C8: x | D8: 5 | E8: 1.5 | F8: Maize | G8: Maïs
D9: 6 | E9: 1.6 | F9: Barley | G9: Orge
D10: 7 | E10: 1.99 | F10: Other Cereal | G10: Autres céréales
C11: x | D11: 8 | E11: 2.1 | F11: Cassava | G11: Manioc
C12: x | D12: 9 | E12: 2.2 | F12: Potatoe | G12: Pommes de terre
D13: 10 | E13: 2.3 | F13: Sweet Potatoes | G13: Patates douces
D14: 11 | E14: 2.4 | F14: Yams | G14: Ignames
D15: 12 | E15: 2.5 | F15: Carrots | G15: Carottes
D16: 13 | E16: 2.6 | F16: Cocoyam | G16: Chou caraïbe
D17: 14 | E17: 2.99 | F17: Other tubers | G17: Autres tubercules
C18: x | D18: 15 | E18: 3.1 | F18: Beans | G18: Haricots
D19: 16 | E19: 3.2 | F19: Lentils | G19: Lentilles
D20: 17 | E20: 3.3 | F20: Peas | G20: Pois
C21: x | D21: 18 | E21: 3.4 | F21: Soybeans | G21: Soja
D22: 19 | E22: 3.5 | F22: Chickpeas | G22: Pois chiches
D23: 20 | E23: 3.6 | F23: Fava beans | G23: Fève
D24: 21 | E24: 3.7 | F24: Broad beans | G24: Fève large
D25: 22 | E25: 3.99 | F25: Other pulses | G25: Autres légumineuses
D26: 23 | E26: 4.1 | F26: Cabbage | G26: Choux
D27: 24 | E27: 4.2 | F27: Lettuce | G27: Laitue
D28: 25 | E28: 4.3 | F28: Spinach-Amaranth | G28: Epinards-Amaranthe
D29: 26 | E29: 4.4 | F29: Cassava leaves | G29: Feuilles de manioc
D30: 27 | E30: 4.5 | F30: Potatoe leaves | G30: Feuilles de pomme de terre
D31: 28 | E31: 4.6 | F31: Moringa | G31: Moringa
D32: 29 | E32: 4.7 | F32: Sorrel Hibiscus / Rosselle | G32: Oseille Hibiscus / Rosselle
D33: 30 | E33: 4.9 | F33: Green salad herbs [thyme, parsley, mint, rocca, other] | G33: Herbes aromatiques [thym, persil, menthe, rocca, autres]
... D53: 50 | E53: 7.1 | F53: Sweet Banana | G53: Banane douce
C54: x | D54: 51 | E54: 7.2 | F54: Plantains | G54: Banane plantain
C55: x | D55: 52 | E55: 7.3 | F55: Papaya | G55: Papaye
D56: 53 | E56: 7.4 | F56: Mango | G56: Mangue
D57: 54 | E57: 7.5 | F57: Guava | G57: Goyave
D58: 55 | E58: 7.6 | F58: Pineapple | G58: Ananas
D59: 56 | E59: 7.7 | F59: Avocado | G59: Avocat
D60: 57 | E60: 7.8 | F60: Water Melon | G60: Pastèques
D61: 58 | E61: 7.9 | F61: Dates | G61: Dattes
D62: 59 | E62: 7.101 | F62: Figs | G62: Figues
D63: 60 | E63: 7.11 | F63: Grapes | G63: Raisins
D64: 61 | E64: 7.12 | F64: Olives | G64: Olives
D65: 62 | E65: 7.13 | F65: Apple | G65: Pomme
D66: 63 | E66: 7.14 | F66: Apricot | G66: Abricot
D67: 64 | E67: 7.15 | F67: Cherries | G67: Cerises
... D72: 69 | E72: 8.1 | F72: Coconuts | G72: Noix de coco
C73: x | D73: 70 | E73: 8.2 | F73: Groundnut/peanut | G73: Arachide / cacahuète
D74: 71 | E74: 8.3 | F74: Cashew Nut | G74: Noix de cajou
D75: 72 | E75: 8.4 | F75: Kola Nut | G75: Noix de kola
D76: 73 | E76: 8.5 | F76: Sesame | G76: Sésame
D77: 74 | E77: 8.6 | F77: Bambara nut | G77: Noix de bambara
D78: 75 | E78: 8.7 | F78: Almond | G78: Amande
D79: 76 | E79: 8.8 | F79: Walnut | G79: Noix
D80: 77 | E80: 8.99 | F80: Other nuts | G80: Autres fruits à coque
D81: 78 | E81: 9.1 | F81: Cocoa | G81: Cacao
C82: x | D82: 79 | E82: 9.2 | F82: Coffee | G82: Café
D83: 80 | E83: 9.3 | F83: Tea | G83: Thé
D84: 81 | E84: 9.4 | F84: Sugarcane | G84: Canne à sucre
D85: 82 | E85: 9.5 | F85: Sunflower | G85: Tournesol
D86: 83 | E86: 9.99 | F86: Other food cash crop | G86: Autres cultures vivrières de rente
D87: 84 | E87: 10.1 | F87: Cotton | G87: Coton
D88: 85 | E88: 10.2 | F88: Rubber | G88: Caoutchouc
D89: 86 | E89: 10.3 | F89: Jute | G89: Jute
D90: 87 | E90: 10.4 | F90: Fodder | G90: Fourrage
D91: 88 | E91: 10.5 | F91: Tobacco | G91: Tabac
D92: 89 | E92: 10.6 | F92: Qat | G92: Qat
D93: 90 | E93: 10.99 | F93: Other non-food cash crop | G93: Autre culture de rente non alimentaire

Sheet Additional information
C2: Original | D2: Replacement (EN) | E2: Replacement (FR) | F2: Comment (EN) | G2: Commentaire (FR) | H2: Examples (EN) | I2: Exemples (FR)
B3: FOR CORE QUESTIONS . (Mandatory to fill out) . | C3: ADMIN1 | E3: Province | F3: The first subdivision of the country, after national level; region; province; governorate; etc. | G3: La première subdivision du pays, après le niveau national ; par exemple, région ; province ; gouvernorat ; etc. | H3: region | I3: region
C4: ADMIN2 | E4: Territoire | F4: The second subdivision of the country; district; municipality; LGA; etc. | G4: La deuxième subdivision du pays ; par exemple, district, municipalité, LGA, etc. | H4: district | I4: district
C5: reference year | D5: last year | E5: l'année dernière | F5: Comparison questions will need need a reference year. Select whether you want to use "last year" or "a normal year" as a baseline. A "normal year" should refers to an average year from the past 5 years - make sure to train the enumerators accordingly. | G5: Les questions de comparaison auront besoin d'une année de référence. Choisissez si vous voulez utiliser "l'année dernière" ou "une année normale" comme année de référence. Une "année normale" doit correspondre à une année moyenne des 5 dernières années - veillez à former les recenseurs en conséquence. | H5: a normal year | I5: une année normale
C6: season | D6: Rainy season | E6: Saison des pluies | F6: Name the crop season(s) of interest if there are several cropping seasons in the country (e.g. Meher and Belg in Ethiopia, rainy season / flood-recession cropping / irrigated dry season in the Sahel). You can refer to the “last season” or “ongoing season". | G6: Nommez la ou les saisons culturales concernée(s) en ANGLAIS s'il y en a plusieurs dans le pays (par exemple, Meher et Belg en Ethiopie, saison des pluies / cultures de décrue / saison sèche irriguée au Sahel). Vous pouvez vous référer à la "dernière saison" ou "saison actuelle". | H6: wet season | I6: saison des pluies
C7: season phase | D7: =IF(E7="Pas encore en saison","Not yet in season",IF(E7="Préparation du terrain","Land preparation",IF(E7="Semis / plantation","Planting",IF(E7="Début de la croissance","Early growing",IF(E7="Croissance","Growing",IF(E7="Proche de la récolte","Maturing",IF(E7="Récolte","Harvesting",IF(E7="Post-récolte","Recently finished","")))))))) | E7: Proche de la récolte | F7: Indicate the phase of the season at the time of data collection. If the harvest from the season has not yet occurred, the question on crop harvest (crp_harv_change) will include the word “expected” (where #expected or nothing# is located). If the harvest has occured, "expected" will not be inserted in the question. | G7: Indiquez le stade de la saison culturale au moment de la collecte des données. Si la récolte de la saison n'a pas encore eu lieu, la question sur la récolte des cultures (crp_harv_change) inclura le mot "attendue" (là où se trouve #attendue ou rien#). Si la récolte a eu lieu, "attendue" ne sera pas inséré dans la question. | H7: Harvesting | I7: Récolte
C8: local measurement unit | F8: Specify the local measurement unit for land size, other than acres, hectares, square meters and square feet. If no other unit of measurement is needed, keep this cell blank. | G8: Indiquez l'unité utilisée localement pour mesurer la taille des terrains, autre que les acres, les hectares, les mètres carrés et les pieds carrés. Si aucune autre unité de mesure n'est nécessaire, garder cette cellule vide. | H8: Jeribs | I8: Jeribs
C9: local measurement unit conversion | D9: =IF(E9<>"",E9,"") | F9: Include the conversion of the local measurement unit to hectares. In other words, how many local measurement units are in 1 ha. | G9: Indiquez la conversion de l'unité de mesure locale en hectares. En d'autres termes, indiquez combien d'unités de mesure locales y a-t-il dans 1 ha. | H9: 0.2 | I9: 0.2
B10: FOR OPTIONAL QUESTIONS . (Fill out if applicable) . | C10: currency | E10: CDF | F10: The name of the main currency used nationally; USD; Naira; Rial; Pesos; etc. | G10: Nom de la principale devise utilisée au niveau national; par exemple, USD; Naira; Rial; Pesos; etc. | H10: Naira | I10: Naira
C11: MIN AMOUNT | E11: 0 | F11: The minimum amount for an income source should be set at 0 or any value below which it is not possible to do a transaction. For example, the smallest coin/banknote in a currency can be 1000, in which case you would set the minimum at 1000. Provide this input in the same currency as specified above. Only digits should be inputted. | G11: Le montant minimum d'une source de revenu doit être fixé à 0 ou à toute valeur en dessous de laquelle il n'est pas possible d'effectuer une transaction. Par exemple, la plus petite pièce/billet d'une devise peut être de 1000, auquel cas vous fixerez le minimum à 1000. Cette saisie doit être effectuée dans la même devise que celle spécifiée ci-dessus. Seuls des chiffres doivent être saisis. | H11: 5 | I11: 5
C12: MAX AMOUNT | E12: 10000000 | F12: Set the maximum amount for an income source over 3 months. Enumerators will not be able to input values above this amount in questions related to income amounts. Using previous representative surveys for this population, you can estimate this amount by using the mean income plus five (5) standard deviations, unless the country has high inflation. In the latter case, set the maximum value based on your country context (higher than the proposed approach). Provide this input in the same currency as specified above. Only digits should be inputted. | G12: Fixez le montant maximum pouvant être généré par une source de revenu sur 3 mois. Il ne sera pas possible pour les enquêteurs d'entrer des valeurs supérieures à ce montant dans les questions relatives aux montants des revenus. En vous basant sur des enquêtes précédentes représentatives de cette population, vous pouvez estimer ce montant en utilisant le revenu moyen plus cinq (5) écarts types, sauf si le pays connaît une forte inflation. Dans ce dernier cas, fixez la valeur maximale en fonction du contexte de votre pays (plus élevée que l'approche proposée). Cette saisie doit être effectuée dans la même devise que celle spécifiée ci-dessus. Seuls des chiffres doivent être saisis. | H12: 5000000 | I12: 5000000
C13: THRESHOLD | E13: 2000000 | F13: The threshold salary should be calculated to flag outliers (responses that look suspiciously high). Using previous representative surveys for this population, a good estimate is the average plus three (3) standard deviations, which should give the threshold for the 3 or 4% highest income values. Provide this input in the same currency as specified above. Only digits should be inputted. | G13: Le salaire seuil doit être calculé pour signaler les valeurs aberrantes (réponses qui semblent suspectes). En utilisant des enquêtes précédentes représentatives de cette population, une bonne estimation est la moyenne plus deux écarts types, ce qui devrait dégager le seuil pour les 3 ou 4% des valeurs de revenu les plus élevées. Cette saisie doit être effectuée dans la même devise que celle spécifiée ci-dessus. Seuls des chiffres doivent être saisis. | H13: 1200000 | I13: 1200000
C14: local vegetables | D14: Funbwa, spinach, cabbage, carrot | E14: Fumbwa, épinard, choux, carottes | F14: Input some common local vegetables [to be used as examples in the food consumption score indicator]. | G14: Saisissez quelques légumes locaux courants [à utiliser comme exemples dans l'indicateur de score de consommation alimentaire]. | H14: eggplants, zucchini, cauliflower | I14: aubergines, courgettes, choux-fleurs
C15: local fruits | D15: bananas, oranges, mangos | E15: bananes, oranges, mangues | F15: Input some common local fruits [to be used as examples in the food consumption score indicator]. | G15: Indiquez quelques fruits locaux courants [à utiliser comme exemples dans l'indicateur de score de consommation alimentaire]. | H15: apples, bananas, oranges | I15: pommes, bananes, oranges
B17: FILL OUT FOR QUESTIONNAIRE DURATION ESTIMATION . | C17: Expected percentage of respondents cultivating crops | D17: =IF(E17="","",E17) | E17: 0.75 | F17: If the survey is representative and has no quotas, write the proportion of rural households cultivating crops at country level, or if the survey follows a previous round with identical sample design, just report the percentage from the previous round. If you are using quotas, calculate the ratio of the quota over the minimum sample size at the level where the quota is implemented (so if you have a minimum sample size per strata of 110 with a quota of 100 crop producers, then it's 100/110 = 91% (the maximum you should write is 100%). | G17: Si l'enquête est représentative et ne comporte pas de quotas, écrivez la proportion de ménages ruraux impliqués dans les cultures au niveau du pays, ou si l'enquête suit un cycle précédent avec un plan d'échantillonnage identique, indiquez simplement le pourcentage du cycle précédent. Si vous utilisez des quotas, calculez le rapport entre le quota et la taille minimale de l'échantillon au niveau où le quota est appliqué (ainsi, si vous avez une taille minimale d'échantillon par strate de 110 avec un quota de 100 producteurs de cultures, alors c'est 100/110 = 91% (le maximum que vous devez écrire est 100%). | H17: 0.91 | I17: 0.91
C18: Expected percentage of respondents raising livestock | D18: =IF(E18="","",E18) | E18: 0.2 | F18: If the survey is representative and has no quotas, write the proportion of rural households raising livestock at country level, or if the survey follows a previous round with identical sample design, just report the percentage from the previous round. If you are using quotas, calculate the ratio of the quota over the minimum sample size at the level where the quota is implemented (so if you have a minimum sample size of 110 but a quota of 100 livestock producers, then it's 100/110 = 91% (the maximum you should write is 100%) | G18: Si l'enquête est représentative et ne comporte pas de quotas, écrivez la proportion de ménages ruraux impliqués dans l'élevage, ou si l'enquête suit un cycle précédent avec un plan d'échantillonnage identique, indiquez simplement le pourcentage du cycle précédent. Si vous utilisez des quotas, calculez le rapport entre le quota et la taille minimale de l'échantillon au niveau où le quota est appliqué (ainsi, si vous avez une taille minimale d'échantillon par strate de 110 avec un quota de 100 éleveurs, alors c'est 100/110 = 91% (le maximum que vous devez écrire est 100%). | H18: 0.91 | I18: 0.91
C19: Expected percentage of respondents involved in fishery | D19: =IF(E19="","",E19) | E19: 0.05 | F19: If the survey is representative and has no quotas, write the proportion of rural households involved in fisheries or aquaculture, otherwise if you are using quotas, calculate the ratio of the quota over the sample size at the level where the quota is implemented. (so if you haven't set a quota, and you expect to have a representative proportion of fishermen, just write the percentage of fishermen in the population you are targeting, in the example to the right, 5%) | G19: Si l'enquête est représentative et ne comporte pas de quotas, écrivez la proportion de ménages ruraux impliqués dans la pêche ou l'aquaculture; sinon, si vous utilisez des quotas, calculez le rapport entre le quota et la taille de l'échantillon au niveau où le quota est appliqué (ainsi, si vous n'avez pas fixé de quota, et que vous pensez avoir une proportion représentative de pêcheurs, écrivez simplement le pourcentage de pêcheurs dans la population que vous ciblez, dans l'exemple à droite, 5%). | H19: 0.05 | I19: 0.05
